{
"meta":{"test_sets":[],"test_metrics":[],"learn_metrics":[{"best_value":"Min","name":"Logloss"}],"launch_mode":"Train","parameters":"","iteration_count":987,"learn_sets":["learn"],"name":"experiment"},
"iterations":[
{"learn":[0.673253891],"iteration":0,"passed_time":0.1893982825,"remaining_time":186.7467066},
{"learn":[0.6545199907],"iteration":1,"passed_time":0.2388926361,"remaining_time":117.6546233},
{"learn":[0.6362746568],"iteration":2,"passed_time":0.2838139773,"remaining_time":93.09098455},
{"learn":[0.6198712743],"iteration":3,"passed_time":0.338551835,"remaining_time":83.19911345},
{"learn":[0.604442289],"iteration":4,"passed_time":0.3476565685,"remaining_time":68.27975005},
{"learn":[0.589825445],"iteration":5,"passed_time":0.3578860178,"remaining_time":58.51436391},
{"learn":[0.5750175686],"iteration":6,"passed_time":0.4084965455,"remaining_time":57.18951636},
{"learn":[0.5613658908],"iteration":7,"passed_time":0.4639266773,"remaining_time":56.77302714},
{"learn":[0.5486590922],"iteration":8,"passed_time":0.5159262748,"remaining_time":56.06398853},
{"learn":[0.5366045412],"iteration":9,"passed_time":0.5749199404,"remaining_time":56.16967817},
{"learn":[0.5245632013],"iteration":10,"passed_time":0.6271676412,"remaining_time":55.64687435},
{"learn":[0.513279792],"iteration":11,"passed_time":0.6804349674,"remaining_time":55.2853411},
{"learn":[0.5022547173],"iteration":12,"passed_time":0.7304261819,"remaining_time":54.72577701},
{"learn":[0.4923485598],"iteration":13,"passed_time":0.7864965585,"remaining_time":54.66151081},
{"learn":[0.4828806615],"iteration":14,"passed_time":0.8405467532,"remaining_time":54.4674296},
{"learn":[0.4738160349],"iteration":15,"passed_time":0.8944625396,"remaining_time":54.28269537},
{"learn":[0.4647087324],"iteration":16,"passed_time":0.9497513612,"remaining_time":54.19169532},
{"learn":[0.4565494292],"iteration":17,"passed_time":1.005159384,"remaining_time":54.11108015},
{"learn":[0.4478930691],"iteration":18,"passed_time":1.060606778,"remaining_time":54.03512424},
{"learn":[0.4401700132],"iteration":19,"passed_time":1.12473613,"remaining_time":54.38099187},
{"learn":[0.4329040057],"iteration":20,"passed_time":1.183830564,"remaining_time":54.45620597},
{"learn":[0.4260784674],"iteration":21,"passed_time":1.239436411,"remaining_time":54.36618803},
{"learn":[0.419591917],"iteration":22,"passed_time":1.292002175,"remaining_time":54.15174332},
{"learn":[0.4131864304],"iteration":23,"passed_time":1.346937446,"remaining_time":54.04586504},
{"learn":[0.4072217421],"iteration":24,"passed_time":1.398352205,"remaining_time":53.80859286},
{"learn":[0.401148353],"iteration":25,"passed_time":1.45060503,"remaining_time":53.61659361},
{"learn":[0.3957283666],"iteration":26,"passed_time":1.500371878,"remaining_time":53.34655567},
{"learn":[0.3905496564],"iteration":27,"passed_time":1.555335786,"remaining_time":53.27025067},
{"learn":[0.3854842392],"iteration":28,"passed_time":1.610968619,"remaining_time":53.21751506},
{"learn":[0.3810685975],"iteration":29,"passed_time":1.664113853,"remaining_time":53.0852319},
{"learn":[0.3766085573],"iteration":30,"passed_time":1.716905853,"remaining_time":52.94716113},
{"learn":[0.3733432449],"iteration":31,"passed_time":1.72016781,"remaining_time":51.33625807},
{"learn":[0.3693615228],"iteration":32,"passed_time":1.777134215,"remaining_time":51.37533457},
{"learn":[0.3654554833],"iteration":33,"passed_time":1.831032704,"remaining_time":51.3227696},
{"learn":[0.3614693071],"iteration":34,"passed_time":1.882068544,"remaining_time":51.1922644},
{"learn":[0.3572770565],"iteration":35,"passed_time":1.935744743,"remaining_time":51.13592362},
{"learn":[0.3535010492],"iteration":36,"passed_time":1.994165409,"remaining_time":51.20154429},
{"learn":[0.3496249898],"iteration":37,"passed_time":2.045803562,"remaining_time":51.0912521},
{"learn":[0.3466772188],"iteration":38,"passed_time":2.097829454,"remaining_time":50.99339288},
{"learn":[0.3434443315],"iteration":39,"passed_time":2.152998529,"remaining_time":50.97224017},
{"learn":[0.3406312179],"iteration":40,"passed_time":2.197101784,"remaining_time":50.69410457},
{"learn":[0.3375865608],"iteration":41,"passed_time":2.248650525,"remaining_time":50.5946368},
{"learn":[0.3344912879],"iteration":42,"passed_time":2.297336898,"remaining_time":50.43455887},
{"learn":[0.3319176835],"iteration":43,"passed_time":2.316587695,"remaining_time":49.64868628},
{"learn":[0.3294491863],"iteration":44,"passed_time":2.361154548,"remaining_time":49.42683522},
{"learn":[0.3274543994],"iteration":45,"passed_time":2.370316164,"remaining_time":48.48842413},
{"learn":[0.3247260078],"iteration":46,"passed_time":2.413948432,"remaining_time":48.27896864},
{"learn":[0.3222758323],"iteration":47,"passed_time":2.461052939,"remaining_time":48.14434811},
{"learn":[0.3200097503],"iteration":48,"passed_time":2.512841914,"remaining_time":48.10297378},
{"learn":[0.3178795968],"iteration":49,"passed_time":2.56581047,"remaining_time":48.08328821},
{"learn":[0.3155845218],"iteration":50,"passed_time":2.618573778,"remaining_time":48.05853052},
{"learn":[0.31326629],"iteration":51,"passed_time":2.674444782,"remaining_time":48.08857444},
{"learn":[0.3111469064],"iteration":52,"passed_time":2.731442906,"remaining_time":48.13523914},
{"learn":[0.3094598308],"iteration":53,"passed_time":2.786368007,"remaining_time":48.14224723},
{"learn":[0.3072278675],"iteration":54,"passed_time":2.844433785,"remaining_time":48.20022341},
{"learn":[0.3056406594],"iteration":55,"passed_time":2.898264225,"remaining_time":48.18364275},
{"learn":[0.3033437894],"iteration":56,"passed_time":2.944258031,"remaining_time":48.0378942},
{"learn":[0.3016004429],"iteration":57,"passed_time":3.000199189,"remaining_time":48.05491459},
{"learn":[0.2994488161],"iteration":58,"passed_time":3.054359817,"remaining_time":48.0414561},
{"learn":[0.2974894115],"iteration":59,"passed_time":3.105628464,"remaining_time":47.98195977},
{"learn":[0.2955776344],"iteration":60,"passed_time":3.161879478,"remaining_time":47.99836715},
{"learn":[0.2937159769],"iteration":61,"passed_time":3.215664787,"remaining_time":47.97564399},
{"learn":[0.2924386418],"iteration":62,"passed_time":3.262618951,"remaining_time":47.85174461},
{"learn":[0.2910610089],"iteration":63,"passed_time":3.313442746,"remaining_time":47.7860571},
{"learn":[0.2901315382],"iteration":64,"passed_time":3.316999313,"remaining_time":47.05035949},
{"learn":[0.2887242748],"iteration":65,"passed_time":3.365344491,"remaining_time":46.96185267},
{"learn":[0.2872993676],"iteration":66,"passed_time":3.418798389,"remaining_time":46.9446943},
{"learn":[0.2858025064],"iteration":67,"passed_time":3.465504058,"remaining_time":46.83526808},
{"learn":[0.2836010896],"iteration":68,"passed_time":3.513166967,"remaining_time":46.7403953},
{"learn":[0.2824064194],"iteration":69,"passed_time":3.568639203,"remaining_time":46.74917356},
{"learn":[0.2806934349],"iteration":70,"passed_time":3.61874053,"remaining_time":46.68684966},
{"learn":[0.2794840225],"iteration":71,"passed_time":3.664450975,"remaining_time":46.56906447},
{"learn":[0.2781203275],"iteration":72,"passed_time":3.713556967,"remaining_time":46.49576805},
{"learn":[0.277110014],"iteration":73,"passed_time":3.767328722,"remaining_time":46.48069085},
{"learn":[0.2757406386],"iteration":74,"passed_time":3.820915118,"remaining_time":46.46232783},
{"learn":[0.2741255511],"iteration":75,"passed_time":3.868076094,"remaining_time":46.36601739},
{"learn":[0.2728602481],"iteration":76,"passed_time":3.910259305,"remaining_time":46.21215542},
{"learn":[0.2711621843],"iteration":77,"passed_time":3.954936651,"remaining_time":46.09022328},
{"learn":[0.2699743408],"iteration":78,"passed_time":4.00610077,"remaining_time":46.04480378},
{"learn":[0.2686514911],"iteration":79,"passed_time":4.06120561,"remaining_time":46.04391861},
{"learn":[0.2676346117],"iteration":80,"passed_time":4.106443099,"remaining_time":45.93132652},
{"learn":[0.265954699],"iteration":81,"passed_time":4.160377347,"remaining_time":45.91635974},
{"learn":[0.264478356],"iteration":82,"passed_time":4.20640231,"remaining_time":45.8143095},
{"learn":[0.2628667943],"iteration":83,"passed_time":4.251959124,"remaining_time":45.70856058},
{"learn":[0.2617700466],"iteration":84,"passed_time":4.296166667,"remaining_time":45.58990981},
{"learn":[0.2607324557],"iteration":85,"passed_time":4.342103984,"remaining_time":45.49111267},
{"learn":[0.2597518572],"iteration":86,"passed_time":4.389265701,"remaining_time":45.40619691},
{"learn":[0.2586933497],"iteration":87,"passed_time":4.437108816,"remaining_time":45.3291003},
{"learn":[0.2572981692],"iteration":88,"passed_time":4.476489818,"remaining_time":45.16727929},
{"learn":[0.2560284474],"iteration":89,"passed_time":4.527597397,"remaining_time":45.12505406},
{"learn":[0.2549443399],"iteration":90,"passed_time":4.579386353,"remaining_time":45.08934255},
{"learn":[0.2541748407],"iteration":91,"passed_time":4.633229424,"remaining_time":45.07326451},
{"learn":[0.2521534017],"iteration":92,"passed_time":4.674884428,"remaining_time":44.93921159},
{"learn":[0.2513938303],"iteration":93,"passed_time":4.72583629,"remaining_time":44.89544476},
{"learn":[0.2500985544],"iteration":94,"passed_time":4.775627403,"remaining_time":44.84062783},
{"learn":[0.2489719061],"iteration":95,"passed_time":4.81816191,"remaining_time":44.71856522},
{"learn":[0.2476459588],"iteration":96,"passed_time":4.864000421,"remaining_time":44.62845747},
{"learn":[0.2465140394],"iteration":97,"passed_time":4.909992994,"remaining_time":44.54065073},
{"learn":[0.2452187363],"iteration":98,"passed_time":4.962944528,"remaining_time":44.51610849},
{"learn":[0.2442809447],"iteration":99,"passed_time":5.016914945,"remaining_time":44.50003556},
{"learn":[0.2432796911],"iteration":100,"passed_time":5.071192323,"remaining_time":44.48590493},
{"learn":[0.2424789196],"iteration":101,"passed_time":5.120148443,"remaining_time":44.42481738},
{"learn":[0.2408698748],"iteration":102,"passed_time":5.172148953,"remaining_time":44.39009392},
{"learn":[0.2396966602],"iteration":103,"passed_time":5.214536049,"remaining_time":44.27341665},
{"learn":[0.2386328203],"iteration":104,"passed_time":5.259949156,"remaining_time":44.18357291},
{"learn":[0.2376147427],"iteration":105,"passed_time":5.308901037,"remaining_time":44.12397937},
{"learn":[0.2368565394],"iteration":106,"passed_time":5.364406455,"remaining_time":44.11848299},
{"learn":[0.2359781249],"iteration":107,"passed_time":5.409628199,"remaining_time":44.02836285},
{"learn":[0.2350433416],"iteration":108,"passed_time":5.462010915,"remaining_time":43.99674847},
{"learn":[0.2340661665],"iteration":109,"passed_time":5.507581985,"remaining_time":43.9104491},
{"learn":[0.2329561438],"iteration":110,"passed_time":5.550075564,"remaining_time":43.80059634},
{"learn":[0.2320825091],"iteration":111,"passed_time":5.601188676,"remaining_time":43.75928653},
{"learn":[0.2311605077],"iteration":112,"passed_time":5.643712931,"remaining_time":43.65137258},
{"learn":[0.2304044436],"iteration":113,"passed_time":5.695237382,"remaining_time":43.61352837},
{"learn":[0.2289477384],"iteration":114,"passed_time":5.744833057,"remaining_time":43.56082109},
{"learn":[0.2281634737],"iteration":115,"passed_time":5.79637473,"remaining_time":43.52277922},
{"learn":[0.2275948857],"iteration":116,"passed_time":5.843241909,"remaining_time":43.44974753},
{"learn":[0.2265931813],"iteration":117,"passed_time":5.884232195,"remaining_time":43.33387947},
{"learn":[0.2256088681],"iteration":118,"passed_time":5.935456813,"remaining_time":43.29392028},
{"learn":[0.2251641351],"iteration":119,"passed_time":5.985075675,"remaining_time":43.24217176},
{"learn":[0.2245248466],"iteration":120,"passed_time":6.033725699,"remaining_time":43.18352442},
{"learn":[0.2234413672],"iteration":121,"passed_time":6.08363885,"remaining_time":43.13399676},
{"learn":[0.2223795639],"iteration":122,"passed_time":6.137685355,"remaining_time":43.11349713},
{"learn":[0.2219123244],"iteration":123,"passed_time":6.183498754,"remaining_time":43.03515665},
{"learn":[0.2216931611],"iteration":124,"passed_time":6.18562934,"remaining_time":42.65609993},
{"learn":[0.2205708648],"iteration":125,"passed_time":6.231686222,"remaining_time":42.58318919},
{"learn":[0.2195359386],"iteration":126,"passed_time":6.285908082,"remaining_time":42.56599174},
{"learn":[0.2184646388],"iteration":127,"passed_time":6.336844978,"remaining_time":42.52617059},
{"learn":[0.2175782272],"iteration":128,"passed_time":6.393328277,"remaining_time":42.52306715},
{"learn":[0.2169498205],"iteration":129,"passed_time":6.44583891,"remaining_time":42.49295343},
{"learn":[0.2162449855],"iteration":130,"passed_time":6.483755847,"remaining_time":42.36713744},
{"learn":[0.2154629023],"iteration":131,"passed_time":6.531470404,"remaining_time":42.30611512},
{"learn":[0.2147099805],"iteration":132,"passed_time":6.579722301,"remaining_time":42.2487432},
{"learn":[0.214314428],"iteration":133,"passed_time":6.629594781,"remaining_time":42.20182349},
{"learn":[0.2126428309],"iteration":134,"passed_time":6.678925239,"remaining_time":42.15143928},
{"learn":[0.2121865325],"iteration":135,"passed_time":6.733760999,"remaining_time":42.13551919},
{"learn":[0.211504705],"iteration":136,"passed_time":6.787967481,"remaining_time":42.1151267},
{"learn":[0.2111160381],"iteration":137,"passed_time":6.839676919,"remaining_time":42.07888191},
{"learn":[0.2101498049],"iteration":138,"passed_time":6.895426492,"remaining_time":42.06706234},
{"learn":[0.2095562788],"iteration":139,"passed_time":6.945568549,"remaining_time":42.02068972},
{"learn":[0.2086925272],"iteration":140,"passed_time":6.995499194,"remaining_time":41.97299517},
{"learn":[0.2084063846],"iteration":141,"passed_time":6.998829801,"remaining_time":41.64796607},
{"learn":[0.2077266102],"iteration":142,"passed_time":7.048106145,"remaining_time":41.59861249},
{"learn":[0.2057401273],"iteration":143,"passed_time":7.096529317,"remaining_time":41.54426537},
{"learn":[0.2050838243],"iteration":144,"passed_time":7.153558407,"remaining_time":41.53997365},
{"learn":[0.2044659954],"iteration":145,"passed_time":7.204604272,"remaining_time":41.50049447},
{"learn":[0.2038731033],"iteration":146,"passed_time":7.258944104,"remaining_time":41.4796806},
{"learn":[0.2033312991],"iteration":147,"passed_time":7.307727879,"remaining_time":41.42691683},
{"learn":[0.2023359255],"iteration":148,"passed_time":7.36115268,"remaining_time":41.40030836},
{"learn":[0.202030094],"iteration":149,"passed_time":7.415581266,"remaining_time":41.37894347},
{"learn":[0.2012904402],"iteration":150,"passed_time":7.463258661,"remaining_time":41.31976318},
{"learn":[0.2007032037],"iteration":151,"passed_time":7.520431929,"remaining_time":41.31289908},
{"learn":[0.1997335344],"iteration":152,"passed_time":7.567055485,"remaining_time":41.24787107},
{"learn":[0.1992326443],"iteration":153,"passed_time":7.614419945,"remaining_time":41.1870897},
{"learn":[0.1988603648],"iteration":154,"passed_time":7.620135838,"remaining_time":40.90292269},
{"learn":[0.1979153457],"iteration":155,"passed_time":7.692674572,"remaining_time":40.9782857},
{"learn":[0.1975969977],"iteration":156,"passed_time":7.753768408,"remaining_time":40.99125973},
{"learn":[0.1970774112],"iteration":157,"passed_time":7.804619231,"remaining_time":40.9495528},
{"learn":[0.1966883576],"iteration":158,"passed_time":7.854866268,"remaining_time":40.9045866},
{"learn":[0.1958324657],"iteration":159,"passed_time":7.898591928,"remaining_time":40.82584703},
{"learn":[0.1953182544],"iteration":160,"passed_time":7.948838344,"remaining_time":40.78099672},
{"learn":[0.1947054223],"iteration":161,"passed_time":7.994960478,"remaining_time":40.71507651},
{"learn":[0.1943129103],"iteration":162,"passed_time":8.047926939,"remaining_time":40.68399876},
{"learn":[0.1933063393],"iteration":163,"passed_time":8.096215146,"remaining_time":40.62917723},
{"learn":[0.1930437817],"iteration":164,"passed_time":8.149200565,"remaining_time":40.59783554},
{"learn":[0.1924746568],"iteration":165,"passed_time":8.194672148,"remaining_time":40.52907128},
{"learn":[0.1914986232],"iteration":166,"passed_time":8.242723158,"remaining_time":40.47325143},
{"learn":[0.1908324372],"iteration":167,"passed_time":8.289970527,"remaining_time":40.41360632},
{"learn":[0.1901719666],"iteration":168,"passed_time":8.341907831,"remaining_time":40.37680832},
{"learn":[0.1896782974],"iteration":169,"passed_time":8.391163263,"remaining_time":40.32694345},
{"learn":[0.1892869115],"iteration":170,"passed_time":8.439747172,"remaining_time":40.27388124},
{"learn":[0.1887418743],"iteration":171,"passed_time":8.48893189,"remaining_time":40.22371797},
{"learn":[0.1881846987],"iteration":172,"passed_time":8.535447709,"remaining_time":40.16100829},
{"learn":[0.187667628],"iteration":173,"passed_time":8.583887752,"remaining_time":40.10747553},
{"learn":[0.1871319221],"iteration":174,"passed_time":8.636893801,"remaining_time":40.07518724},
{"learn":[0.1865970378],"iteration":175,"passed_time":8.68322413,"remaining_time":40.0119021},
{"learn":[0.1860373206],"iteration":176,"passed_time":8.730589141,"remaining_time":39.95354353},
{"learn":[0.1857528604],"iteration":177,"passed_time":8.7892491,"remaining_time":39.94664338},
{"learn":[0.1849433231],"iteration":178,"passed_time":8.838311114,"remaining_time":39.89584011},
{"learn":[0.1844352011],"iteration":179,"passed_time":8.891750497,"remaining_time":39.86468139},
{"learn":[0.1839518359],"iteration":180,"passed_time":8.940430925,"remaining_time":39.81208467},
{"learn":[0.1833723955],"iteration":181,"passed_time":8.993113763,"remaining_time":39.77723395},
{"learn":[0.1829654323],"iteration":182,"passed_time":9.047485645,"remaining_time":39.74960906},
{"learn":[0.1824274243],"iteration":183,"passed_time":9.097820745,"remaining_time":39.7040764},
{"learn":[0.1819976373],"iteration":184,"passed_time":9.140213871,"remaining_time":39.6240623},
{"learn":[0.181430198],"iteration":185,"passed_time":9.183862089,"remaining_time":39.54985771},
{"learn":[0.1808150332],"iteration":186,"passed_time":9.233763531,"remaining_time":39.50273168},
{"learn":[0.1804371108],"iteration":187,"passed_time":9.292179125,"remaining_time":39.49176128},
{"learn":[0.1801800628],"iteration":188,"passed_time":9.345763606,"remaining_time":39.45989078},
{"learn":[0.1794953666],"iteration":189,"passed_time":9.402237733,"remaining_time":39.43991302},
{"learn":[0.1789827648],"iteration":190,"passed_time":9.452659052,"remaining_time":39.39432778},
{"learn":[0.1789136848],"iteration":191,"passed_time":9.456227638,"remaining_time":39.15469256},
{"learn":[0.178179052],"iteration":192,"passed_time":9.511174343,"remaining_time":39.12887268},
{"learn":[0.1774975986],"iteration":193,"passed_time":9.563563164,"remaining_time":39.09229685},
{"learn":[0.1770154778],"iteration":194,"passed_time":9.616944914,"remaining_time":39.05959165},
{"learn":[0.1765842257],"iteration":195,"passed_time":9.673975639,"remaining_time":39.04140168},
{"learn":[0.1763173404],"iteration":196,"passed_time":9.721103983,"remaining_time":38.98310734},
{"learn":[0.1757686912],"iteration":197,"passed_time":9.766828353,"remaining_time":38.91933116},
{"learn":[0.1751987215],"iteration":198,"passed_time":9.811414302,"remaining_time":38.85122849},
{"learn":[0.1749247822],"iteration":199,"passed_time":9.860616914,"remaining_time":38.80152756},
{"learn":[0.1743182554],"iteration":200,"passed_time":9.910326571,"remaining_time":38.75381435},
{"learn":[0.1738575578],"iteration":201,"passed_time":9.966976965,"remaining_time":38.73305405},
{"learn":[0.1729536716],"iteration":202,"passed_time":10.01646718,"remaining_time":38.68428703},
{"learn":[0.1725695955],"iteration":203,"passed_time":10.06102185,"remaining_time":38.61656916},
{"learn":[0.1723013739],"iteration":204,"passed_time":10.11153423,"remaining_time":38.57180376},
{"learn":[0.1718590516],"iteration":205,"passed_time":10.16110373,"remaining_time":38.52340784},
{"learn":[0.1718043551],"iteration":206,"passed_time":10.16417096,"remaining_time":38.29977463},
{"learn":[0.171566946],"iteration":207,"passed_time":10.2102784,"remaining_time":38.23945611},
{"learn":[0.1711760706],"iteration":208,"passed_time":10.2535837,"remaining_time":38.16884265},
{"learn":[0.1708310051],"iteration":209,"passed_time":10.31204712,"remaining_time":38.15457433},
{"learn":[0.1704378236],"iteration":210,"passed_time":10.36051128,"remaining_time":38.10311258},
{"learn":[0.1701475993],"iteration":211,"passed_time":10.4119423,"remaining_time":38.06252492},
{"learn":[0.1698910098],"iteration":212,"passed_time":10.47297354,"remaining_time":38.05672075},
{"learn":[0.1696726854],"iteration":213,"passed_time":10.51913685,"remaining_time":37.99669524},
{"learn":[0.1692701911],"iteration":214,"passed_time":10.56496622,"remaining_time":37.93559962},
{"learn":[0.1692503177],"iteration":215,"passed_time":10.56754112,"remaining_time":37.72025095},
{"learn":[0.1689347178],"iteration":216,"passed_time":10.61652782,"remaining_time":37.67155032},
{"learn":[0.1686782381],"iteration":217,"passed_time":10.66889973,"remaining_time":37.63478849},
{"learn":[0.1681444582],"iteration":218,"passed_time":10.72820157,"remaining_time":37.62218631},
{"learn":[0.1674220067],"iteration":219,"passed_time":10.77725879,"remaining_time":37.57344313},
{"learn":[0.1661613018],"iteration":220,"passed_time":10.82961862,"remaining_time":37.53614416},
{"learn":[0.1658003498],"iteration":221,"passed_time":10.87629989,"remaining_time":37.47914153},
{"learn":[0.1651279491],"iteration":222,"passed_time":10.92944048,"remaining_time":37.44436109},
{"learn":[0.1647853617],"iteration":223,"passed_time":10.98020771,"remaining_time":37.40133252},
{"learn":[0.1644929985],"iteration":224,"passed_time":11.02854252,"remaining_time":37.34999735},
{"learn":[0.1641329346],"iteration":225,"passed_time":11.08136048,"remaining_time":37.31378462},
{"learn":[0.1639015598],"iteration":226,"passed_time":11.12919123,"remaining_time":37.26072836},
{"learn":[0.1630915924],"iteration":227,"passed_time":11.16885903,"remaining_time":37.18054386},
{"learn":[0.1626991076],"iteration":228,"passed_time":11.2110083,"remaining_time":37.10892704},
{"learn":[0.1623572624],"iteration":229,"passed_time":11.25641839,"remaining_time":37.0482988},
{"learn":[0.1622245146],"iteration":230,"passed_time":11.3049321,"remaining_time":36.99795959},
{"learn":[0.1619261067],"iteration":231,"passed_time":11.35533977,"remaining_time":36.95379969},
{"learn":[0.1615913613],"iteration":232,"passed_time":11.40821942,"remaining_time":36.91758559},
{"learn":[0.1612673826],"iteration":233,"passed_time":11.45633933,"remaining_time":36.86591246},
{"learn":[0.1609997611],"iteration":234,"passed_time":11.51796099,"remaining_time":36.85747518},
{"learn":[0.1603917617],"iteration":235,"passed_time":11.57279753,"remaining_time":36.82699555},
{"learn":[0.1599382891],"iteration":236,"passed_time":11.62725348,"remaining_time":36.79510596},
{"learn":[0.1593292968],"iteration":237,"passed_time":11.67895994,"remaining_time":36.75437392},
{"learn":[0.1590127056],"iteration":238,"passed_time":11.7369823,"remaining_time":36.73331698},
{"learn":[0.1584176187],"iteration":239,"passed_time":11.78694465,"remaining_time":36.68686522},
{"learn":[0.1580736381],"iteration":240,"passed_time":11.84103171,"remaining_time":36.65315211},
{"learn":[0.1576441126],"iteration":241,"passed_time":11.8991992,"remaining_time":36.63183226},
{"learn":[0.1573241989],"iteration":242,"passed_time":11.95950842,"remaining_time":36.61676651},
{"learn":[0.1569364929],"iteration":243,"passed_time":12.01491609,"remaining_time":36.58640431},
{"learn":[0.1562671654],"iteration":244,"passed_time":12.06900933,"remaining_time":36.55185684},
{"learn":[0.1560499744],"iteration":245,"passed_time":12.11856051,"remaining_time":36.50346885},
{"learn":[0.1557422514],"iteration":246,"passed_time":12.16903729,"remaining_time":36.45784453},
{"learn":[0.1554025294],"iteration":247,"passed_time":12.22885541,"remaining_time":36.44001673},
{"learn":[0.1551688888],"iteration":248,"passed_time":12.27741969,"remaining_time":36.38849692},
{"learn":[0.1548302045],"iteration":249,"passed_time":12.31895564,"remaining_time":36.31628123},
{"learn":[0.1545449272],"iteration":250,"passed_time":12.36770401,"remaining_time":36.26545876},
{"learn":[0.1543767229],"iteration":251,"passed_time":12.41588355,"remaining_time":36.21299367},
{"learn":[0.1540153094],"iteration":252,"passed_time":12.465685,"remaining_time":36.16526795},
{"learn":[0.153535201],"iteration":253,"passed_time":12.51097375,"remaining_time":36.10450299},
{"learn":[0.1533097566],"iteration":254,"passed_time":12.55861257,"remaining_time":36.05060549},
{"learn":[0.153002948],"iteration":255,"passed_time":12.60359158,"remaining_time":35.9891619},
{"learn":[0.1525441666],"iteration":256,"passed_time":12.65172012,"remaining_time":35.93679257},
{"learn":[0.1522271934],"iteration":257,"passed_time":12.69864014,"remaining_time":35.88104134},
{"learn":[0.1520808777],"iteration":258,"passed_time":12.74969067,"remaining_time":35.83696837},
{"learn":[0.1515694507],"iteration":259,"passed_time":12.80164796,"remaining_time":35.79537719},
{"learn":[0.1513281081],"iteration":260,"passed_time":12.84820909,"remaining_time":35.73869654},
{"learn":[0.1510131965],"iteration":261,"passed_time":12.89725451,"remaining_time":35.68896762},
{"learn":[0.1507746598],"iteration":262,"passed_time":12.95226162,"remaining_time":35.65565557},
{"learn":[0.1505663519],"iteration":263,"passed_time":13.00235091,"remaining_time":35.60871102},
{"learn":[0.150392276],"iteration":264,"passed_time":13.0570906,"remaining_time":35.57441288},
{"learn":[0.1499429849],"iteration":265,"passed_time":13.10858293,"remaining_time":35.531159},
{"learn":[0.1496791607],"iteration":266,"passed_time":13.16567212,"remaining_time":35.50293605},
{"learn":[0.1495471473],"iteration":267,"passed_time":13.21994264,"remaining_time":35.46693567},
{"learn":[0.1491366321],"iteration":268,"passed_time":13.27141315,"remaining_time":35.4233258},
{"learn":[0.1486232165],"iteration":269,"passed_time":13.32192286,"remaining_time":35.37710625},
{"learn":[0.1483359575],"iteration":270,"passed_time":13.37478846,"remaining_time":35.33707947},
{"learn":[0.1480723925],"iteration":271,"passed_time":13.42923648,"remaining_time":35.30111795},
{"learn":[0.1477908504],"iteration":272,"passed_time":13.48417124,"remaining_time":35.266294},
{"learn":[0.147315961],"iteration":273,"passed_time":13.53504265,"remaining_time":35.22074966},
{"learn":[0.1467527013],"iteration":274,"passed_time":13.58246938,"remaining_time":35.16624799},
{"learn":[0.1465668637],"iteration":275,"passed_time":13.62370606,"remaining_time":35.09585147},
{"learn":[0.1460209662],"iteration":276,"passed_time":13.66928909,"remaining_time":35.03680596},
{"learn":[0.1456737434],"iteration":277,"passed_time":13.71330661,"remaining_time":34.9738647},
{"learn":[0.145179985],"iteration":278,"passed_time":13.76291939,"remaining_time":34.92525779},
{"learn":[0.1449526634],"iteration":279,"passed_time":13.80703424,"remaining_time":34.86276145},
{"learn":[0.1445822157],"iteration":280,"passed_time":13.86566925,"remaining_time":34.83687718},
{"learn":[0.1441163179],"iteration":281,"passed_time":13.91751778,"remaining_time":34.79379445},
{"learn":[0.1437334905],"iteration":282,"passed_time":13.96243057,"remaining_time":34.73339619},
{"learn":[0.143534184],"iteration":283,"passed_time":14.01066259,"remaining_time":34.68132324},
{"learn":[0.1426476622],"iteration":284,"passed_time":14.06856777,"remaining_time":34.65310376},
{"learn":[0.142325843],"iteration":285,"passed_time":14.12198423,"remaining_time":34.61367464},
{"learn":[0.1418678831],"iteration":286,"passed_time":14.17402014,"remaining_time":34.57078083},
{"learn":[0.141708644],"iteration":287,"passed_time":14.22965919,"remaining_time":34.53656865},
{"learn":[0.1412625711],"iteration":288,"passed_time":14.28920433,"remaining_time":34.51164229},
{"learn":[0.1411194576],"iteration":289,"passed_time":14.34668577,"remaining_time":34.48151718},
{"learn":[0.140942171],"iteration":290,"passed_time":14.40641133,"remaining_time":34.45657142},
{"learn":[0.1403891436],"iteration":291,"passed_time":14.46907786,"remaining_time":34.43838737},
{"learn":[0.1401194014],"iteration":292,"passed_time":14.51809257,"remaining_time":34.38756398},
{"learn":[0.1398803689],"iteration":293,"passed_time":14.56762874,"remaining_time":34.33798203},
{"learn":[0.139661999],"iteration":294,"passed_time":14.62547888,"remaining_time":34.30790301},
{"learn":[0.1394454708],"iteration":295,"passed_time":14.67882507,"remaining_time":34.26712203},
{"learn":[0.1391506443],"iteration":296,"passed_time":14.72379084,"remaining_time":34.20678679},
{"learn":[0.13899252],"iteration":297,"passed_time":14.77431376,"remaining_time":34.15940329},
{"learn":[0.1386788239],"iteration":298,"passed_time":14.81973268,"remaining_time":34.10025446},
{"learn":[0.1382853613],"iteration":299,"passed_time":14.869009,"remaining_time":34.05003062},
{"learn":[0.1381111183],"iteration":300,"passed_time":14.92571147,"remaining_time":34.01673776},
{"learn":[0.137794953],"iteration":301,"passed_time":14.9754468,"remaining_time":33.96748694},
{"learn":[0.1374921178],"iteration":302,"passed_time":15.02060902,"remaining_time":33.90790947},
{"learn":[0.1372573426],"iteration":303,"passed_time":15.07226997,"remaining_time":33.8630276},
{"learn":[0.1368304198],"iteration":304,"passed_time":15.1160943,"remaining_time":33.80057807},
{"learn":[0.1366845281],"iteration":305,"passed_time":15.17330848,"remaining_time":33.76804925},
{"learn":[0.1361861588],"iteration":306,"passed_time":15.22769751,"remaining_time":33.72910198},
{"learn":[0.1359226282],"iteration":307,"passed_time":15.28481017,"remaining_time":33.69605878},
{"learn":[0.1355354454],"iteration":308,"passed_time":15.33086111,"remaining_time":33.63858844},
{"learn":[0.1352876579],"iteration":309,"passed_time":15.37988887,"remaining_time":33.5876928},
{"learn":[0.1351315652],"iteration":310,"passed_time":15.42479427,"remaining_time":33.52784865},
{"learn":[0.1348151175],"iteration":311,"passed_time":15.46846795,"remaining_time":33.46543546},
{"learn":[0.134461842],"iteration":312,"passed_time":15.51524266,"remaining_time":33.40981965},
{"learn":[0.1343313252],"iteration":313,"passed_time":15.55665154,"remaining_time":33.34275951},
{"learn":[0.1340880738],"iteration":314,"passed_time":15.60384978,"remaining_time":33.28821286},
{"learn":[0.1339722334],"iteration":315,"passed_time":15.6506727,"remaining_time":33.23291576},
{"learn":[0.133476677],"iteration":316,"passed_time":15.70155529,"remaining_time":33.1862525},
{"learn":[0.1329907901],"iteration":317,"passed_time":15.74311453,"remaining_time":33.1199485},
{"learn":[0.132984171],"iteration":318,"passed_time":15.7455981,"remaining_time":32.97197346},
{"learn":[0.1328452335],"iteration":319,"passed_time":15.79419162,"remaining_time":32.92101815},
{"learn":[0.1325794255],"iteration":320,"passed_time":15.8319334,"remaining_time":32.84756275},
{"learn":[0.1320901799],"iteration":321,"passed_time":15.88110589,"remaining_time":32.79793607},
{"learn":[0.1320148675],"iteration":322,"passed_time":15.92450804,"remaining_time":32.73644996},
{"learn":[0.1317942672],"iteration":323,"passed_time":15.96010182,"remaining_time":32.65909724},
{"learn":[0.1316656863],"iteration":324,"passed_time":16.00200358,"remaining_time":32.59485038},
{"learn":[0.1313963166],"iteration":325,"passed_time":16.04828591,"remaining_time":32.53962266},
{"learn":[0.1309802367],"iteration":326,"passed_time":16.09642111,"remaining_time":32.48818939},
{"learn":[0.1308499153],"iteration":327,"passed_time":16.15095311,"remaining_time":32.44962835},
{"learn":[0.1304811431],"iteration":328,"passed_time":16.19473846,"remaining_time":32.38947691},
{"learn":[0.1301622256],"iteration":329,"passed_time":16.24758887,"remaining_time":32.34747239},
{"learn":[0.1298957373],"iteration":330,"passed_time":16.29644797,"remaining_time":32.29749205},
{"learn":[0.129653393],"iteration":331,"passed_time":16.3356587,"remaining_time":32.22848328},
{"learn":[0.1294645078],"iteration":332,"passed_time":16.38440073,"remaining_time":32.17837261},
{"learn":[0.1288879535],"iteration":333,"passed_time":16.42852994,"remaining_time":32.11925165},
{"learn":[0.1286402546],"iteration":334,"passed_time":16.47032453,"remaining_time":32.0556764},
{"learn":[0.1285122956],"iteration":335,"passed_time":16.51172263,"remaining_time":31.99146259},
{"learn":[0.128122339],"iteration":336,"passed_time":16.55329394,"remaining_time":31.92771829},
{"learn":[0.1278647742],"iteration":337,"passed_time":16.59105012,"remaining_time":31.85677966},
{"learn":[0.1275743917],"iteration":338,"passed_time":16.63097159,"remaining_time":31.79017579},
{"learn":[0.127442621],"iteration":339,"passed_time":16.67571557,"remaining_time":31.73290581},
{"learn":[0.1273007476],"iteration":340,"passed_time":16.71606729,"remaining_time":31.66738847},
{"learn":[0.1272766242],"iteration":341,"passed_time":16.71895606,"remaining_time":31.5313645},
{"learn":[0.1271408387],"iteration":342,"passed_time":16.76985617,"remaining_time":31.48626056},
{"learn":[0.1270021007],"iteration":343,"passed_time":16.8193854,"remaining_time":31.43856049},
{"learn":[0.1268365798],"iteration":344,"passed_time":16.86504243,"remaining_time":31.38364417},
{"learn":[0.1266498909],"iteration":345,"passed_time":16.9195583,"remaining_time":31.34519326},
{"learn":[0.1264711569],"iteration":346,"passed_time":16.97370583,"remaining_time":31.30597041},
{"learn":[0.1261702268],"iteration":347,"passed_time":17.02408485,"remaining_time":31.259742},
{"learn":[0.1259435936],"iteration":348,"passed_time":17.07409915,"remaining_time":31.21282308},
{"learn":[0.1258370018],"iteration":349,"passed_time":17.12888927,"remaining_time":31.17457846},
{"learn":[0.1257594496],"iteration":350,"passed_time":17.17533853,"remaining_time":31.12112622},
{"learn":[0.1253740209],"iteration":351,"passed_time":17.22583011,"remaining_time":31.07500603},
{"learn":[0.1252215717],"iteration":352,"passed_time":17.27848237,"remaining_time":31.0327417},
{"learn":[0.1248773309],"iteration":353,"passed_time":17.3332479,"remaining_time":30.99419752},
{"learn":[0.1247277051],"iteration":354,"passed_time":17.38507711,"remaining_time":30.95033446},
{"learn":[0.1243282354],"iteration":355,"passed_time":17.4373078,"remaining_time":30.90713826},
{"learn":[0.1241046287],"iteration":356,"passed_time":17.49030528,"remaining_time":30.86524462},
{"learn":[0.1238730622],"iteration":357,"passed_time":17.54567133,"remaining_time":30.82745046},
{"learn":[0.1237192244],"iteration":358,"passed_time":17.60222958,"remaining_time":30.79164395},
{"learn":[0.1234340793],"iteration":359,"passed_time":17.6487481,"remaining_time":30.73823627},
{"learn":[0.1231962036],"iteration":360,"passed_time":17.69701581,"remaining_time":30.6879},
{"learn":[0.1229534639],"iteration":361,"passed_time":17.7506197,"remaining_time":30.64678816},
{"learn":[0.1226645448],"iteration":362,"passed_time":17.80412172,"remaining_time":30.60543238},
{"learn":[0.1224185873],"iteration":363,"passed_time":17.85145928,"remaining_time":30.55345916},
{"learn":[0.1221046328],"iteration":364,"passed_time":17.90326853,"remaining_time":30.50913158},
{"learn":[0.1219166326],"iteration":365,"passed_time":17.95517389,"remaining_time":30.4649262},
{"learn":[0.1217042959],"iteration":366,"passed_time":18.00522592,"remaining_time":30.41754787},
{"learn":[0.1215927175],"iteration":367,"passed_time":18.05218428,"remaining_time":30.36495128},
{"learn":[0.121584176],"iteration":368,"passed_time":18.05657383,"remaining_time":30.24109113},
{"learn":[0.1212839707],"iteration":369,"passed_time":18.10863326,"remaining_time":30.19736951},
{"learn":[0.1209533891],"iteration":370,"passed_time":18.16125728,"remaining_time":30.15454039},
{"learn":[0.1208149229],"iteration":371,"passed_time":18.21556823,"remaining_time":30.11444748},
{"learn":[0.1205741031],"iteration":372,"passed_time":18.27012802,"remaining_time":30.07468795},
{"learn":[0.1202729606],"iteration":373,"passed_time":18.32345265,"remaining_time":30.03282479},
{"learn":[0.1201098811],"iteration":374,"passed_time":18.37548391,"remaining_time":29.98878975},
{"learn":[0.1199147387],"iteration":375,"passed_time":18.42949827,"remaining_time":29.94793469},
{"learn":[0.1197746106],"iteration":376,"passed_time":18.47661691,"remaining_time":29.89585229},
{"learn":[0.1197189182],"iteration":377,"passed_time":18.48026251,"remaining_time":29.77375626},
{"learn":[0.1195907182],"iteration":378,"passed_time":18.54115042,"remaining_time":29.74411466},
{"learn":[0.1194469799],"iteration":379,"passed_time":18.58917355,"remaining_time":29.69375881},
{"learn":[0.1192398782],"iteration":380,"passed_time":18.64654749,"remaining_time":29.65828813},
{"learn":[0.1191315591],"iteration":381,"passed_time":18.70079372,"remaining_time":29.61774921},
{"learn":[0.1189785525],"iteration":382,"passed_time":18.75686824,"remaining_time":29.58002198},
{"learn":[0.1187243156],"iteration":383,"passed_time":18.81060661,"remaining_time":29.53853069},
{"learn":[0.1184199393],"iteration":384,"passed_time":18.85759166,"remaining_time":29.48641605},
{"learn":[0.1182032508],"iteration":385,"passed_time":18.91576406,"remaining_time":29.45174663},
{"learn":[0.1179312956],"iteration":386,"passed_time":18.97156114,"remaining_time":29.41327308},
{"learn":[0.1177669563],"iteration":387,"passed_time":19.01783826,"remaining_time":29.36001319},
{"learn":[0.1173870263],"iteration":388,"passed_time":19.0674514,"remaining_time":29.31191757},
{"learn":[0.1172287538],"iteration":389,"passed_time":19.11710249,"remaining_time":29.26387227},
{"learn":[0.1171289475],"iteration":390,"passed_time":19.17244312,"remaining_time":29.22449131},
{"learn":[0.1168759685],"iteration":391,"passed_time":19.22239107,"remaining_time":29.1768436},
{"learn":[0.1167232119],"iteration":392,"passed_time":19.27803018,"remaining_time":29.13778608},
{"learn":[0.1166195705],"iteration":393,"passed_time":19.33261944,"remaining_time":29.09706428},
{"learn":[0.1161418416],"iteration":394,"passed_time":19.38835834,"remaining_time":29.05799529},
{"learn":[0.1158740945],"iteration":395,"passed_time":19.43680925,"remaining_time":29.00796532},
{"learn":[0.1156814224],"iteration":396,"passed_time":19.49200898,"remaining_time":28.96797304},
{"learn":[0.115490649],"iteration":397,"passed_time":19.54153145,"remaining_time":28.91950258},
{"learn":[0.1152620015],"iteration":398,"passed_time":19.59645316,"remaining_time":28.8789836},
{"learn":[0.1150331043],"iteration":399,"passed_time":19.64234899,"remaining_time":28.82514714},
{"learn":[0.1149066422],"iteration":400,"passed_time":19.69493523,"remaining_time":28.7811273},
{"learn":[0.1147651896],"iteration":401,"passed_time":19.75141505,"remaining_time":28.74273086},
{"learn":[0.1145620919],"iteration":402,"passed_time":19.80077363,"remaining_time":28.69392507},
{"learn":[0.1144702177],"iteration":403,"passed_time":19.85364329,"remaining_time":28.65018326},
{"learn":[0.1142703355],"iteration":404,"passed_time":19.90236641,"remaining_time":28.60043766},
{"learn":[0.1140279336],"iteration":405,"passed_time":19.95743299,"remaining_time":28.55977479},
{"learn":[0.1138549191],"iteration":406,"passed_time":20.00984147,"remaining_time":28.51525321},
{"learn":[0.1137329741],"iteration":407,"passed_time":20.05983957,"remaining_time":28.46727233},
{"learn":[0.1134545148],"iteration":408,"passed_time":20.10847237,"remaining_time":28.41735215},
{"learn":[0.1133178727],"iteration":409,"passed_time":20.16622943,"remaining_time":28.38027898},
{"learn":[0.1132335433],"iteration":410,"passed_time":20.21332839,"remaining_time":28.32816826},
{"learn":[0.1130313754],"iteration":411,"passed_time":20.27185447,"remaining_time":28.2920299},
{"learn":[0.112699597],"iteration":412,"passed_time":20.32114673,"remaining_time":28.2429497},
{"learn":[0.1124868518],"iteration":413,"passed_time":20.37648846,"remaining_time":28.20224127},
{"learn":[0.1123746027],"iteration":414,"passed_time":20.43179246,"remaining_time":28.16141032},
{"learn":[0.1122260466],"iteration":415,"passed_time":20.48326187,"remaining_time":28.11524646},
{"learn":[0.1121056406],"iteration":416,"passed_time":20.53880353,"remaining_time":28.07462353},
{"learn":[0.1119721148],"iteration":417,"passed_time":20.59184361,"remaining_time":28.03052396},
{"learn":[0.1116997706],"iteration":418,"passed_time":20.64747045,"remaining_time":27.98988834},
{"learn":[0.1115408515],"iteration":419,"passed_time":20.70868428,"remaining_time":27.95672378},
{"learn":[0.1113444921],"iteration":420,"passed_time":20.76554999,"remaining_time":27.91758027},
{"learn":[0.1111772311],"iteration":421,"passed_time":20.82080711,"remaining_time":27.87619909},
{"learn":[0.1110440242],"iteration":422,"passed_time":20.87777244,"remaining_time":27.83702993},
{"learn":[0.1109399295],"iteration":423,"passed_time":20.93797253,"remaining_time":27.80207201},
{"learn":[0.1107710439],"iteration":424,"passed_time":20.98987816,"remaining_time":27.75602712},
{"learn":[0.1104366244],"iteration":425,"passed_time":21.04102888,"remaining_time":27.70896056},
{"learn":[0.1103475452],"iteration":426,"passed_time":21.097283,"remaining_time":27.66856787},
{"learn":[0.1101887215],"iteration":427,"passed_time":21.15439682,"remaining_time":27.62922388},
{"learn":[0.1100176679],"iteration":428,"passed_time":21.21016983,"remaining_time":27.58805306},
{"learn":[0.1099007224],"iteration":429,"passed_time":21.25854094,"remaining_time":27.53722629},
{"learn":[0.1096782148],"iteration":430,"passed_time":21.30959326,"remaining_time":27.48986973},
{"learn":[0.1094434828],"iteration":431,"passed_time":21.35684449,"remaining_time":27.43761272},
{"learn":[0.1091469812],"iteration":432,"passed_time":21.40458408,"remaining_time":27.38600365},
{"learn":[0.1090449803],"iteration":433,"passed_time":21.46076673,"remaining_time":27.34517051},
{"learn":[0.1089043271],"iteration":434,"passed_time":21.51936054,"remaining_time":27.30732648},
{"learn":[0.1087651521],"iteration":435,"passed_time":21.57540151,"remaining_time":27.26616108},
{"learn":[0.1085222328],"iteration":436,"passed_time":21.63237971,"remaining_time":27.22610719},
{"learn":[0.1083578892],"iteration":437,"passed_time":21.68557775,"remaining_time":27.18123786},
{"learn":[0.1077893616],"iteration":438,"passed_time":21.73809616,"remaining_time":27.13548222},
{"learn":[0.1076899687],"iteration":439,"passed_time":21.79250785,"remaining_time":27.09204953},
{"learn":[0.1076270186],"iteration":440,"passed_time":21.84517184,"remaining_time":27.04640323},
{"learn":[0.1074966943],"iteration":441,"passed_time":21.9025797,"remaining_time":27.00657451},
{"learn":[0.1072455702],"iteration":442,"passed_time":21.95499455,"remaining_time":26.96053507},
{"learn":[0.1068220134],"iteration":443,"passed_time":22.0066438,"remaining_time":26.9135306},
{"learn":[0.1064871048],"iteration":444,"passed_time":22.05444455,"remaining_time":26.86181786},
{"learn":[0.1063297169],"iteration":445,"passed_time":22.10163278,"remaining_time":26.80937967},
{"learn":[0.1061164399],"iteration":446,"passed_time":22.14608438,"remaining_time":26.75365899},
{"learn":[0.1059425266],"iteration":447,"passed_time":22.20470656,"remaining_time":26.71503758},
{"learn":[0.1058352627],"iteration":448,"passed_time":22.26152156,"remaining_time":26.67416169},
{"learn":[0.1054648108],"iteration":449,"passed_time":22.3136842,"remaining_time":26.62766315},
{"learn":[0.1053052766],"iteration":450,"passed_time":22.3718832,"remaining_time":26.58831351},
{"learn":[0.1050743037],"iteration":451,"passed_time":22.42205086,"remaining_time":26.53937436},
{"learn":[0.1049155391],"iteration":452,"passed_time":22.46943298,"remaining_time":26.48714617},
{"learn":[0.1048058435],"iteration":453,"passed_time":22.52703725,"remaining_time":26.44694021},
{"learn":[0.104742705],"iteration":454,"passed_time":22.57478209,"remaining_time":26.39512983},
{"learn":[0.104653758],"iteration":455,"passed_time":22.62694293,"remaining_time":26.34847959},
{"learn":[0.1045746724],"iteration":456,"passed_time":22.67960333,"remaining_time":26.30238461},
{"learn":[0.1045372694],"iteration":457,"passed_time":22.73708029,"remaining_time":26.26182418},
{"learn":[0.104472095],"iteration":458,"passed_time":22.78943665,"remaining_time":26.21529968},
{"learn":[0.104215711],"iteration":459,"passed_time":22.83638655,"remaining_time":26.1625559},
{"learn":[0.1040180795],"iteration":460,"passed_time":22.8904294,"remaining_time":26.11793029},
{"learn":[0.1038941144],"iteration":461,"passed_time":22.94205849,"remaining_time":26.07052101},
{"learn":[0.1038065949],"iteration":462,"passed_time":23.00018496,"remaining_time":26.03044691},
{"learn":[0.1036100869],"iteration":463,"passed_time":23.04134651,"remaining_time":25.9711729},
{"learn":[0.1033794155],"iteration":464,"passed_time":23.08811151,"remaining_time":25.91826711},
{"learn":[0.1032285291],"iteration":465,"passed_time":23.14363673,"remaining_time":25.87518184},
{"learn":[0.102963307],"iteration":466,"passed_time":23.1937398,"remaining_time":25.82600578},
{"learn":[0.1028274892],"iteration":467,"passed_time":23.24841921,"remaining_time":25.78190079},
{"learn":[0.1026708506],"iteration":468,"passed_time":23.29933719,"remaining_time":25.73359629},
{"learn":[0.1025422512],"iteration":469,"passed_time":23.35673232,"remaining_time":25.69240555},
{"learn":[0.1023964944],"iteration":470,"passed_time":23.40899574,"remaining_time":25.645524},
{"learn":[0.1022858088],"iteration":471,"passed_time":23.46459578,"remaining_time":25.60226023},
{"learn":[0.1021629432],"iteration":472,"passed_time":23.51966533,"remaining_time":25.55836783},
{"learn":[0.1020356465],"iteration":473,"passed_time":23.56662931,"remaining_time":25.50565577},
{"learn":[0.1017332471],"iteration":474,"passed_time":23.61639627,"remaining_time":25.45598924},
{"learn":[0.1017122862],"iteration":475,"passed_time":23.621146,"remaining_time":25.35799497},
{"learn":[0.1016014266],"iteration":476,"passed_time":23.67072127,"remaining_time":25.30831834},
{"learn":[0.1015300325],"iteration":477,"passed_time":23.7266543,"remaining_time":25.26541222},
{"learn":[0.1014443144],"iteration":478,"passed_time":23.78280823,"remaining_time":25.22268597},
{"learn":[0.1013427173],"iteration":479,"passed_time":23.83969848,"remaining_time":25.18068152},
{"learn":[0.1011994275],"iteration":480,"passed_time":23.89666211,"remaining_time":25.13869237},
{"learn":[0.1009252862],"iteration":481,"passed_time":23.9486505,"remaining_time":25.09142843},
{"learn":[0.100871632],"iteration":482,"passed_time":23.99683672,"remaining_time":25.04017744},
{"learn":[0.1007317256],"iteration":483,"passed_time":24.04643704,"remaining_time":24.99040875},
{"learn":[0.1005235851],"iteration":484,"passed_time":24.0956917,"remaining_time":24.94028295},
{"learn":[0.1004424557],"iteration":485,"passed_time":24.14912585,"remaining_time":24.89446924},
{"learn":[0.1003100133],"iteration":486,"passed_time":24.20253551,"remaining_time":24.84859909},
{"learn":[0.1001885119],"iteration":487,"passed_time":24.25886879,"remaining_time":24.80568755},
{"learn":[0.09992743781],"iteration":488,"passed_time":24.31083532,"remaining_time":24.75827401},
{"learn":[0.09981751697],"iteration":489,"passed_time":24.35907032,"remaining_time":24.70705704},
{"learn":[0.09941566143],"iteration":490,"passed_time":24.41683855,"remaining_time":24.66548253},
{"learn":[0.09923767336],"iteration":491,"passed_time":24.45253835,"remaining_time":24.60163919},
{"learn":[0.09909033668],"iteration":492,"passed_time":24.50233303,"remaining_time":24.55203351},
{"learn":[0.09904877878],"iteration":493,"passed_time":24.54869352,"remaining_time":24.49899981},
{"learn":[0.09899259294],"iteration":494,"passed_time":24.59278546,"remaining_time":24.44373827},
{"learn":[0.0987112644],"iteration":495,"passed_time":24.64120893,"remaining_time":24.39280964},
{"learn":[0.098626805],"iteration":496,"passed_time":24.69213189,"remaining_time":24.34435538},
{"learn":[0.09844880354],"iteration":497,"passed_time":24.738896,"remaining_time":24.29180752},
{"learn":[0.09827588661],"iteration":498,"passed_time":24.78112176,"remaining_time":24.23484453},
{"learn":[0.09816527907],"iteration":499,"passed_time":24.82161209,"remaining_time":24.17625017},
{"learn":[0.09809910007],"iteration":500,"passed_time":24.8681766,"remaining_time":24.12362041},
{"learn":[0.09802430103],"iteration":501,"passed_time":24.91198374,"remaining_time":24.06835082},
{"learn":[0.09792384375],"iteration":502,"passed_time":24.96754274,"remaining_time":24.02443476},
{"learn":[0.09780420452],"iteration":503,"passed_time":25.01659013,"remaining_time":23.9742322},
{"learn":[0.09761638523],"iteration":504,"passed_time":25.06412422,"remaining_time":23.92258985},
{"learn":[0.09754465191],"iteration":505,"passed_time":25.11565259,"remaining_time":23.87476066},
{"learn":[0.09738341883],"iteration":506,"passed_time":25.16517662,"remaining_time":23.82501928},
{"learn":[0.09726552871],"iteration":507,"passed_time":25.21482221,"remaining_time":23.77539338},
{"learn":[0.09717130351],"iteration":508,"passed_time":25.25944343,"remaining_time":23.72104904},
{"learn":[0.09705549909],"iteration":509,"passed_time":25.31479794,"remaining_time":23.6767816},
{"learn":[0.09695455323],"iteration":510,"passed_time":25.35899077,"remaining_time":23.62207359},
{"learn":[0.09687113438],"iteration":511,"passed_time":25.41670502,"remaining_time":23.57995095},
{"learn":[0.09663423085],"iteration":512,"passed_time":25.47169717,"remaining_time":23.53525236},
{"learn":[0.09654775216],"iteration":513,"passed_time":25.52317953,"remaining_time":23.48728388},
{"learn":[0.09642807652],"iteration":514,"passed_time":25.57416633,"remaining_time":23.43884758},
{"learn":[0.09630121037],"iteration":515,"passed_time":25.63282425,"remaining_time":23.39740353},
{"learn":[0.09600739035],"iteration":516,"passed_time":25.67839084,"remaining_time":23.34399167},
{"learn":[0.09593114901],"iteration":517,"passed_time":25.73035494,"remaining_time":23.29640244},
{"learn":[0.09584634877],"iteration":518,"passed_time":25.78939676,"remaining_time":23.25517858},
{"learn":[0.09573541339],"iteration":519,"passed_time":25.84895064,"remaining_time":23.21434606},
{"learn":[0.09559811019],"iteration":520,"passed_time":25.90306533,"remaining_time":23.16857667},
{"learn":[0.09539291477],"iteration":521,"passed_time":25.95751665,"remaining_time":23.12307517},
{"learn":[0.09528801789],"iteration":522,"passed_time":26.01092747,"remaining_time":23.07661634},
{"learn":[0.09515583368],"iteration":523,"passed_time":26.05831641,"remaining_time":23.02481011},
{"learn":[0.09503827807],"iteration":524,"passed_time":26.11399613,"remaining_time":22.98031659},
{"learn":[0.09493120409],"iteration":525,"passed_time":26.17007764,"remaining_time":22.93613269},
{"learn":[0.09477341585],"iteration":526,"passed_time":26.22321937,"remaining_time":22.88933759},
{"learn":[0.09463793878],"iteration":527,"passed_time":26.27572937,"remaining_time":22.84196928},
{"learn":[0.09441600634],"iteration":528,"passed_time":26.32431948,"remaining_time":22.79118776},
{"learn":[0.09435143313],"iteration":529,"passed_time":26.3802582,"remaining_time":22.74675094},
{"learn":[0.09421762694],"iteration":530,"passed_time":26.43576919,"remaining_time":22.70190348},
{"learn":[0.094069277],"iteration":531,"passed_time":26.49014902,"remaining_time":22.6560485},
{"learn":[0.09387800328],"iteration":532,"passed_time":26.53904184,"remaining_time":22.60548779},
{"learn":[0.09374072031],"iteration":533,"passed_time":26.58493628,"remaining_time":22.55238977},
{"learn":[0.09361178618],"iteration":534,"passed_time":26.63308678,"remaining_time":22.50122472},
{"learn":[0.09352088932],"iteration":535,"passed_time":26.68002233,"remaining_time":22.44904864},
{"learn":[0.09344782535],"iteration":536,"passed_time":26.72895958,"remaining_time":22.39856948},
{"learn":[0.09337825637],"iteration":537,"passed_time":26.78127745,"remaining_time":22.35091742},
{"learn":[0.09328741451],"iteration":538,"passed_time":26.83164781,"remaining_time":22.30162935},
{"learn":[0.09325182782],"iteration":539,"passed_time":26.87834885,"remaining_time":22.24929988},
{"learn":[0.09312290766],"iteration":540,"passed_time":26.92642175,"remaining_time":22.19812218},
{"learn":[0.09302556996],"iteration":541,"passed_time":26.96685133,"remaining_time":22.14068052},
{"learn":[0.09298639509],"iteration":542,"passed_time":27.01344078,"remaining_time":22.08833832},
{"learn":[0.09270628067],"iteration":543,"passed_time":27.06031409,"remaining_time":22.03624843},
{"learn":[0.09255694106],"iteration":544,"passed_time":27.09856004,"remaining_time":21.9771808},
{"learn":[0.09248798184],"iteration":545,"passed_time":27.15244094,"remaining_time":21.93081768},
{"learn":[0.09234376381],"iteration":546,"passed_time":27.20207845,"remaining_time":21.88101374},
{"learn":[0.09224389601],"iteration":547,"passed_time":27.24920928,"remaining_time":21.82920233},
{"learn":[0.09212578305],"iteration":548,"passed_time":27.30004084,"remaining_time":21.78036045},
{"learn":[0.09203933723],"iteration":549,"passed_time":27.34043184,"remaining_time":21.72321584},
{"learn":[0.09199406478],"iteration":550,"passed_time":27.38539308,"remaining_time":21.66974842},
{"learn":[0.09180833973],"iteration":551,"passed_time":27.43520692,"remaining_time":21.62013589},
{"learn":[0.09165455969],"iteration":552,"passed_time":27.48059789,"remaining_time":21.56705151},
{"learn":[0.09155325064],"iteration":553,"passed_time":27.52559751,"remaining_time":21.51368903},
{"learn":[0.09141251903],"iteration":554,"passed_time":27.57172666,"remaining_time":21.46123589},
{"learn":[0.09134681805],"iteration":555,"passed_time":27.6170671,"remaining_time":21.4081941},
{"learn":[0.09124509055],"iteration":556,"passed_time":27.6719067,"remaining_time":21.36251325},
{"learn":[0.09107486754],"iteration":557,"passed_time":27.71783447,"remaining_time":21.30994801},
{"learn":[0.09099820481],"iteration":558,"passed_time":27.76047708,"remaining_time":21.25489122},
{"learn":[0.09088384401],"iteration":559,"passed_time":27.80008901,"remaining_time":21.19756787},
{"learn":[0.09055830741],"iteration":560,"passed_time":27.84732522,"remaining_time":21.14609722},
{"learn":[0.09041489637],"iteration":561,"passed_time":27.8951137,"remaining_time":21.09505929},
{"learn":[0.09031903932],"iteration":562,"passed_time":27.94987601,"remaining_time":21.04928496},
{"learn":[0.09019366983],"iteration":563,"passed_time":27.998542,"remaining_time":20.9989065},
{"learn":[0.09013570314],"iteration":564,"passed_time":28.04797182,"remaining_time":20.94910462},
{"learn":[0.08999706602],"iteration":565,"passed_time":28.1069919,"remaining_time":20.90643744},
{"learn":[0.08984452269],"iteration":566,"passed_time":28.1617434,"remaining_time":20.86055067},
{"learn":[0.08955404226],"iteration":567,"passed_time":28.21703572,"remaining_time":20.81503163},
{"learn":[0.08944324185],"iteration":568,"passed_time":28.26404698,"remaining_time":20.76339479},
{"learn":[0.0892311256],"iteration":569,"passed_time":28.31906472,"remaining_time":20.71763156},
{"learn":[0.08909854155],"iteration":570,"passed_time":28.37101384,"remaining_time":20.66960028},
{"learn":[0.08890893377],"iteration":571,"passed_time":28.42867795,"remaining_time":20.62570166},
{"learn":[0.08882118838],"iteration":572,"passed_time":28.48036503,"remaining_time":20.57743651},
{"learn":[0.08858630929],"iteration":573,"passed_time":28.53344553,"remaining_time":20.53016203},
{"learn":[0.08841757813],"iteration":574,"passed_time":28.5901676,"remaining_time":20.48547661},
{"learn":[0.08836760561],"iteration":575,"passed_time":28.6448267,"remaining_time":20.43927738},
{"learn":[0.088233271],"iteration":576,"passed_time":28.69385765,"remaining_time":20.38904963},
{"learn":[0.08811306583],"iteration":577,"passed_time":28.74438878,"remaining_time":20.33988756},
{"learn":[0.0879905988],"iteration":578,"passed_time":28.79808307,"remaining_time":20.29294972},
{"learn":[0.08787195377],"iteration":579,"passed_time":28.84602412,"remaining_time":20.24195141},
{"learn":[0.08782827507],"iteration":580,"passed_time":28.89712943,"remaining_time":20.19317478},
{"learn":[0.08775355097],"iteration":581,"passed_time":28.94534757,"remaining_time":20.14238104},
{"learn":[0.08770184731],"iteration":582,"passed_time":28.99505211,"remaining_time":20.09262616},
{"learn":[0.08746806776],"iteration":583,"passed_time":29.05468406,"remaining_time":20.04972205},
{"learn":[0.08733494145],"iteration":584,"passed_time":29.10788821,"remaining_time":20.00234369},
{"learn":[0.08727114213],"iteration":585,"passed_time":29.16014685,"remaining_time":19.95429844},
{"learn":[0.08719137171],"iteration":586,"passed_time":29.20107941,"remaining_time":19.89852089},
{"learn":[0.08689512292],"iteration":587,"passed_time":29.24619933,"remaining_time":19.84563526},
{"learn":[0.08684377531],"iteration":588,"passed_time":29.30000184,"remaining_time":19.79864301},
{"learn":[0.08671076782],"iteration":589,"passed_time":29.34765524,"remaining_time":19.74749005},
{"learn":[0.08659823661],"iteration":590,"passed_time":29.39288031,"remaining_time":19.69472184},
{"learn":[0.08652171854],"iteration":591,"passed_time":29.43825375,"remaining_time":19.6420781},
{"learn":[0.0864419705],"iteration":592,"passed_time":29.47681827,"remaining_time":19.58493491},
{"learn":[0.08623843023],"iteration":593,"passed_time":29.51873287,"remaining_time":19.53007074},
{"learn":[0.0861367068],"iteration":594,"passed_time":29.56128109,"remaining_time":19.47566754},
{"learn":[0.08606751509],"iteration":595,"passed_time":29.60444112,"remaining_time":19.4217055},
{"learn":[0.08592883835],"iteration":596,"passed_time":29.6493951,"remaining_time":19.36895158},
{"learn":[0.08576296673],"iteration":597,"passed_time":29.69549872,"remaining_time":19.31697158},
{"learn":[0.08551590516],"iteration":598,"passed_time":29.74052052,"remaining_time":19.26431046},
{"learn":[0.08532829007],"iteration":599,"passed_time":29.7803461,"remaining_time":19.20832323},
{"learn":[0.08511702684],"iteration":600,"passed_time":29.82735092,"remaining_time":19.15700076},
{"learn":[0.08499693961],"iteration":601,"passed_time":29.87414402,"remaining_time":19.10555722},
{"learn":[0.08489276883],"iteration":602,"passed_time":29.92337814,"remaining_time":19.05568359},
{"learn":[0.08468791911],"iteration":603,"passed_time":29.96889879,"remaining_time":19.00345735},
{"learn":[0.08455190687],"iteration":604,"passed_time":30.01996335,"remaining_time":18.95475372},
{"learn":[0.08443750525],"iteration":605,"passed_time":30.06962918,"remaining_time":18.9051629},
{"learn":[0.08439601355],"iteration":606,"passed_time":30.12062841,"remaining_time":18.85640659},
{"learn":[0.08434543309],"iteration":607,"passed_time":30.16925187,"remaining_time":18.80616194},
{"learn":[0.08422762885],"iteration":608,"passed_time":30.21728304,"remaining_time":18.75555499},
{"learn":[0.08412131523],"iteration":609,"passed_time":30.26377579,"remaining_time":18.7040057},
{"learn":[0.08407537698],"iteration":610,"passed_time":30.31266229,"remaining_time":18.65394603},
{"learn":[0.0840022961],"iteration":611,"passed_time":30.35624288,"remaining_time":18.60063902},
{"learn":[0.08386092351],"iteration":612,"passed_time":30.41048297,"remaining_time":18.55386726},
{"learn":[0.08364508964],"iteration":613,"passed_time":30.46590423,"remaining_time":18.50778872},
{"learn":[0.08357167609],"iteration":614,"passed_time":30.51954974,"remaining_time":18.46060569},
{"learn":[0.08356999072],"iteration":615,"passed_time":30.52204193,"remaining_time":18.38259344},
{"learn":[0.08341178769],"iteration":616,"passed_time":30.57505027,"remaining_time":18.33511928},
{"learn":[0.08326031075],"iteration":617,"passed_time":30.62855198,"remaining_time":18.28792182},
{"learn":[0.08317602385],"iteration":618,"passed_time":30.68183351,"remaining_time":18.24057307},
{"learn":[0.08306695013],"iteration":619,"passed_time":30.7299129,"remaining_time":18.19012586},
{"learn":[0.08298571901],"iteration":620,"passed_time":30.78236637,"remaining_time":18.14226423},
{"learn":[0.08285676422],"iteration":621,"passed_time":30.8397699,"remaining_time":18.09729263},
{"learn":[0.08279065688],"iteration":622,"passed_time":30.90139586,"remaining_time":18.05474814},
{"learn":[0.08273394888],"iteration":623,"passed_time":30.95560575,"remaining_time":18.00782834},
{"learn":[0.08263075301],"iteration":624,"passed_time":31.01056818,"remaining_time":17.96132109},
{"learn":[0.0826061051],"iteration":625,"passed_time":31.02906043,"remaining_time":17.8937553},
{"learn":[0.08241360667],"iteration":626,"passed_time":31.07917943,"remaining_time":17.84450494},
{"learn":[0.08225793923],"iteration":627,"passed_time":31.13518359,"remaining_time":17.7986161},
{"learn":[0.08211046846],"iteration":628,"passed_time":31.18629261,"remaining_time":17.74990899},
{"learn":[0.08205055754],"iteration":629,"passed_time":31.24036663,"remaining_time":17.70287442},
{"learn":[0.08197269512],"iteration":630,"passed_time":31.29264807,"remaining_time":17.6548062},
{"learn":[0.08186995123],"iteration":631,"passed_time":31.34412903,"remaining_time":17.60627501},
{"learn":[0.0817147941],"iteration":632,"passed_time":31.39590765,"remaining_time":17.55790096},
{"learn":[0.08160544342],"iteration":633,"passed_time":31.43790091,"remaining_time":17.50406786},
{"learn":[0.08140994611],"iteration":634,"passed_time":31.48769382,"remaining_time":17.45459563},
{"learn":[0.08140215603],"iteration":635,"passed_time":31.49062539,"remaining_time":17.37926024},
{"learn":[0.08128592718],"iteration":636,"passed_time":31.54502735,"remaining_time":17.33243261},
{"learn":[0.0812126342],"iteration":637,"passed_time":31.5945182,"remaining_time":17.28289475},
{"learn":[0.08096434291],"iteration":638,"passed_time":31.64602513,"remaining_time":17.234455},
{"learn":[0.08088413708],"iteration":639,"passed_time":31.69743671,"remaining_time":17.18595397},
{"learn":[0.08083531233],"iteration":640,"passed_time":31.7473192,"remaining_time":17.13661848},
{"learn":[0.08071428125],"iteration":641,"passed_time":31.7950022,"remaining_time":17.08609931},
{"learn":[0.08065750393],"iteration":642,"passed_time":31.85110118,"remaining_time":17.04009146},
{"learn":[0.08049165927],"iteration":643,"passed_time":31.89656649,"remaining_time":16.98838867},
{"learn":[0.0804173754],"iteration":644,"passed_time":31.94491301,"remaining_time":16.93823294},
{"learn":[0.08027711311],"iteration":645,"passed_time":31.99976552,"remaining_time":16.89151709},
{"learn":[0.08005261342],"iteration":646,"passed_time":32.05187046,"remaining_time":16.84333223},
{"learn":[0.08002223924],"iteration":647,"passed_time":32.09733945,"remaining_time":16.79166369},
{"learn":[0.07991812651],"iteration":648,"passed_time":32.14628479,"remaining_time":16.74182474},
{"learn":[0.07985526095],"iteration":649,"passed_time":32.19470958,"remaining_time":16.69171866},
{"learn":[0.07978633776],"iteration":650,"passed_time":32.2466623,"remaining_time":16.6434386},
{"learn":[0.07963878193],"iteration":651,"passed_time":32.29915495,"remaining_time":16.59542471},
{"learn":[0.07957357361],"iteration":652,"passed_time":32.34747159,"remaining_time":16.54526112},
{"learn":[0.07950134845],"iteration":653,"passed_time":32.39671351,"remaining_time":16.49557431},
{"learn":[0.0794368862],"iteration":654,"passed_time":32.44600392,"remaining_time":16.44591344},
{"learn":[0.07934742274],"iteration":655,"passed_time":32.48689444,"remaining_time":16.39201533},
{"learn":[0.07917662553],"iteration":656,"passed_time":32.53686994,"remaining_time":16.34272006},
{"learn":[0.079098682],"iteration":657,"passed_time":32.58249155,"remaining_time":16.29124577},
{"learn":[0.07896392257],"iteration":658,"passed_time":32.63607283,"remaining_time":16.24375097},
{"learn":[0.0789147764],"iteration":659,"passed_time":32.68553758,"remaining_time":16.19419817},
{"learn":[0.07876793174],"iteration":660,"passed_time":32.7287731,"remaining_time":16.14157342},
{"learn":[0.07872676712],"iteration":661,"passed_time":32.77201327,"remaining_time":16.08897932},
{"learn":[0.07865943051],"iteration":662,"passed_time":32.81785461,"remaining_time":16.0376846},
{"learn":[0.07862663505],"iteration":663,"passed_time":32.85719926,"remaining_time":15.98324602},
{"learn":[0.07855801435],"iteration":664,"passed_time":32.90508087,"remaining_time":15.93298653},
{"learn":[0.07843536123],"iteration":665,"passed_time":32.94878395,"remaining_time":15.88072019},
{"learn":[0.07831749914],"iteration":666,"passed_time":32.99534837,"remaining_time":15.82985229},
{"learn":[0.07807670225],"iteration":667,"passed_time":33.03903844,"remaining_time":15.77762465},
{"learn":[0.07800100181],"iteration":668,"passed_time":33.07925974,"remaining_time":15.72377369},
{"learn":[0.07796287383],"iteration":669,"passed_time":33.11803602,"remaining_time":15.66927973},
{"learn":[0.07784961203],"iteration":670,"passed_time":33.16010223,"remaining_time":15.61638197},
{"learn":[0.07782621732],"iteration":671,"passed_time":33.17631359,"remaining_time":15.551397},
{"learn":[0.07779206526],"iteration":672,"passed_time":33.21116686,"remaining_time":15.49525467},
{"learn":[0.07770010127],"iteration":673,"passed_time":33.25013849,"remaining_time":15.44108805},
{"learn":[0.07758513956],"iteration":674,"passed_time":33.28942885,"remaining_time":15.38711378},
{"learn":[0.07754942879],"iteration":675,"passed_time":33.32975712,"remaining_time":15.33366045},
{"learn":[0.07739517398],"iteration":676,"passed_time":33.37905396,"remaining_time":15.28435263},
{"learn":[0.0772097302],"iteration":677,"passed_time":33.43115811,"remaining_time":15.23632427},
{"learn":[0.07712748767],"iteration":678,"passed_time":33.4771054,"remaining_time":15.18549111},
{"learn":[0.0768710479],"iteration":679,"passed_time":33.52826714,"remaining_time":15.13702649},
{"learn":[0.07662100374],"iteration":680,"passed_time":33.57584986,"remaining_time":15.08694575},
{"learn":[0.07648956434],"iteration":681,"passed_time":33.62125736,"remaining_time":15.03589955},
{"learn":[0.07645359955],"iteration":682,"passed_time":33.67370723,"remaining_time":14.98800439},
{"learn":[0.07613540796],"iteration":683,"passed_time":33.7251477,"remaining_time":14.93964876},
{"learn":[0.07606125943],"iteration":684,"passed_time":33.7771398,"remaining_time":14.89152733},
{"learn":[0.07599562865],"iteration":685,"passed_time":33.82905626,"remaining_time":14.84336142},
{"learn":[0.07588777631],"iteration":686,"passed_time":33.88234796,"remaining_time":14.79578513},
{"learn":[0.07585228232],"iteration":687,"passed_time":33.92788207,"remaining_time":14.74482084},
{"learn":[0.07574360565],"iteration":688,"passed_time":33.97634165,"remaining_time":14.69513761},
{"learn":[0.07565499697],"iteration":689,"passed_time":34.02866881,"remaining_time":14.64712266},
{"learn":[0.07549175979],"iteration":690,"passed_time":34.08009074,"remaining_time":14.59870747},
{"learn":[0.0754436405],"iteration":691,"passed_time":34.12877829,"remaining_time":14.54911791},
{"learn":[0.0753648018],"iteration":692,"passed_time":34.17831627,"remaining_time":14.49989175},
{"learn":[0.07527829726],"iteration":693,"passed_time":34.22669254,"remaining_time":14.45017423},
{"learn":[0.07517708348],"iteration":694,"passed_time":34.27511414,"remaining_time":14.40047961},
{"learn":[0.07505608274],"iteration":695,"passed_time":34.32619578,"remaining_time":14.35190082},
{"learn":[0.07498621779],"iteration":696,"passed_time":34.37833672,"remaining_time":14.3037556},
{"learn":[0.07487085036],"iteration":697,"passed_time":34.42086547,"remaining_time":14.25161908},
{"learn":[0.07480569231],"iteration":698,"passed_time":34.47107842,"remaining_time":14.20267609},
{"learn":[0.07470709749],"iteration":699,"passed_time":34.51644665,"remaining_time":14.15174313},
{"learn":[0.0746152325],"iteration":700,"passed_time":34.56327773,"remaining_time":14.10142287},
{"learn":[0.07457390802],"iteration":701,"passed_time":34.61165305,"remaining_time":14.05173949},
{"learn":[0.07446865734],"iteration":702,"passed_time":34.66281051,"remaining_time":14.00318376},
{"learn":[0.0743959279],"iteration":703,"passed_time":34.71388261,"remaining_time":13.95458633},
{"learn":[0.07430547504],"iteration":704,"passed_time":34.75717571,"remaining_time":13.90287028},
{"learn":[0.07423143165],"iteration":705,"passed_time":34.80889574,"remaining_time":13.85453216},
{"learn":[0.07417939461],"iteration":706,"passed_time":34.85835487,"remaining_time":13.80528906},
{"learn":[0.07403110961],"iteration":707,"passed_time":34.91107927,"remaining_time":13.75733208},
{"learn":[0.07396835501],"iteration":708,"passed_time":34.9619661,"remaining_time":13.70864115},
{"learn":[0.07388878928],"iteration":709,"passed_time":35.01116262,"remaining_time":13.65928457},
{"learn":[0.07388203272],"iteration":710,"passed_time":35.01535216,"remaining_time":13.59245738},
{"learn":[0.07383456896],"iteration":711,"passed_time":35.0616868,"remaining_time":13.54208409},
{"learn":[0.0737728048],"iteration":712,"passed_time":35.10851826,"remaining_time":13.49191305},
{"learn":[0.07369351159],"iteration":713,"passed_time":35.15771885,"remaining_time":13.44265721},
{"learn":[0.07358540686],"iteration":714,"passed_time":35.21192336,"remaining_time":13.39530511},
{"learn":[0.07344592972],"iteration":715,"passed_time":35.26231881,"remaining_time":13.34649217},
{"learn":[0.0733703049],"iteration":716,"passed_time":35.3089365,"remaining_time":13.29625224},
{"learn":[0.07329045205],"iteration":717,"passed_time":35.35644353,"remaining_time":13.24635559},
{"learn":[0.07316467037],"iteration":718,"passed_time":35.4106703,"remaining_time":13.19897029},
{"learn":[0.07307681715],"iteration":719,"passed_time":35.46154737,"remaining_time":13.15032382},
{"learn":[0.0730182722],"iteration":720,"passed_time":35.51048659,"remaining_time":13.10095622},
{"learn":[0.07298291859],"iteration":721,"passed_time":35.56100013,"remaining_time":13.05216764},
{"learn":[0.07292331592],"iteration":722,"passed_time":35.61306421,"remaining_time":13.00394046},
{"learn":[0.07286120553],"iteration":723,"passed_time":35.66253707,"remaining_time":12.95476139},
{"learn":[0.07279821007],"iteration":724,"passed_time":35.70893761,"remaining_time":12.90447125},
{"learn":[0.07272998202],"iteration":725,"passed_time":35.75911193,"remaining_time":12.8555485},
{"learn":[0.07265832671],"iteration":726,"passed_time":35.81531871,"remaining_time":12.80877973},
{"learn":[0.07257328249],"iteration":727,"passed_time":35.86640259,"remaining_time":12.76016246},
{"learn":[0.07251641083],"iteration":728,"passed_time":35.92181374,"remaining_time":12.71306988},
{"learn":[0.07246544633],"iteration":729,"passed_time":35.97368976,"remaining_time":12.66470996},
{"learn":[0.07234903726],"iteration":730,"passed_time":36.02353384,"remaining_time":12.61562881},
{"learn":[0.07224104711],"iteration":731,"passed_time":36.07528904,"remaining_time":12.56721135},
{"learn":[0.07221175596],"iteration":732,"passed_time":36.1274918,"remaining_time":12.51893986},
{"learn":[0.07217326265],"iteration":733,"passed_time":36.18134567,"remaining_time":12.47122678},
{"learn":[0.07204289046],"iteration":734,"passed_time":36.23479414,"remaining_time":12.42335799},
{"learn":[0.07195914548],"iteration":735,"passed_time":36.28424652,"remaining_time":12.37411124},
{"learn":[0.07188802298],"iteration":736,"passed_time":36.33527299,"remaining_time":12.32539789},
{"learn":[0.07183632421],"iteration":737,"passed_time":36.38391606,"remaining_time":12.27587412},
{"learn":[0.07179224018],"iteration":738,"passed_time":36.43655096,"remaining_time":12.22769234},
{"learn":[0.07175018],"iteration":739,"passed_time":36.48358278,"remaining_time":12.17762831},
{"learn":[0.07168583014],"iteration":740,"passed_time":36.5313843,"remaining_time":12.12782799},
{"learn":[0.07161219982],"iteration":741,"passed_time":36.58146167,"remaining_time":12.07878451},
{"learn":[0.07155430541],"iteration":742,"passed_time":36.63216772,"remaining_time":12.02994472},
{"learn":[0.07149911402],"iteration":743,"passed_time":36.67912059,"remaining_time":11.97987406},
{"learn":[0.07149624761],"iteration":744,"passed_time":36.68237257,"remaining_time":11.91561632},
{"learn":[0.07141032846],"iteration":745,"passed_time":36.72947306,"remaining_time":11.86568768},
{"learn":[0.07125625414],"iteration":746,"passed_time":36.7831957,"remaining_time":11.8178942},
{"learn":[0.07109198344],"iteration":747,"passed_time":36.83800296,"remaining_time":11.77043143},
{"learn":[0.07099729441],"iteration":748,"passed_time":36.88995974,"remaining_time":11.72204328},
{"learn":[0.07091487018],"iteration":749,"passed_time":36.93537729,"remaining_time":11.67157922},
{"learn":[0.07085627348],"iteration":750,"passed_time":36.97938359,"remaining_time":11.62068512},
{"learn":[0.07077859743],"iteration":751,"passed_time":37.0252279,"remaining_time":11.57038372},
{"learn":[0.07072260377],"iteration":752,"passed_time":37.07697275,"remaining_time":11.52192779},
{"learn":[0.07064867909],"iteration":753,"passed_time":37.12888155,"remaining_time":11.4735138},
{"learn":[0.07056591757],"iteration":754,"passed_time":37.1812678,"remaining_time":11.42523726},
{"learn":[0.07047547728],"iteration":755,"passed_time":37.22828456,"remaining_time":11.37530917},
{"learn":[0.07042901921],"iteration":756,"passed_time":37.27851696,"remaining_time":11.32636579},
{"learn":[0.07020861958],"iteration":757,"passed_time":37.32846749,"remaining_time":11.27733385},
{"learn":[0.07015002272],"iteration":758,"passed_time":37.38251875,"remaining_time":11.22953132},
{"learn":[0.06995291248],"iteration":759,"passed_time":37.42554342,"remaining_time":11.17841889},
{"learn":[0.06987117055],"iteration":760,"passed_time":37.47017301,"remaining_time":11.12780434},
{"learn":[0.06974500665],"iteration":761,"passed_time":37.51496579,"remaining_time":11.07725368},
{"learn":[0.06971954446],"iteration":762,"passed_time":37.55993789,"remaining_time":11.02677076},
{"learn":[0.06960991675],"iteration":763,"passed_time":37.60191079,"remaining_time":10.97542684},
{"learn":[0.06947574419],"iteration":764,"passed_time":37.64402589,"remaining_time":10.92414869},
{"learn":[0.06942398977],"iteration":765,"passed_time":37.68434742,"remaining_time":10.872377},
{"learn":[0.06935774239],"iteration":766,"passed_time":37.72127607,"remaining_time":10.81966198},
{"learn":[0.06922668494],"iteration":767,"passed_time":37.770284,"remaining_time":10.77043255},
{"learn":[0.06916400695],"iteration":768,"passed_time":37.81157363,"remaining_time":10.71901567},
{"learn":[0.06908548785],"iteration":769,"passed_time":37.85206059,"remaining_time":10.66739889},
{"learn":[0.06892810256],"iteration":770,"passed_time":37.8981335,"remaining_time":10.61737592},
{"learn":[0.06887022993],"iteration":771,"passed_time":37.94277551,"remaining_time":10.56696468},
{"learn":[0.06879785237],"iteration":772,"passed_time":37.98041785,"remaining_time":10.51463056},
{"learn":[0.06876114315],"iteration":773,"passed_time":38.02771398,"remaining_time":10.46499106},
{"learn":[0.06870275307],"iteration":774,"passed_time":38.06841734,"remaining_time":10.41355416},
{"learn":[0.06861069853],"iteration":775,"passed_time":38.11399064,"remaining_time":10.3634691},
{"learn":[0.06854882714],"iteration":776,"passed_time":38.16109549,"remaining_time":10.31380959},
{"learn":[0.06850844152],"iteration":777,"passed_time":38.21142928,"remaining_time":10.26502406},
{"learn":[0.06844109234],"iteration":778,"passed_time":38.2645157,"remaining_time":10.21696953},
{"learn":[0.06830789519],"iteration":779,"passed_time":38.31486899,"remaining_time":10.16817677},
{"learn":[0.06817737494],"iteration":780,"passed_time":38.3585879,"remaining_time":10.1176301},
{"learn":[0.06816090318],"iteration":781,"passed_time":38.36290132,"remaining_time":10.05677081},
{"learn":[0.06806106043],"iteration":782,"passed_time":38.40998939,"remaining_time":10.0072003},
{"learn":[0.06802993573],"iteration":783,"passed_time":38.46220706,"remaining_time":9.958964329},
{"learn":[0.06797356632],"iteration":784,"passed_time":38.51262514,"remaining_time":9.910255133},
{"learn":[0.06797061717],"iteration":785,"passed_time":38.5150092,"remaining_time":9.849258077},
{"learn":[0.0679437839],"iteration":786,"passed_time":38.56703454,"remaining_time":9.801025296},
{"learn":[0.06790314106],"iteration":787,"passed_time":38.61633644,"remaining_time":9.752095115},
{"learn":[0.06781696058],"iteration":788,"passed_time":38.66712921,"remaining_time":9.703538128},
{"learn":[0.0677807564],"iteration":789,"passed_time":38.7211145,"remaining_time":9.65577159},
{"learn":[0.06778034948],"iteration":790,"passed_time":38.72295611,"remaining_time":9.59506877},
{"learn":[0.06773086955],"iteration":791,"passed_time":38.77689007,"remaining_time":9.547340357},
{"learn":[0.06766723975],"iteration":792,"passed_time":38.82505506,"remaining_time":9.49818497},
{"learn":[0.06760926274],"iteration":793,"passed_time":38.87715923,"remaining_time":9.449989587},
{"learn":[0.06747925379],"iteration":794,"passed_time":38.92690258,"remaining_time":9.401214207},
{"learn":[0.06734303021],"iteration":795,"passed_time":38.97483999,"remaining_time":9.352003064},
{"learn":[0.06728983463],"iteration":796,"passed_time":39.02414516,"remaining_time":9.30312118},
{"learn":[0.06722873609],"iteration":797,"passed_time":39.07859259,"remaining_time":9.255456139},
{"learn":[0.06716603686],"iteration":798,"passed_time":39.12885198,"remaining_time":9.2067887},
{"learn":[0.06700163407],"iteration":799,"passed_time":39.18288005,"remaining_time":9.158998211},
{"learn":[0.06694755424],"iteration":800,"passed_time":39.23302943,"remaining_time":9.110291478},
{"learn":[0.06690458736],"iteration":801,"passed_time":39.27445691,"remaining_time":9.059569238},
{"learn":[0.0668316259],"iteration":802,"passed_time":39.3145678,"remaining_time":9.008568462},
{"learn":[0.06674910322],"iteration":803,"passed_time":39.34814032,"remaining_time":8.956106565},
{"learn":[0.06667835955],"iteration":804,"passed_time":39.39949448,"remaining_time":8.907711795},
{"learn":[0.06666530846],"iteration":805,"passed_time":39.44577907,"remaining_time":8.858171231},
{"learn":[0.0665882995],"iteration":806,"passed_time":39.48640871,"remaining_time":8.807377408},
{"learn":[0.06647813042],"iteration":807,"passed_time":39.53581893,"remaining_time":8.758553947},
{"learn":[0.06641188287],"iteration":808,"passed_time":39.57770029,"remaining_time":8.708072498},
{"learn":[0.06635580739],"iteration":809,"passed_time":39.62559597,"remaining_time":8.658926527},
{"learn":[0.0663210587],"iteration":810,"passed_time":39.67292365,"remaining_time":8.609660373},
{"learn":[0.06625963484],"iteration":811,"passed_time":39.71417513,"remaining_time":8.559089469},
{"learn":[0.06619300051],"iteration":812,"passed_time":39.75427944,"remaining_time":8.508295968},
{"learn":[0.06599158348],"iteration":813,"passed_time":39.79626701,"remaining_time":8.457928985},
{"learn":[0.06591359172],"iteration":814,"passed_time":39.83446867,"remaining_time":8.406783571},
{"learn":[0.06588970244],"iteration":815,"passed_time":39.88275861,"remaining_time":8.357783973},
{"learn":[0.06581253955],"iteration":816,"passed_time":39.92331974,"remaining_time":8.307177914},
{"learn":[0.06570926872],"iteration":817,"passed_time":39.96659091,"remaining_time":8.257156312},
{"learn":[0.06561755316],"iteration":818,"passed_time":40.02012792,"remaining_time":8.209257009},
{"learn":[0.0655413816],"iteration":819,"passed_time":40.06677728,"remaining_time":8.159941226},
{"learn":[0.0654517468],"iteration":820,"passed_time":40.11226212,"remaining_time":8.110396483},
{"learn":[0.06537091607],"iteration":821,"passed_time":40.16707358,"remaining_time":8.062733747},
{"learn":[0.06524743001],"iteration":822,"passed_time":40.21545506,"remaining_time":8.013772332},
{"learn":[0.06512355201],"iteration":823,"passed_time":40.26975292,"remaining_time":7.965982677},
{"learn":[0.06508964378],"iteration":824,"passed_time":40.32077712,"remaining_time":7.917534417},
{"learn":[0.06497941707],"iteration":825,"passed_time":40.37340939,"remaining_time":7.869393355},
{"learn":[0.0649102365],"iteration":826,"passed_time":40.4205927,"remaining_time":7.820187221},
{"learn":[0.06486929902],"iteration":827,"passed_time":40.47028069,"remaining_time":7.771466944},
{"learn":[0.0648134835],"iteration":828,"passed_time":40.51609856,"remaining_time":7.722006722},
{"learn":[0.06473427755],"iteration":829,"passed_time":40.56309363,"remaining_time":7.672777951},
{"learn":[0.06465436285],"iteration":830,"passed_time":40.60814415,"remaining_time":7.623189515},
{"learn":[0.06447105559],"iteration":831,"passed_time":40.6542272,"remaining_time":7.573804347},
{"learn":[0.06440039677],"iteration":832,"passed_time":40.70453284,"remaining_time":7.525207751},
{"learn":[0.06439935062],"iteration":833,"passed_time":40.70713711,"remaining_time":7.467856088},
{"learn":[0.06433268984],"iteration":834,"passed_time":40.76168445,"remaining_time":7.420091062},
{"learn":[0.06428656884],"iteration":835,"passed_time":40.81632683,"remaining_time":7.372326976},
{"learn":[0.06418336797],"iteration":836,"passed_time":40.86913229,"remaining_time":7.324217257},
{"learn":[0.06405031971],"iteration":837,"passed_time":40.91510722,"remaining_time":7.274881833},
{"learn":[0.06385436597],"iteration":838,"passed_time":40.96801301,"remaining_time":7.226777028},
{"learn":[0.06379009223],"iteration":839,"passed_time":41.01433641,"remaining_time":7.177508871},
{"learn":[0.06375640357],"iteration":840,"passed_time":41.06817253,"remaining_time":7.12955195},
{"learn":[0.06358801541],"iteration":841,"passed_time":41.11109894,"remaining_time":7.079702312},
{"learn":[0.06350745358],"iteration":842,"passed_time":41.15767646,"remaining_time":7.030492777},
{"learn":[0.0635046729],"iteration":843,"passed_time":41.16171224,"remaining_time":6.974081576},
{"learn":[0.0634549189],"iteration":844,"passed_time":41.21296078,"remaining_time":6.925728321},
{"learn":[0.06339287925],"iteration":845,"passed_time":41.26114808,"remaining_time":6.876858014},
{"learn":[0.06327128731],"iteration":846,"passed_time":41.3134678,"remaining_time":6.828672364},
{"learn":[0.06320212644],"iteration":847,"passed_time":41.36703446,"remaining_time":6.780681356},
{"learn":[0.06315024416],"iteration":848,"passed_time":41.41731034,"remaining_time":6.732142317},
{"learn":[0.06312107872],"iteration":849,"passed_time":41.45809524,"remaining_time":6.682069467},
{"learn":[0.06310001727],"iteration":850,"passed_time":41.50004368,"remaining_time":6.632204395},
{"learn":[0.06304330246],"iteration":851,"passed_time":41.5390075,"remaining_time":6.58188499},
{"learn":[0.06298899028],"iteration":852,"passed_time":41.57809657,"remaining_time":6.531611889},
{"learn":[0.06292488512],"iteration":853,"passed_time":41.61509413,"remaining_time":6.48103925},
{"learn":[0.06289781253],"iteration":854,"passed_time":41.65926326,"remaining_time":6.431605556},
{"learn":[0.06278654631],"iteration":855,"passed_time":41.69958832,"remaining_time":6.381595876},
{"learn":[0.06272489987],"iteration":856,"passed_time":41.73849325,"remaining_time":6.331393376},
{"learn":[0.06267673125],"iteration":857,"passed_time":41.77947289,"remaining_time":6.28152914},
{"learn":[0.06264948941],"iteration":858,"passed_time":41.81743954,"remaining_time":6.231236626},
{"learn":[0.0625835449],"iteration":859,"passed_time":41.86072024,"remaining_time":6.181757524},
{"learn":[0.06249461792],"iteration":860,"passed_time":41.8998258,"remaining_time":6.131681825},
{"learn":[0.06241461037],"iteration":861,"passed_time":41.94785386,"remaining_time":6.082925443},
{"learn":[0.06235459254],"iteration":862,"passed_time":41.99762218,"remaining_time":6.0344208},
{"learn":[0.06228209288],"iteration":863,"passed_time":42.04189007,"remaining_time":5.985130184},
{"learn":[0.06223083264],"iteration":864,"passed_time":42.0855364,"remaining_time":5.935763516},
{"learn":[0.06214676448],"iteration":865,"passed_time":42.13302056,"remaining_time":5.886946291},
{"learn":[0.06211883573],"iteration":866,"passed_time":42.17176344,"remaining_time":5.836922276},
{"learn":[0.06204631065],"iteration":867,"passed_time":42.21060431,"remaining_time":5.786937687},
{"learn":[0.06190679795],"iteration":868,"passed_time":42.2615394,"remaining_time":5.738621},
{"learn":[0.06182647451],"iteration":869,"passed_time":42.31489787,"remaining_time":5.690624196},
{"learn":[0.06169979536],"iteration":870,"passed_time":42.35657521,"remaining_time":5.641059385},
{"learn":[0.06157886525],"iteration":871,"passed_time":42.40874348,"remaining_time":5.592896216},
{"learn":[0.06152458303],"iteration":872,"passed_time":42.45465404,"remaining_time":5.543906714},
{"learn":[0.06143692083],"iteration":873,"passed_time":42.50408717,"remaining_time":5.495379691},
{"learn":[0.06139088034],"iteration":874,"passed_time":42.56428421,"remaining_time":5.448228379},
{"learn":[0.06126778347],"iteration":875,"passed_time":42.6107121,"remaining_time":5.399302561},
{"learn":[0.06123806668],"iteration":876,"passed_time":42.66047894,"remaining_time":5.350801235},
{"learn":[0.0610414307],"iteration":877,"passed_time":42.71336961,"remaining_time":5.302684838},
{"learn":[0.06091419387],"iteration":878,"passed_time":42.76338171,"remaining_time":5.254203896},
{"learn":[0.06082063583],"iteration":879,"passed_time":42.81126647,"remaining_time":5.205460809},
{"learn":[0.06079050932],"iteration":880,"passed_time":42.85985426,"remaining_time":5.156804258},
{"learn":[0.06071791773],"iteration":881,"passed_time":42.91419054,"remaining_time":5.108832207},
{"learn":[0.0607052599],"iteration":882,"passed_time":42.91850596,"remaining_time":5.054954269},
{"learn":[0.06065194782],"iteration":883,"passed_time":42.9697658,"remaining_time":5.006658232},
{"learn":[0.06062313415],"iteration":884,"passed_time":43.01451999,"remaining_time":4.957605693},
{"learn":[0.06057597332],"iteration":885,"passed_time":43.06701137,"remaining_time":4.909444863},
{"learn":[0.060539812],"iteration":886,"passed_time":43.11551477,"remaining_time":4.860824664},
{"learn":[0.06038599144],"iteration":887,"passed_time":43.16644812,"remaining_time":4.812475635},
{"learn":[0.06024156427],"iteration":888,"passed_time":43.21583855,"remaining_time":4.763950706},
{"learn":[0.0601581805],"iteration":889,"passed_time":43.26834334,"remaining_time":4.715763263},
{"learn":[0.060114575],"iteration":890,"passed_time":43.31438671,"remaining_time":4.666869949},
{"learn":[0.06004482309],"iteration":891,"passed_time":43.37032593,"remaining_time":4.619036954},
{"learn":[0.059992394],"iteration":892,"passed_time":43.41815136,"remaining_time":4.570331722},
{"learn":[0.05992734242],"iteration":893,"passed_time":43.47034342,"remaining_time":4.522082705},
{"learn":[0.05987515276],"iteration":894,"passed_time":43.52002134,"remaining_time":4.473566439},
{"learn":[0.05985232444],"iteration":895,"passed_time":43.5692261,"remaining_time":4.424999526},
{"learn":[0.05971617341],"iteration":896,"passed_time":43.62050707,"remaining_time":4.376639506},
{"learn":[0.05960103927],"iteration":897,"passed_time":43.6670579,"remaining_time":4.327804179},
{"learn":[0.05954306012],"iteration":898,"passed_time":43.71304978,"remaining_time":4.278919222},
{"learn":[0.05946198387],"iteration":899,"passed_time":43.75900935,"remaining_time":4.230037571},
{"learn":[0.05941149927],"iteration":900,"passed_time":43.80988644,"remaining_time":4.18163178},
{"learn":[0.05924422113],"iteration":901,"passed_time":43.85924517,"remaining_time":4.133077427},
{"learn":[0.05919609054],"iteration":902,"passed_time":43.91625502,"remaining_time":4.085233025},
{"learn":[0.05908895261],"iteration":903,"passed_time":43.97192932,"remaining_time":4.037245723},
{"learn":[0.05902472386],"iteration":904,"passed_time":44.02627504,"remaining_time":3.989121054},
{"learn":[0.05892914993],"iteration":905,"passed_time":44.07487957,"remaining_time":3.940469366},
{"learn":[0.05888803667],"iteration":906,"passed_time":44.12777082,"remaining_time":3.892195883},
{"learn":[0.05881709347],"iteration":907,"passed_time":44.17994543,"remaining_time":3.843849878},
{"learn":[0.05875154935],"iteration":908,"passed_time":44.22719116,"remaining_time":3.795072509},
{"learn":[0.0587166521],"iteration":909,"passed_time":44.27503641,"remaining_time":3.746349234},
{"learn":[0.05869489106],"iteration":910,"passed_time":44.32721191,"remaining_time":3.697989138},
{"learn":[0.05864275957],"iteration":911,"passed_time":44.39052071,"remaining_time":3.650536242},
{"learn":[0.05860254539],"iteration":912,"passed_time":44.46352406,"remaining_time":3.603834371},
{"learn":[0.05843647029],"iteration":913,"passed_time":44.51743444,"remaining_time":3.555550016},
{"learn":[0.05840145703],"iteration":914,"passed_time":44.5701268,"remaining_time":3.507157519},
{"learn":[0.05828254156],"iteration":915,"passed_time":44.61755693,"remaining_time":3.458347753},
{"learn":[0.05823388765],"iteration":916,"passed_time":44.66664898,"remaining_time":3.409667861},
{"learn":[0.05820241629],"iteration":917,"passed_time":44.71291373,"remaining_time":3.360774561},
{"learn":[0.05818172296],"iteration":918,"passed_time":44.76416553,"remaining_time":3.312255991},
{"learn":[0.05807769871],"iteration":919,"passed_time":44.80653524,"remaining_time":3.263084632},
{"learn":[0.05796740296],"iteration":920,"passed_time":44.84825638,"remaining_time":3.213881565},
{"learn":[0.0578533373],"iteration":921,"passed_time":44.88994872,"remaining_time":3.164692698},
{"learn":[0.05779838282],"iteration":922,"passed_time":44.93988731,"remaining_time":3.116091861},
{"learn":[0.05776451449],"iteration":923,"passed_time":44.98573011,"remaining_time":3.067208871},
{"learn":[0.05774553929],"iteration":924,"passed_time":45.0274744,"remaining_time":3.018057744},
{"learn":[0.05772494452],"iteration":925,"passed_time":45.08082287,"remaining_time":2.969687036},
{"learn":[0.05756255943],"iteration":926,"passed_time":45.12150703,"remaining_time":2.920485892},
{"learn":[0.05746277408],"iteration":927,"passed_time":45.16397835,"remaining_time":2.871416727},
{"learn":[0.05739595706],"iteration":928,"passed_time":45.20767149,"remaining_time":2.822438048},
{"learn":[0.05730490125],"iteration":929,"passed_time":45.25623495,"remaining_time":2.773769239},
{"learn":[0.05724410882],"iteration":930,"passed_time":45.30938447,"remaining_time":2.725376509},
{"learn":[0.05720249316],"iteration":931,"passed_time":45.35347976,"remaining_time":2.676439256},
{"learn":[0.05711409549],"iteration":932,"passed_time":45.39314895,"remaining_time":2.627256209},
{"learn":[0.05706208824],"iteration":933,"passed_time":45.43029462,"remaining_time":2.577950337},
{"learn":[0.05699860557],"iteration":934,"passed_time":45.47900605,"remaining_time":2.529313706},
{"learn":[0.05697400414],"iteration":935,"passed_time":45.53156572,"remaining_time":2.480886593},
{"learn":[0.05694544248],"iteration":936,"passed_time":45.57963503,"remaining_time":2.432211048},
{"learn":[0.05687239217],"iteration":937,"passed_time":45.644157,"remaining_time":2.384396261},
{"learn":[0.05682619703],"iteration":938,"passed_time":45.70274484,"remaining_time":2.336242548},
{"learn":[0.05676590723],"iteration":939,"passed_time":45.75790613,"remaining_time":2.287895307},
{"learn":[0.0567650019],"iteration":940,"passed_time":45.76041908,"remaining_time":2.236959913},
{"learn":[0.05661187686],"iteration":941,"passed_time":45.81289891,"remaining_time":2.188514279},
{"learn":[0.05647454551],"iteration":942,"passed_time":45.86121634,"remaining_time":2.139865874},
{"learn":[0.05636572094],"iteration":943,"passed_time":45.91097739,"remaining_time":2.091283928},
{"learn":[0.05625467968],"iteration":944,"passed_time":45.95636897,"remaining_time":2.042505288},
{"learn":[0.05611939194],"iteration":945,"passed_time":46.00129211,"remaining_time":1.993713506},
{"learn":[0.05608903318],"iteration":946,"passed_time":46.05090676,"remaining_time":1.945128058},
{"learn":[0.05605222968],"iteration":947,"passed_time":46.0995708,"remaining_time":1.89650133},
{"learn":[0.05599866395],"iteration":948,"passed_time":46.14960843,"remaining_time":1.847929526},
{"learn":[0.05590814797],"iteration":949,"passed_time":46.20234747,"remaining_time":1.799459849},
{"learn":[0.05581748783],"iteration":950,"passed_time":46.25974641,"remaining_time":1.751157593},
{"learn":[0.05577962968],"iteration":951,"passed_time":46.30493309,"remaining_time":1.702387246},
{"learn":[0.05571994656],"iteration":952,"passed_time":46.35014534,"remaining_time":1.653625332},
{"learn":[0.05565464989],"iteration":953,"passed_time":46.3939043,"remaining_time":1.604820589},
{"learn":[0.05557739388],"iteration":954,"passed_time":46.44386384,"remaining_time":1.556234181},
{"learn":[0.0554711206],"iteration":955,"passed_time":46.49114076,"remaining_time":1.507557912},
{"learn":[0.05544150955],"iteration":956,"passed_time":46.54312806,"remaining_time":1.459032228},
{"learn":[0.05538593961],"iteration":957,"passed_time":46.59161504,"remaining_time":1.410393357},
{"learn":[0.05533407203],"iteration":958,"passed_time":46.63890881,"remaining_time":1.361719965},
{"learn":[0.0552644914],"iteration":959,"passed_time":46.69181673,"remaining_time":1.313207346},
{"learn":[0.05520427574],"iteration":960,"passed_time":46.74264029,"remaining_time":1.264629186},
{"learn":[0.05514146676],"iteration":961,"passed_time":46.7887459,"remaining_time":1.21592375},
{"learn":[0.05507014247],"iteration":962,"passed_time":46.83869098,"remaining_time":1.167319401},
{"learn":[0.05501026755],"iteration":963,"passed_time":46.88601726,"remaining_time":1.118649789},
{"learn":[0.05492099792],"iteration":964,"passed_time":46.93447118,"remaining_time":1.070008669},
{"learn":[0.05487303712],"iteration":965,"passed_time":46.98255287,"remaining_time":1.021359845},
{"learn":[0.05481808358],"iteration":966,"passed_time":47.03190921,"remaining_time":0.9727385565},
{"learn":[0.0547209056],"iteration":967,"passed_time":47.07869877,"remaining_time":0.9240653685},
{"learn":[0.05466664341],"iteration":968,"passed_time":47.13007468,"remaining_time":0.8754812634},
{"learn":[0.05465188884],"iteration":969,"passed_time":47.1835646,"remaining_time":0.8269284518},
{"learn":[0.05454163788],"iteration":970,"passed_time":47.23109675,"remaining_time":0.7782672997},
{"learn":[0.05446253757],"iteration":971,"passed_time":47.28231674,"remaining_time":0.7296653817},
{"learn":[0.05442931707],"iteration":972,"passed_time":47.3364197,"remaining_time":0.6810995641},
{"learn":[0.05440641083],"iteration":973,"passed_time":47.38187785,"remaining_time":0.6324069939},
{"learn":[0.05431776818],"iteration":974,"passed_time":47.43358469,"remaining_time":0.5837979654},
{"learn":[0.05427253851],"iteration":975,"passed_time":47.48635223,"remaining_time":0.5351945436},
{"learn":[0.05422821527],"iteration":976,"passed_time":47.53879873,"remaining_time":0.4865793115},
{"learn":[0.05420156183],"iteration":977,"passed_time":47.59049272,"remaining_time":0.4379493195},
{"learn":[0.05415295753],"iteration":978,"passed_time":47.63799013,"remaining_time":0.3892787753},
{"learn":[0.05410673051],"iteration":979,"passed_time":47.68878836,"remaining_time":0.3406342026},
{"learn":[0.0540819246],"iteration":980,"passed_time":47.73643408,"remaining_time":0.2919659576},
{"learn":[0.05404196346],"iteration":981,"passed_time":47.79147953,"remaining_time":0.2433374722},
{"learn":[0.05397112392],"iteration":982,"passed_time":47.83736707,"remaining_time":0.1946586656},
{"learn":[0.0538959957],"iteration":983,"passed_time":47.89147104,"remaining_time":0.1460105824},
{"learn":[0.05379710404],"iteration":984,"passed_time":47.9437951,"remaining_time":0.0973478073},
{"learn":[0.05361320185],"iteration":985,"passed_time":47.99530275,"remaining_time":0.04867677764},
{"learn":[0.05353368814],"iteration":986,"passed_time":48.03636107,"remaining_time":0}
]}