{
"meta":{"test_sets":[],"test_metrics":[],"learn_metrics":[{"best_value":"Min","name":"Logloss"}],"launch_mode":"Train","parameters":"","iteration_count":987,"learn_sets":["learn"],"name":"experiment"},
"iterations":[
{"learn":[0.6731710639],"iteration":0,"passed_time":0.200293604,"remaining_time":197.4894936},
{"learn":[0.6549217163],"iteration":1,"passed_time":0.2523458647,"remaining_time":124.2803384},
{"learn":[0.6374785951],"iteration":2,"passed_time":0.2955746778,"remaining_time":96.94849432},
{"learn":[0.6207116854],"iteration":3,"passed_time":0.3444733242,"remaining_time":84.65431942},
{"learn":[0.6050922549],"iteration":4,"passed_time":0.3513320512,"remaining_time":69.00161485},
{"learn":[0.5903825226],"iteration":5,"passed_time":0.3592259084,"remaining_time":58.73343603},
{"learn":[0.5752050505],"iteration":6,"passed_time":0.4070459599,"remaining_time":56.98643438},
{"learn":[0.5623691287],"iteration":7,"passed_time":0.4094228245,"remaining_time":50.10311815},
{"learn":[0.5488466501],"iteration":8,"passed_time":0.4590537928,"remaining_time":49.88384548},
{"learn":[0.5364278546],"iteration":9,"passed_time":0.5107607915,"remaining_time":49.90132933},
{"learn":[0.5238806801],"iteration":10,"passed_time":0.5587347266,"remaining_time":49.57500847},
{"learn":[0.5121969339],"iteration":11,"passed_time":0.6068787079,"remaining_time":49.30889502},
{"learn":[0.5017538171],"iteration":12,"passed_time":0.657095608,"remaining_time":49.23162479},
{"learn":[0.4917340145],"iteration":13,"passed_time":0.7021248229,"remaining_time":48.79767519},
{"learn":[0.48295754],"iteration":14,"passed_time":0.7045862944,"remaining_time":45.65719188},
{"learn":[0.4731451741],"iteration":15,"passed_time":0.7556480787,"remaining_time":45.85839278},
{"learn":[0.4640585282],"iteration":16,"passed_time":0.8035638993,"remaining_time":45.85041073},
{"learn":[0.45549517],"iteration":17,"passed_time":0.8528252876,"remaining_time":45.91042798},
{"learn":[0.4476100218],"iteration":18,"passed_time":0.9038563313,"remaining_time":46.04910151},
{"learn":[0.4397589463],"iteration":19,"passed_time":0.9489634944,"remaining_time":45.88238495},
{"learn":[0.4320049871],"iteration":20,"passed_time":0.9979713119,"remaining_time":45.90668035},
{"learn":[0.4247707605],"iteration":21,"passed_time":1.044812981,"remaining_time":45.82929667},
{"learn":[0.4182905731],"iteration":22,"passed_time":1.098415293,"remaining_time":46.03792794},
{"learn":[0.4122817172],"iteration":23,"passed_time":1.146660955,"remaining_time":46.00977083},
{"learn":[0.4061712999],"iteration":24,"passed_time":1.190819064,"remaining_time":45.8227176},
{"learn":[0.4007079988],"iteration":25,"passed_time":1.241205515,"remaining_time":45.87686537},
{"learn":[0.3950447993],"iteration":26,"passed_time":1.293364977,"remaining_time":45.98631028},
{"learn":[0.3894061886],"iteration":27,"passed_time":1.340803885,"remaining_time":45.92253307},
{"learn":[0.3844708517],"iteration":28,"passed_time":1.390130823,"remaining_time":45.92225271},
{"learn":[0.3795934846],"iteration":29,"passed_time":1.440605799,"remaining_time":45.95532498},
{"learn":[0.3748913002],"iteration":30,"passed_time":1.492102372,"remaining_time":46.01451185},
{"learn":[0.3703927187],"iteration":31,"passed_time":1.537780212,"remaining_time":45.8931282},
{"learn":[0.3663110267],"iteration":32,"passed_time":1.577678958,"remaining_time":45.60926442},
{"learn":[0.3619969139],"iteration":33,"passed_time":1.627762179,"remaining_time":45.62521638},
{"learn":[0.3582654096],"iteration":34,"passed_time":1.67922228,"remaining_time":45.67484602},
{"learn":[0.3548429537],"iteration":35,"passed_time":1.730486855,"remaining_time":45.71369442},
{"learn":[0.3513020944],"iteration":36,"passed_time":1.78044026,"remaining_time":45.71400669},
{"learn":[0.3479654152],"iteration":37,"passed_time":1.831880542,"remaining_time":45.74880618},
{"learn":[0.3442637841],"iteration":38,"passed_time":1.880736644,"remaining_time":45.71636767},
{"learn":[0.341361685],"iteration":39,"passed_time":1.931094103,"remaining_time":45.7186529},
{"learn":[0.3382243632],"iteration":40,"passed_time":1.984180867,"remaining_time":45.7813439},
{"learn":[0.3352244503],"iteration":41,"passed_time":2.034407743,"remaining_time":45.77417422},
{"learn":[0.3321947483],"iteration":42,"passed_time":2.085401402,"remaining_time":45.78183543},
{"learn":[0.3295533401],"iteration":43,"passed_time":2.134060702,"remaining_time":45.73680095},
{"learn":[0.3266567707],"iteration":44,"passed_time":2.184670914,"remaining_time":45.73244446},
{"learn":[0.3239941669],"iteration":45,"passed_time":2.23096878,"remaining_time":45.63786134},
{"learn":[0.3215387953],"iteration":46,"passed_time":2.277574442,"remaining_time":45.55148884},
{"learn":[0.3192472497],"iteration":47,"passed_time":2.322071079,"remaining_time":45.42551548},
{"learn":[0.31694029],"iteration":48,"passed_time":2.368676783,"remaining_time":45.34324127},
{"learn":[0.3153668774],"iteration":49,"passed_time":2.371542002,"remaining_time":44.44269711},
{"learn":[0.312979536],"iteration":50,"passed_time":2.421928352,"remaining_time":44.44950858},
{"learn":[0.3106549226],"iteration":51,"passed_time":2.475134271,"remaining_time":44.50481814},
{"learn":[0.3083883315],"iteration":52,"passed_time":2.525118257,"remaining_time":44.4992538},
{"learn":[0.3064189696],"iteration":53,"passed_time":2.577058496,"remaining_time":44.52584401},
{"learn":[0.304803552],"iteration":54,"passed_time":2.595534118,"remaining_time":43.98250541},
{"learn":[0.3029174183],"iteration":55,"passed_time":2.650876166,"remaining_time":44.07081626},
{"learn":[0.3009450864],"iteration":56,"passed_time":2.697711653,"remaining_time":44.01529539},
{"learn":[0.2989933874],"iteration":57,"passed_time":2.749901897,"remaining_time":44.04584245},
{"learn":[0.2969688895],"iteration":58,"passed_time":2.795560609,"remaining_time":43.97085161},
{"learn":[0.2952062433],"iteration":59,"passed_time":2.853670214,"remaining_time":44.0892048},
{"learn":[0.2938054912],"iteration":60,"passed_time":2.910632001,"remaining_time":44.18434808},
{"learn":[0.2922788325],"iteration":61,"passed_time":2.961539842,"remaining_time":44.18426377},
{"learn":[0.2903501093],"iteration":62,"passed_time":3.007719092,"remaining_time":44.11321335},
{"learn":[0.2881673773],"iteration":63,"passed_time":3.054394372,"remaining_time":44.05009384},
{"learn":[0.2863016889],"iteration":64,"passed_time":3.103259708,"remaining_time":44.0185454},
{"learn":[0.2847828095],"iteration":65,"passed_time":3.15129708,"remaining_time":43.97491834},
{"learn":[0.2833450213],"iteration":66,"passed_time":3.207108595,"remaining_time":44.03790907},
{"learn":[0.2815178725],"iteration":67,"passed_time":3.258624627,"remaining_time":44.03935341},
{"learn":[0.280113492],"iteration":68,"passed_time":3.309107037,"remaining_time":44.02551101},
{"learn":[0.278565337],"iteration":69,"passed_time":3.357898156,"remaining_time":43.98846584},
{"learn":[0.2774371913],"iteration":70,"passed_time":3.411346794,"remaining_time":44.01117836},
{"learn":[0.2761618077],"iteration":71,"passed_time":3.463210112,"remaining_time":44.01162851},
{"learn":[0.2752541574],"iteration":72,"passed_time":3.468938266,"remaining_time":43.43300788},
{"learn":[0.273823001],"iteration":73,"passed_time":3.521357542,"remaining_time":43.44593832},
{"learn":[0.2717010016],"iteration":74,"passed_time":3.573973777,"remaining_time":43.45952112},
{"learn":[0.2702508811],"iteration":75,"passed_time":3.625859839,"remaining_time":43.46260939},
{"learn":[0.2687416567],"iteration":76,"passed_time":3.680187403,"remaining_time":43.49312386},
{"learn":[0.2668617992],"iteration":77,"passed_time":3.7256887,"remaining_time":43.41860292},
{"learn":[0.2656634893],"iteration":78,"passed_time":3.777478948,"remaining_time":43.41709981},
{"learn":[0.2637131761],"iteration":79,"passed_time":3.832629368,"remaining_time":43.45243546},
{"learn":[0.2625703132],"iteration":80,"passed_time":3.881445718,"remaining_time":43.41468914},
{"learn":[0.2619746286],"iteration":81,"passed_time":3.884739493,"remaining_time":42.87425904},
{"learn":[0.2609895307],"iteration":82,"passed_time":3.937596714,"remaining_time":42.88659554},
{"learn":[0.2595619311],"iteration":83,"passed_time":3.988430328,"remaining_time":42.87562603},
{"learn":[0.2582731577],"iteration":84,"passed_time":4.044094262,"remaining_time":42.91497675},
{"learn":[0.2570944653],"iteration":85,"passed_time":4.098583937,"remaining_time":42.93981543},
{"learn":[0.2558663873],"iteration":86,"passed_time":4.142307387,"remaining_time":42.85145572},
{"learn":[0.2547420799],"iteration":87,"passed_time":4.19430525,"remaining_time":42.84864113},
{"learn":[0.25363782],"iteration":88,"passed_time":4.24258531,"remaining_time":42.80720908},
{"learn":[0.2529291636],"iteration":89,"passed_time":4.285404989,"remaining_time":42.71120306},
{"learn":[0.2520593386],"iteration":90,"passed_time":4.33372309,"remaining_time":42.67050427},
{"learn":[0.2509828159],"iteration":91,"passed_time":4.384495593,"remaining_time":42.65351691},
{"learn":[0.2497798397],"iteration":92,"passed_time":4.441488012,"remaining_time":42.69559444},
{"learn":[0.248727996],"iteration":93,"passed_time":4.495297984,"remaining_time":42.70533085},
{"learn":[0.2477282351],"iteration":94,"passed_time":4.547117996,"remaining_time":42.69504476},
{"learn":[0.2459940812],"iteration":95,"passed_time":4.601651768,"remaining_time":42.70908047},
{"learn":[0.244676909],"iteration":96,"passed_time":4.651936578,"remaining_time":42.68271706},
{"learn":[0.2439401649],"iteration":97,"passed_time":4.705657093,"remaining_time":42.6870322},
{"learn":[0.2427054423],"iteration":98,"passed_time":4.75901867,"remaining_time":42.68695535},
{"learn":[0.2418160202],"iteration":99,"passed_time":4.813459068,"remaining_time":42.69538193},
{"learn":[0.2408937119],"iteration":100,"passed_time":4.868487266,"remaining_time":42.70771998},
{"learn":[0.2398255488],"iteration":101,"passed_time":4.924592131,"remaining_time":42.72807878},
{"learn":[0.2388122322],"iteration":102,"passed_time":4.974611236,"remaining_time":42.69472168},
{"learn":[0.2380437809],"iteration":103,"passed_time":5.024661031,"remaining_time":42.66130472},
{"learn":[0.2372931359],"iteration":104,"passed_time":5.077202328,"remaining_time":42.64849956},
{"learn":[0.2361852119],"iteration":105,"passed_time":5.122186538,"remaining_time":42.57213529},
{"learn":[0.2352254027],"iteration":106,"passed_time":5.175460703,"remaining_time":42.56453662},
{"learn":[0.2346940244],"iteration":107,"passed_time":5.226423101,"remaining_time":42.5372769},
{"learn":[0.2335808768],"iteration":108,"passed_time":5.278592122,"remaining_time":42.51930168},
{"learn":[0.2324325755],"iteration":109,"passed_time":5.320697596,"remaining_time":42.42047084},
{"learn":[0.2314651316],"iteration":110,"passed_time":5.3705438,"remaining_time":42.38375107},
{"learn":[0.2305751562],"iteration":111,"passed_time":5.424239457,"remaining_time":42.37687075},
{"learn":[0.2296606019],"iteration":112,"passed_time":5.475971825,"remaining_time":42.35397677},
{"learn":[0.2293193645],"iteration":113,"passed_time":5.481666302,"remaining_time":41.97802353},
{"learn":[0.2283304048],"iteration":114,"passed_time":5.54072393,"remaining_time":42.01314145},
{"learn":[0.2275135611],"iteration":115,"passed_time":5.595253904,"remaining_time":42.01263923},
{"learn":[0.2267179475],"iteration":116,"passed_time":5.649109076,"remaining_time":42.00619569},
{"learn":[0.2262449712],"iteration":117,"passed_time":5.705686344,"remaining_time":42.0189952},
{"learn":[0.2256585958],"iteration":118,"passed_time":5.751450059,"remaining_time":41.95175337},
{"learn":[0.2249525618],"iteration":119,"passed_time":5.799527565,"remaining_time":41.90158665},
{"learn":[0.2235030812],"iteration":120,"passed_time":5.850264036,"remaining_time":41.87048475},
{"learn":[0.2225790451],"iteration":121,"passed_time":5.900210457,"remaining_time":41.83345939},
{"learn":[0.2220672509],"iteration":122,"passed_time":5.9483199,"remaining_time":41.78332027},
{"learn":[0.22130274],"iteration":123,"passed_time":6.000120384,"remaining_time":41.75890235},
{"learn":[0.2205717585],"iteration":124,"passed_time":6.049520857,"remaining_time":41.71749583},
{"learn":[0.2194345395],"iteration":125,"passed_time":6.092153072,"remaining_time":41.62971266},
{"learn":[0.2188353926],"iteration":126,"passed_time":6.143445111,"remaining_time":41.60128185},
{"learn":[0.2180640529],"iteration":127,"passed_time":6.194557846,"remaining_time":41.57129054},
{"learn":[0.2173095931],"iteration":128,"passed_time":6.242409068,"remaining_time":41.51927892},
{"learn":[0.2161863834],"iteration":129,"passed_time":6.298388035,"remaining_time":41.52091189},
{"learn":[0.2149781928],"iteration":130,"passed_time":6.342018622,"remaining_time":41.44097664},
{"learn":[0.2137727914],"iteration":131,"passed_time":6.394592193,"remaining_time":41.41951761},
{"learn":[0.2126951734],"iteration":132,"passed_time":6.448433136,"remaining_time":41.40572856},
{"learn":[0.212193382],"iteration":133,"passed_time":6.501847267,"remaining_time":41.38862477},
{"learn":[0.211415012],"iteration":134,"passed_time":6.552701671,"remaining_time":41.35482832},
{"learn":[0.2107949796],"iteration":135,"passed_time":6.611353437,"remaining_time":41.36957187},
{"learn":[0.2100550111],"iteration":136,"passed_time":6.664351326,"remaining_time":41.34816516},
{"learn":[0.209192736],"iteration":137,"passed_time":6.721734706,"remaining_time":41.35328091},
{"learn":[0.2085028578],"iteration":138,"passed_time":6.773619115,"remaining_time":41.32394971},
{"learn":[0.207763733],"iteration":139,"passed_time":6.829918735,"remaining_time":41.32100835},
{"learn":[0.2072096212],"iteration":140,"passed_time":6.885033625,"remaining_time":41.31020175},
{"learn":[0.2068371322],"iteration":141,"passed_time":6.941193553,"remaining_time":41.30498981},
{"learn":[0.2061470694],"iteration":142,"passed_time":6.993343081,"remaining_time":41.27539553},
{"learn":[0.2050005042],"iteration":143,"passed_time":7.054505617,"remaining_time":41.29825163},
{"learn":[0.2044224098],"iteration":144,"passed_time":7.121451074,"remaining_time":41.35352968},
{"learn":[0.2037214985],"iteration":145,"passed_time":7.174939091,"remaining_time":41.3296149},
{"learn":[0.2028726448],"iteration":146,"passed_time":7.225851149,"remaining_time":41.290578},
{"learn":[0.2021713825],"iteration":147,"passed_time":7.280181059,"remaining_time":41.27075614},
{"learn":[0.2014280043],"iteration":148,"passed_time":7.344736775,"remaining_time":41.30798267},
{"learn":[0.2009376949],"iteration":149,"passed_time":7.395324614,"remaining_time":41.26591134},
{"learn":[0.2002480479],"iteration":150,"passed_time":7.449774159,"remaining_time":41.24510727},
{"learn":[0.1996764283],"iteration":151,"passed_time":7.507240874,"remaining_time":41.24043507},
{"learn":[0.1988740211],"iteration":152,"passed_time":7.567174812,"remaining_time":41.24852153},
{"learn":[0.1984791176],"iteration":153,"passed_time":7.61889094,"remaining_time":41.21127372},
{"learn":[0.1979121742],"iteration":154,"passed_time":7.670167798,"remaining_time":41.17148134},
{"learn":[0.1969012659],"iteration":155,"passed_time":7.722459752,"remaining_time":41.13694906},
{"learn":[0.1962327531],"iteration":156,"passed_time":7.77568491,"remaining_time":41.10712405},
{"learn":[0.1955645305],"iteration":157,"passed_time":7.826609934,"remaining_time":41.0649344},
{"learn":[0.1948933444],"iteration":158,"passed_time":7.88365688,"remaining_time":41.05451507},
{"learn":[0.1942044355],"iteration":159,"passed_time":7.934936915,"remaining_time":41.01370518},
{"learn":[0.1938755835],"iteration":160,"passed_time":7.986499399,"remaining_time":40.97421431},
{"learn":[0.1932772693],"iteration":161,"passed_time":8.031516013,"remaining_time":40.90123896},
{"learn":[0.1927622816],"iteration":162,"passed_time":8.09574777,"remaining_time":40.92574333},
{"learn":[0.1923062335],"iteration":163,"passed_time":8.143411442,"remaining_time":40.86602206},
{"learn":[0.1919022211],"iteration":164,"passed_time":8.197032111,"remaining_time":40.83612361},
{"learn":[0.191352637],"iteration":165,"passed_time":8.242332656,"remaining_time":40.76478982},
{"learn":[0.1909010783],"iteration":166,"passed_time":8.294089664,"remaining_time":40.72547021},
{"learn":[0.1904028034],"iteration":167,"passed_time":8.349746434,"remaining_time":40.70501387},
{"learn":[0.1900263247],"iteration":168,"passed_time":8.405421029,"remaining_time":40.68422723},
{"learn":[0.1897738518],"iteration":169,"passed_time":8.461855235,"remaining_time":40.66668075},
{"learn":[0.1895173008],"iteration":170,"passed_time":8.514995625,"remaining_time":40.63296158},
{"learn":[0.1891318476],"iteration":171,"passed_time":8.56906015,"remaining_time":40.60339548},
{"learn":[0.1889032814],"iteration":172,"passed_time":8.571915189,"remaining_time":40.33259517},
{"learn":[0.1882077633],"iteration":173,"passed_time":8.626389373,"remaining_time":40.30606069},
{"learn":[0.187731515],"iteration":174,"passed_time":8.682332389,"remaining_time":40.28602228},
{"learn":[0.1874908868],"iteration":175,"passed_time":8.732890889,"remaining_time":40.24076427},
{"learn":[0.1870416425],"iteration":176,"passed_time":8.786611775,"remaining_time":40.20991829},
{"learn":[0.1865987999],"iteration":177,"passed_time":8.832591987,"remaining_time":40.14363437},
{"learn":[0.1858994829],"iteration":178,"passed_time":8.877168418,"remaining_time":40.07124068},
{"learn":[0.1854869937],"iteration":179,"passed_time":8.933560591,"remaining_time":40.05212998},
{"learn":[0.1851833635],"iteration":180,"passed_time":8.978244528,"remaining_time":39.98047011},
{"learn":[0.1847455468],"iteration":181,"passed_time":9.027418293,"remaining_time":39.92896553},
{"learn":[0.1841597527],"iteration":182,"passed_time":9.073477868,"remaining_time":39.8638044},
{"learn":[0.183821212],"iteration":183,"passed_time":9.122897849,"remaining_time":39.81351616},
{"learn":[0.1835761005],"iteration":184,"passed_time":9.174331527,"remaining_time":39.77196695},
{"learn":[0.1830246538],"iteration":185,"passed_time":9.223801167,"remaining_time":39.72185341},
{"learn":[0.1824928282],"iteration":186,"passed_time":9.274007221,"remaining_time":39.6748972},
{"learn":[0.181638665],"iteration":187,"passed_time":9.338140043,"remaining_time":39.68709518},
{"learn":[0.1813848671],"iteration":188,"passed_time":9.395526359,"remaining_time":39.67000018},
{"learn":[0.1808414025],"iteration":189,"passed_time":9.452255412,"remaining_time":39.64972402},
{"learn":[0.1803394286],"iteration":190,"passed_time":9.500962796,"remaining_time":39.59563553},
{"learn":[0.1797514743],"iteration":191,"passed_time":9.555667457,"remaining_time":39.56643556},
{"learn":[0.1788428448],"iteration":192,"passed_time":9.611718826,"remaining_time":39.54251164},
{"learn":[0.1775760345],"iteration":193,"passed_time":9.661070954,"remaining_time":39.49087251},
{"learn":[0.177371502],"iteration":194,"passed_time":9.710786293,"remaining_time":39.44073202},
{"learn":[0.1771348583],"iteration":195,"passed_time":9.756877325,"remaining_time":39.3759692},
{"learn":[0.1767956091],"iteration":196,"passed_time":9.811499201,"remaining_time":39.34560593},
{"learn":[0.1762822163],"iteration":197,"passed_time":9.86393576,"remaining_time":39.30628947},
{"learn":[0.1759523207],"iteration":198,"passed_time":9.910525081,"remaining_time":39.24368725},
{"learn":[0.1753732138],"iteration":199,"passed_time":9.960247089,"remaining_time":39.1935723},
{"learn":[0.1750399901],"iteration":200,"passed_time":10.00403573,"remaining_time":39.12025911},
{"learn":[0.1747497683],"iteration":201,"passed_time":10.07400815,"remaining_time":39.14899206},
{"learn":[0.1744212656],"iteration":202,"passed_time":10.12392617,"remaining_time":39.09930107},
{"learn":[0.17394316],"iteration":203,"passed_time":10.17384153,"remaining_time":39.04959763},
{"learn":[0.1737289682],"iteration":204,"passed_time":10.21854982,"remaining_time":38.98002908},
{"learn":[0.1733552481],"iteration":205,"passed_time":10.2728179,"remaining_time":38.94694554},
{"learn":[0.1730050335],"iteration":206,"passed_time":10.32613803,"remaining_time":38.91008531},
{"learn":[0.1722845921],"iteration":207,"passed_time":10.37562466,"remaining_time":38.85870966},
{"learn":[0.171758626],"iteration":208,"passed_time":10.43267127,"remaining_time":38.83549403},
{"learn":[0.1712269133],"iteration":209,"passed_time":10.48535606,"remaining_time":38.79581744},
{"learn":[0.1706769645],"iteration":210,"passed_time":10.53612258,"remaining_time":38.74896265},
{"learn":[0.1704126532],"iteration":211,"passed_time":10.58426979,"remaining_time":38.69249571},
{"learn":[0.1698676321],"iteration":212,"passed_time":10.63374747,"remaining_time":38.64094151},
{"learn":[0.1694126658],"iteration":213,"passed_time":10.68643466,"remaining_time":38.60099998},
{"learn":[0.1689655502],"iteration":214,"passed_time":10.74889089,"remaining_time":38.59601751},
{"learn":[0.1685746739],"iteration":215,"passed_time":10.80027184,"remaining_time":38.55097031},
{"learn":[0.1677647331],"iteration":216,"passed_time":10.85205234,"remaining_time":38.50728251},
{"learn":[0.1670154546],"iteration":217,"passed_time":10.89604904,"remaining_time":38.43606291},
{"learn":[0.1667401922],"iteration":218,"passed_time":10.95249397,"remaining_time":38.40874597},
{"learn":[0.1664032582],"iteration":219,"passed_time":11.00223632,"remaining_time":38.35779662},
{"learn":[0.1659835842],"iteration":220,"passed_time":11.05201541,"remaining_time":38.30698553},
{"learn":[0.1656199715],"iteration":221,"passed_time":11.10069765,"remaining_time":38.25240407},
{"learn":[0.1650370011],"iteration":222,"passed_time":11.14981549,"remaining_time":38.19936786},
{"learn":[0.1645734992],"iteration":223,"passed_time":11.19693938,"remaining_time":38.13957478},
{"learn":[0.1642610939],"iteration":224,"passed_time":11.25362512,"remaining_time":38.11227706},
{"learn":[0.1642461117],"iteration":225,"passed_time":11.25528841,"remaining_time":37.89944461},
{"learn":[0.1637372339],"iteration":226,"passed_time":11.30656005,"remaining_time":37.85456228},
{"learn":[0.1632839213],"iteration":227,"passed_time":11.35703511,"remaining_time":37.80697213},
{"learn":[0.1630394625],"iteration":228,"passed_time":11.41160039,"remaining_time":37.77289561},
{"learn":[0.1625987378],"iteration":229,"passed_time":11.46864157,"remaining_time":37.74678988},
{"learn":[0.1618520217],"iteration":230,"passed_time":11.53276283,"remaining_time":37.74358745},
{"learn":[0.1614982506],"iteration":231,"passed_time":11.62072979,"remaining_time":37.81746117},
{"learn":[0.1612545979],"iteration":232,"passed_time":11.70890978,"remaining_time":37.89063508},
{"learn":[0.1608963583],"iteration":233,"passed_time":11.79476395,"remaining_time":37.95494554},
{"learn":[0.1606848953],"iteration":234,"passed_time":11.89832899,"remaining_time":38.07465276},
{"learn":[0.16046673],"iteration":235,"passed_time":11.97140198,"remaining_time":38.09543596},
{"learn":[0.1601989661],"iteration":236,"passed_time":12.04412498,"remaining_time":38.11431955},
{"learn":[0.1599869679],"iteration":237,"passed_time":12.10837188,"remaining_time":38.10575857},
{"learn":[0.1597934753],"iteration":238,"passed_time":12.17493673,"remaining_time":38.10398609},
{"learn":[0.1595235435],"iteration":239,"passed_time":12.2374411,"remaining_time":38.08903544},
{"learn":[0.1591813229],"iteration":240,"passed_time":12.29970797,"remaining_time":38.07295496},
{"learn":[0.1591710654],"iteration":241,"passed_time":12.30155298,"remaining_time":37.87048336},
{"learn":[0.158892176],"iteration":242,"passed_time":12.36340007,"remaining_time":37.85337306},
{"learn":[0.1585851491],"iteration":243,"passed_time":12.43088336,"remaining_time":37.85305877},
{"learn":[0.1581885097],"iteration":244,"passed_time":12.49157539,"remaining_time":37.83162831},
{"learn":[0.1579107006],"iteration":245,"passed_time":12.55875357,"remaining_time":37.82941625},
{"learn":[0.157540959],"iteration":246,"passed_time":12.61681933,"remaining_time":37.79937775},
{"learn":[0.1572932758],"iteration":247,"passed_time":12.67088511,"remaining_time":37.75719393},
{"learn":[0.1568790168],"iteration":248,"passed_time":12.71148616,"remaining_time":37.67500718},
{"learn":[0.1565515794],"iteration":249,"passed_time":12.75466346,"remaining_time":37.60074789},
{"learn":[0.156321711],"iteration":250,"passed_time":12.81687979,"remaining_time":37.58256384},
{"learn":[0.1557513469],"iteration":251,"passed_time":12.87893296,"remaining_time":37.56355447},
{"learn":[0.1554229972],"iteration":252,"passed_time":12.9364782,"remaining_time":37.53112648},
{"learn":[0.155193186],"iteration":253,"passed_time":13.02109795,"remaining_time":37.57663305},
{"learn":[0.1548813627],"iteration":254,"passed_time":13.10435938,"remaining_time":37.61721987},
{"learn":[0.1539126442],"iteration":255,"passed_time":13.20887031,"remaining_time":37.71751638},
{"learn":[0.1535523376],"iteration":256,"passed_time":13.27017748,"remaining_time":37.69350022},
{"learn":[0.1533145307],"iteration":257,"passed_time":13.33279237,"remaining_time":37.67289007},
{"learn":[0.1530142883],"iteration":258,"passed_time":13.38614872,"remaining_time":37.62593153},
{"learn":[0.1527442802],"iteration":259,"passed_time":13.44273943,"remaining_time":37.58796756},
{"learn":[0.1523011753],"iteration":260,"passed_time":13.50007505,"remaining_time":37.55193289},
{"learn":[0.1520956171],"iteration":261,"passed_time":13.55932377,"remaining_time":37.52102952},
{"learn":[0.1519235777],"iteration":262,"passed_time":13.62091299,"remaining_time":37.49635363},
{"learn":[0.1517615031],"iteration":263,"passed_time":13.67622907,"remaining_time":37.45421824},
{"learn":[0.1514879179],"iteration":264,"passed_time":13.7350628,"remaining_time":37.42156732},
{"learn":[0.1513838725],"iteration":265,"passed_time":13.78387462,"remaining_time":37.3615549},
{"learn":[0.1512458354],"iteration":266,"passed_time":13.83242276,"remaining_time":37.30091531},
{"learn":[0.1511373313],"iteration":267,"passed_time":13.87508948,"remaining_time":37.22458709},
{"learn":[0.1504409012],"iteration":268,"passed_time":13.92417953,"remaining_time":37.16565392},
{"learn":[0.150043377],"iteration":269,"passed_time":13.97571686,"remaining_time":37.11329255},
{"learn":[0.149636858],"iteration":270,"passed_time":14.03257878,"remaining_time":37.07500518},
{"learn":[0.149451396],"iteration":271,"passed_time":14.09493768,"remaining_time":37.05103102},
{"learn":[0.1489901128],"iteration":272,"passed_time":14.15553257,"remaining_time":37.0221621},
{"learn":[0.1488295528],"iteration":273,"passed_time":14.2271236,"remaining_time":37.02167565},
{"learn":[0.1484524509],"iteration":274,"passed_time":14.27919777,"remaining_time":36.97014112},
{"learn":[0.1479832999],"iteration":275,"passed_time":14.32907984,"remaining_time":36.91295567},
{"learn":[0.1476620466],"iteration":276,"passed_time":14.37525711,"remaining_time":36.84632688},
{"learn":[0.1473705654],"iteration":277,"passed_time":14.43646316,"remaining_time":36.81817402},
{"learn":[0.1471217575],"iteration":278,"passed_time":14.49872692,"remaining_time":36.79246831},
{"learn":[0.146726565],"iteration":279,"passed_time":14.5452801,"remaining_time":36.72683224},
{"learn":[0.1465418271],"iteration":280,"passed_time":14.59057583,"remaining_time":36.65817273},
{"learn":[0.1463941482],"iteration":281,"passed_time":14.64298973,"remaining_time":36.60747432},
{"learn":[0.1459099019],"iteration":282,"passed_time":14.69686813,"remaining_time":36.56040694},
{"learn":[0.1455648314],"iteration":283,"passed_time":14.75874335,"remaining_time":36.53308653},
{"learn":[0.1453963046],"iteration":284,"passed_time":14.80670154,"remaining_time":36.4712438},
{"learn":[0.1451877207],"iteration":285,"passed_time":14.8485281,"remaining_time":36.39446921},
{"learn":[0.1450628478],"iteration":286,"passed_time":14.8976203,"remaining_time":36.33565927},
{"learn":[0.1448421868],"iteration":287,"passed_time":14.94448893,"remaining_time":36.27152001},
{"learn":[0.1447116822],"iteration":288,"passed_time":14.99283721,"remaining_time":36.21107394},
{"learn":[0.1441480868],"iteration":289,"passed_time":15.04158485,"remaining_time":36.15167117},
{"learn":[0.1438293478],"iteration":290,"passed_time":15.09368489,"remaining_time":36.10035975},
{"learn":[0.1437087919],"iteration":291,"passed_time":15.14697235,"remaining_time":36.05186911},
{"learn":[0.1434982718],"iteration":292,"passed_time":15.19382073,"remaining_time":35.98809415},
{"learn":[0.1432600829],"iteration":293,"passed_time":15.24801211,"remaining_time":35.94174284},
{"learn":[0.1428880607],"iteration":294,"passed_time":15.30109872,"remaining_time":35.89274682},
{"learn":[0.1425366775],"iteration":295,"passed_time":15.34847294,"remaining_time":35.83038784},
{"learn":[0.1421974039],"iteration":296,"passed_time":15.40678746,"remaining_time":35.79354662},
{"learn":[0.1418929674],"iteration":297,"passed_time":15.45509016,"remaining_time":35.73341316},
{"learn":[0.1416374314],"iteration":298,"passed_time":15.50243813,"remaining_time":35.67116199},
{"learn":[0.1413658573],"iteration":299,"passed_time":15.55233305,"remaining_time":35.61484269},
{"learn":[0.14110297],"iteration":300,"passed_time":15.59993208,"remaining_time":35.55333357},
{"learn":[0.140868109],"iteration":301,"passed_time":15.64920153,"remaining_time":35.49570546},
{"learn":[0.1406983176],"iteration":302,"passed_time":15.69587793,"remaining_time":35.4322789},
{"learn":[0.1401966237],"iteration":303,"passed_time":15.74277096,"remaining_time":35.36944924},
{"learn":[0.1398417253],"iteration":304,"passed_time":15.78112332,"remaining_time":35.28762658},
{"learn":[0.1397623634],"iteration":305,"passed_time":15.83102905,"remaining_time":35.23179993},
{"learn":[0.1394684369],"iteration":306,"passed_time":15.88136888,"remaining_time":35.17697342},
{"learn":[0.1393302676],"iteration":307,"passed_time":15.92759821,"remaining_time":35.11311424},
{"learn":[0.1389412823],"iteration":308,"passed_time":15.97407838,"remaining_time":35.04991955},
{"learn":[0.1387212619],"iteration":309,"passed_time":16.02716612,"remaining_time":35.00126279},
{"learn":[0.1384000091],"iteration":310,"passed_time":16.07891573,"remaining_time":34.94966891},
{"learn":[0.1377548589],"iteration":311,"passed_time":16.12658137,"remaining_time":34.88923855},
{"learn":[0.1373499862],"iteration":312,"passed_time":16.17456438,"remaining_time":34.82957313},
{"learn":[0.1371906057],"iteration":313,"passed_time":16.22330065,"remaining_time":34.77159661},
{"learn":[0.1367860525],"iteration":314,"passed_time":16.26685352,"remaining_time":34.70262084},
{"learn":[0.1365596815],"iteration":315,"passed_time":16.31889352,"remaining_time":34.65182769},
{"learn":[0.1363995578],"iteration":316,"passed_time":16.37347649,"remaining_time":34.60640141},
{"learn":[0.1362563059],"iteration":317,"passed_time":16.43090478,"remaining_time":34.56690344},
{"learn":[0.1361203134],"iteration":318,"passed_time":16.48026776,"remaining_time":34.51040395},
{"learn":[0.1359844168],"iteration":319,"passed_time":16.53078618,"remaining_time":34.45635743},
{"learn":[0.1357245314],"iteration":320,"passed_time":16.58285987,"remaining_time":34.40555973},
{"learn":[0.1354853815],"iteration":321,"passed_time":16.63631436,"remaining_time":34.35760574},
{"learn":[0.1352198057],"iteration":322,"passed_time":16.67920174,"remaining_time":34.28789459},
{"learn":[0.1350580889],"iteration":323,"passed_time":16.7263543,"remaining_time":34.22707686},
{"learn":[0.1349583701],"iteration":324,"passed_time":16.77820745,"remaining_time":34.17591795},
{"learn":[0.1344616361],"iteration":325,"passed_time":16.8303639,"remaining_time":34.12536976},
{"learn":[0.1343193182],"iteration":326,"passed_time":16.87328525,"remaining_time":34.05617207},
{"learn":[0.1341641116],"iteration":327,"passed_time":16.91955906,"remaining_time":33.99387018},
{"learn":[0.13398312],"iteration":328,"passed_time":16.9672855,"remaining_time":33.934571},
{"learn":[0.1338183815],"iteration":329,"passed_time":17.01773061,"remaining_time":33.88075458},
{"learn":[0.1336759942],"iteration":330,"passed_time":17.06513105,"remaining_time":33.82092438},
{"learn":[0.1335662537],"iteration":331,"passed_time":17.11190669,"remaining_time":33.7599364},
{"learn":[0.1333928158],"iteration":332,"passed_time":17.15811999,"remaining_time":33.69792935},
{"learn":[0.1332998869],"iteration":333,"passed_time":17.2079223,"remaining_time":33.64303371},
{"learn":[0.1330046925],"iteration":334,"passed_time":17.2519828,"remaining_time":33.57699339},
{"learn":[0.1326981784],"iteration":335,"passed_time":17.30311267,"remaining_time":33.5247808},
{"learn":[0.1325179895],"iteration":336,"passed_time":17.34955419,"remaining_time":33.46353182},
{"learn":[0.1322892615],"iteration":337,"passed_time":17.3993207,"remaining_time":33.40875483},
{"learn":[0.1321149952],"iteration":338,"passed_time":17.44328288,"remaining_time":33.3429124},
{"learn":[0.13194723],"iteration":339,"passed_time":17.49310482,"remaining_time":33.28834947},
{"learn":[0.1315102067],"iteration":340,"passed_time":17.54505944,"remaining_time":33.23785454},
{"learn":[0.1313828923],"iteration":341,"passed_time":17.59275614,"remaining_time":33.17932079},
{"learn":[0.1312102916],"iteration":342,"passed_time":17.63878668,"remaining_time":33.11772192},
{"learn":[0.130971614],"iteration":343,"passed_time":17.68713936,"remaining_time":33.06055409},
{"learn":[0.1308808578],"iteration":344,"passed_time":17.73830961,"remaining_time":33.00868049},
{"learn":[0.1306848521],"iteration":345,"passed_time":17.78203966,"remaining_time":32.94302723},
{"learn":[0.1305279616],"iteration":346,"passed_time":17.83122228,"remaining_time":32.88755695},
{"learn":[0.1304151085],"iteration":347,"passed_time":17.87962895,"remaining_time":32.83069799},
{"learn":[0.1300107619],"iteration":348,"passed_time":17.92935319,"remaining_time":32.77629608},
{"learn":[0.1297267415],"iteration":349,"passed_time":17.97743778,"remaining_time":32.71893676},
{"learn":[0.1293984191],"iteration":350,"passed_time":18.02552438,"remaining_time":32.66163392},
{"learn":[0.1291997712],"iteration":351,"passed_time":18.08278755,"remaining_time":32.62093777},
{"learn":[0.1289645132],"iteration":352,"passed_time":18.13339237,"remaining_time":32.56818913},
{"learn":[0.1287590806],"iteration":353,"passed_time":18.18028008,"remaining_time":32.50880591},
{"learn":[0.1284237711],"iteration":354,"passed_time":18.2273238,"remaining_time":32.44977082},
{"learn":[0.1282171539],"iteration":355,"passed_time":18.2798094,"remaining_time":32.40044868},
{"learn":[0.1279874418],"iteration":356,"passed_time":18.33123112,"remaining_time":32.34923139},
{"learn":[0.1278915035],"iteration":357,"passed_time":18.38260372,"remaining_time":32.29792665},
{"learn":[0.1276420617],"iteration":358,"passed_time":18.42612595,"remaining_time":32.23288886},
{"learn":[0.1275071446],"iteration":359,"passed_time":18.47837043,"remaining_time":32.18316184},
{"learn":[0.1270871487],"iteration":360,"passed_time":18.52217761,"remaining_time":32.11878998},
{"learn":[0.126886047],"iteration":361,"passed_time":18.56528876,"remaining_time":32.05333004},
{"learn":[0.1266010345],"iteration":362,"passed_time":18.61459632,"remaining_time":31.99864491},
{"learn":[0.1264904128],"iteration":363,"passed_time":18.66186521,"remaining_time":31.94050008},
{"learn":[0.1264102733],"iteration":364,"passed_time":18.7152112,"remaining_time":31.89277086},
{"learn":[0.1262196769],"iteration":365,"passed_time":18.7650515,"remaining_time":31.83906279},
{"learn":[0.1260798468],"iteration":366,"passed_time":18.81377612,"remaining_time":31.78349099},
{"learn":[0.1258806307],"iteration":367,"passed_time":18.86062255,"remaining_time":31.72479716},
{"learn":[0.1258418821],"iteration":368,"passed_time":18.90851152,"remaining_time":31.66791361},
{"learn":[0.1256123579],"iteration":369,"passed_time":18.9582392,"remaining_time":31.61414483},
{"learn":[0.1253527318],"iteration":370,"passed_time":19.00379261,"remaining_time":31.55346697},
{"learn":[0.1252234367],"iteration":371,"passed_time":19.05358689,"remaining_time":31.49988155},
{"learn":[0.1251170837],"iteration":372,"passed_time":19.10323402,"remaining_time":31.44607423},
{"learn":[0.1248960626],"iteration":373,"passed_time":19.15082435,"remaining_time":31.38891798},
{"learn":[0.1244768692],"iteration":374,"passed_time":19.19868394,"remaining_time":31.33225218},
{"learn":[0.1242719271],"iteration":375,"passed_time":19.23927957,"remaining_time":31.2638293},
{"learn":[0.124015415],"iteration":376,"passed_time":19.29213094,"remaining_time":31.21538428},
{"learn":[0.1240120569],"iteration":377,"passed_time":19.29470424,"remaining_time":31.08591239},
{"learn":[0.1239384965],"iteration":378,"passed_time":19.31212402,"remaining_time":30.98092718},
{"learn":[0.123733639],"iteration":379,"passed_time":19.36354887,"remaining_time":30.93072148},
{"learn":[0.1235868494],"iteration":380,"passed_time":19.41633286,"remaining_time":30.88267117},
{"learn":[0.1232083228],"iteration":381,"passed_time":19.469566,"remaining_time":30.8353074},
{"learn":[0.1230444047],"iteration":382,"passed_time":19.51930341,"remaining_time":30.78240015},
{"learn":[0.1227956394],"iteration":383,"passed_time":19.56871524,"remaining_time":30.72899815},
{"learn":[0.1226692972],"iteration":384,"passed_time":19.61902799,"remaining_time":30.67702558},
{"learn":[0.1223977632],"iteration":385,"passed_time":19.67009341,"remaining_time":30.62623352},
{"learn":[0.1220735301],"iteration":386,"passed_time":19.72324941,"remaining_time":30.57868125},
{"learn":[0.1215566569],"iteration":387,"passed_time":19.77691316,"remaining_time":30.53188398},
{"learn":[0.1212512314],"iteration":388,"passed_time":19.82822657,"remaining_time":30.48143828},
{"learn":[0.121026379],"iteration":389,"passed_time":19.87652619,"remaining_time":30.42637471},
{"learn":[0.1205010959],"iteration":390,"passed_time":19.91709117,"remaining_time":30.35955586},
{"learn":[0.1204248991],"iteration":391,"passed_time":19.96617126,"remaining_time":30.30579567},
{"learn":[0.1201772449],"iteration":392,"passed_time":20.01524703,"remaining_time":30.25205276},
{"learn":[0.1200184756],"iteration":393,"passed_time":20.06198368,"remaining_time":30.194813},
{"learn":[0.1195597806],"iteration":394,"passed_time":20.10856831,"remaining_time":30.13739858},
{"learn":[0.1193189139],"iteration":395,"passed_time":20.15841627,"remaining_time":30.08490912},
{"learn":[0.1191956481],"iteration":396,"passed_time":20.20520315,"remaining_time":30.02788377},
{"learn":[0.118881301],"iteration":397,"passed_time":20.24710629,"remaining_time":29.96368242},
{"learn":[0.1187481455],"iteration":398,"passed_time":20.2951228,"remaining_time":29.90860202},
{"learn":[0.1185087019],"iteration":399,"passed_time":20.34601636,"remaining_time":29.85777901},
{"learn":[0.1180497649],"iteration":400,"passed_time":20.39294212,"remaining_time":29.80115731},
{"learn":[0.117882121],"iteration":401,"passed_time":20.43624214,"remaining_time":29.73930759},
{"learn":[0.1175197709],"iteration":402,"passed_time":20.49188525,"remaining_time":29.6954367},
{"learn":[0.117264259],"iteration":403,"passed_time":20.54523236,"remaining_time":29.64819423},
{"learn":[0.1171807822],"iteration":404,"passed_time":20.59070705,"remaining_time":29.58960865},
{"learn":[0.1168408542],"iteration":405,"passed_time":20.64068011,"remaining_time":29.53752498},
{"learn":[0.1166650352],"iteration":406,"passed_time":20.6889678,"remaining_time":29.48304994},
{"learn":[0.1164412106],"iteration":407,"passed_time":20.73842022,"remaining_time":29.4302581},
{"learn":[0.1160873865],"iteration":408,"passed_time":20.7890804,"remaining_time":29.37918941},
{"learn":[0.1159071992],"iteration":409,"passed_time":20.83525284,"remaining_time":29.32180705},
{"learn":[0.1157258713],"iteration":410,"passed_time":20.8807164,"remaining_time":29.26348576},
{"learn":[0.1154760079],"iteration":411,"passed_time":20.93119573,"remaining_time":29.21222704},
{"learn":[0.1152931864],"iteration":412,"passed_time":20.97575226,"remaining_time":29.15274043},
{"learn":[0.115048463],"iteration":413,"passed_time":21.0208137,"remaining_time":29.09402476},
{"learn":[0.1147965312],"iteration":414,"passed_time":21.06543344,"remaining_time":29.0347661},
{"learn":[0.1144879827],"iteration":415,"passed_time":21.11529791,"remaining_time":28.9827767},
{"learn":[0.1143613024],"iteration":416,"passed_time":21.16021272,"remaining_time":28.92403177},
{"learn":[0.1142054366],"iteration":417,"passed_time":21.20184156,"remaining_time":28.86088002},
{"learn":[0.1140832498],"iteration":418,"passed_time":21.25500768,"remaining_time":28.81347103},
{"learn":[0.1139033692],"iteration":419,"passed_time":21.30777076,"remaining_time":28.76549053},
{"learn":[0.1137790177],"iteration":420,"passed_time":21.35711276,"remaining_time":28.71288794},
{"learn":[0.1136325997],"iteration":421,"passed_time":21.40279332,"remaining_time":28.65539864},
{"learn":[0.1135041978],"iteration":422,"passed_time":21.45215785,"remaining_time":28.60287713},
{"learn":[0.1133044432],"iteration":423,"passed_time":21.50637385,"remaining_time":28.55681245},
{"learn":[0.1131598452],"iteration":424,"passed_time":21.56512571,"remaining_time":28.51670741},
{"learn":[0.112865209],"iteration":425,"passed_time":21.62063229,"remaining_time":28.47224112},
{"learn":[0.1126831798],"iteration":426,"passed_time":21.67440495,"remaining_time":28.42544911},
{"learn":[0.1123995369],"iteration":427,"passed_time":21.72694091,"remaining_time":28.37700927},
{"learn":[0.1120912929],"iteration":428,"passed_time":21.77781015,"remaining_time":28.32638243},
{"learn":[0.1116645296],"iteration":429,"passed_time":21.82574004,"remaining_time":28.27194699},
{"learn":[0.1113898095],"iteration":430,"passed_time":21.87366359,"remaining_time":28.21753355},
{"learn":[0.1110623212],"iteration":431,"passed_time":21.92176498,"remaining_time":28.16337862},
{"learn":[0.1109213677],"iteration":432,"passed_time":21.96489342,"remaining_time":28.10288904},
{"learn":[0.1107614349],"iteration":433,"passed_time":22.0192698,"remaining_time":28.05681152},
{"learn":[0.1105713875],"iteration":434,"passed_time":22.06652768,"remaining_time":28.00166271},
{"learn":[0.1104505917],"iteration":435,"passed_time":22.11370836,"remaining_time":27.94645253},
{"learn":[0.1101185296],"iteration":436,"passed_time":22.16085509,"remaining_time":27.89123638},
{"learn":[0.1100297789],"iteration":437,"passed_time":22.20753309,"remaining_time":27.83546956},
{"learn":[0.1100218348],"iteration":438,"passed_time":22.21204949,"remaining_time":27.72711418},
{"learn":[0.1098379134],"iteration":439,"passed_time":22.26233339,"remaining_time":27.6761281},
{"learn":[0.1097699798],"iteration":440,"passed_time":22.30599936,"remaining_time":27.61695159},
{"learn":[0.1096097954],"iteration":441,"passed_time":22.35656174,"remaining_time":27.56634875},
{"learn":[0.1093871473],"iteration":442,"passed_time":22.40039426,"remaining_time":27.50748189},
{"learn":[0.109142076],"iteration":443,"passed_time":22.44570664,"remaining_time":27.45049258},
{"learn":[0.1090424414],"iteration":444,"passed_time":22.49674825,"remaining_time":27.40053382},
{"learn":[0.1088469486],"iteration":445,"passed_time":22.55340894,"remaining_time":27.35738618},
{"learn":[0.1087386032],"iteration":446,"passed_time":22.6010535,"remaining_time":27.30328611},
{"learn":[0.1086281817],"iteration":447,"passed_time":22.64480754,"remaining_time":27.24453408},
{"learn":[0.1085743822],"iteration":448,"passed_time":22.69809976,"remaining_time":27.19727767},
{"learn":[0.1082520601],"iteration":449,"passed_time":22.73888736,"remaining_time":27.13507224},
{"learn":[0.1080557322],"iteration":450,"passed_time":22.78125815,"remaining_time":27.07484339},
{"learn":[0.1077607754],"iteration":451,"passed_time":22.83257011,"remaining_time":27.02527657},
{"learn":[0.1076160041],"iteration":452,"passed_time":22.88070755,"remaining_time":26.97195989},
{"learn":[0.1075258864],"iteration":453,"passed_time":22.92395576,"remaining_time":26.91292604},
{"learn":[0.1073849816],"iteration":454,"passed_time":22.97136373,"remaining_time":26.85882528},
{"learn":[0.1072020345],"iteration":455,"passed_time":23.02272089,"remaining_time":26.80935261},
{"learn":[0.1069791665],"iteration":456,"passed_time":23.07905882,"remaining_time":26.76564809},
{"learn":[0.1065281363],"iteration":457,"passed_time":23.13049192,"remaining_time":26.7162232},
{"learn":[0.1062071153],"iteration":458,"passed_time":23.1793789,"remaining_time":26.66386069},
{"learn":[0.1061175607],"iteration":459,"passed_time":23.22476838,"remaining_time":26.60750638},
{"learn":[0.1059266051],"iteration":460,"passed_time":23.2913986,"remaining_time":26.57543528},
{"learn":[0.1056420856],"iteration":461,"passed_time":23.34825089,"remaining_time":26.53210328},
{"learn":[0.1055859569],"iteration":462,"passed_time":23.39811868,"remaining_time":26.48080818},
{"learn":[0.1054764866],"iteration":463,"passed_time":23.45193671,"remaining_time":26.43397177},
{"learn":[0.1053517178],"iteration":464,"passed_time":23.49267195,"remaining_time":26.37241883},
{"learn":[0.1051057795],"iteration":465,"passed_time":23.53810167,"remaining_time":26.3162038},
{"learn":[0.1049890191],"iteration":466,"passed_time":23.5887381,"remaining_time":26.26583258},
{"learn":[0.1049122232],"iteration":467,"passed_time":23.63776004,"remaining_time":26.21366979},
{"learn":[0.1047660975],"iteration":468,"passed_time":23.68682877,"remaining_time":26.16157207},
{"learn":[0.1046098916],"iteration":469,"passed_time":23.73341096,"remaining_time":26.10675206},
{"learn":[0.1044887293],"iteration":470,"passed_time":23.77990151,"remaining_time":26.05186662},
{"learn":[0.1044179122],"iteration":471,"passed_time":23.82553203,"remaining_time":25.99607838},
{"learn":[0.1043327826],"iteration":472,"passed_time":23.87354082,"remaining_time":25.94291751},
{"learn":[0.1040089243],"iteration":473,"passed_time":23.91615705,"remaining_time":25.88394213},
{"learn":[0.1037655944],"iteration":474,"passed_time":23.97707109,"remaining_time":25.84475873},
{"learn":[0.1031161717],"iteration":475,"passed_time":24.02916115,"remaining_time":25.79601124},
{"learn":[0.1029061256],"iteration":476,"passed_time":24.08107599,"remaining_time":25.74706238},
{"learn":[0.1026440688],"iteration":477,"passed_time":24.12876642,"remaining_time":25.69360273},
{"learn":[0.1025124355],"iteration":478,"passed_time":24.17808124,"remaining_time":25.64188992},
{"learn":[0.1023862033],"iteration":479,"passed_time":24.22848211,"remaining_time":25.59133423},
{"learn":[0.1022801562],"iteration":480,"passed_time":24.27826303,"remaining_time":25.54012702},
{"learn":[0.1019685333],"iteration":481,"passed_time":24.32133653,"remaining_time":25.48189823},
{"learn":[0.1018462859],"iteration":482,"passed_time":24.36883914,"remaining_time":25.42835389},
{"learn":[0.1017617508],"iteration":483,"passed_time":24.41228206,"remaining_time":25.37061545},
{"learn":[0.1015794069],"iteration":484,"passed_time":24.46214408,"remaining_time":25.31958006},
{"learn":[0.1014989537],"iteration":485,"passed_time":24.51015738,"remaining_time":25.26664372},
{"learn":[0.1014306162],"iteration":486,"passed_time":24.55785049,"remaining_time":25.21339886},
{"learn":[0.1012979962],"iteration":487,"passed_time":24.61267899,"remaining_time":25.16747299},
{"learn":[0.101185866],"iteration":488,"passed_time":24.65863483,"remaining_time":25.11247474},
{"learn":[0.100779168],"iteration":489,"passed_time":24.70681897,"remaining_time":25.05977353},
{"learn":[0.1006312688],"iteration":490,"passed_time":24.75499967,"remaining_time":25.00708724},
{"learn":[0.1004731653],"iteration":491,"passed_time":24.80368957,"remaining_time":24.95493158},
{"learn":[0.10036239],"iteration":492,"passed_time":24.84846302,"remaining_time":24.89886558},
{"learn":[0.1001133827],"iteration":493,"passed_time":24.89611878,"remaining_time":24.84572178},
{"learn":[0.100006701],"iteration":494,"passed_time":24.93721771,"remaining_time":24.78608306},
{"learn":[0.09969453455],"iteration":495,"passed_time":24.98167712,"remaining_time":24.72984569},
{"learn":[0.09954251175],"iteration":496,"passed_time":25.02736649,"remaining_time":24.67486837},
{"learn":[0.09930915374],"iteration":497,"passed_time":25.07924404,"remaining_time":24.62600469},
{"learn":[0.09914847915],"iteration":498,"passed_time":25.12902334,"remaining_time":24.57507693},
{"learn":[0.0990027987],"iteration":499,"passed_time":25.18038135,"remaining_time":24.52569143},
{"learn":[0.09890774284],"iteration":500,"passed_time":25.22522316,"remaining_time":24.46997695},
{"learn":[0.09872404697],"iteration":501,"passed_time":25.27849855,"remaining_time":24.42245378},
{"learn":[0.09863345943],"iteration":502,"passed_time":25.32719033,"remaining_time":24.37049725},
{"learn":[0.09855873854],"iteration":503,"passed_time":25.37673769,"remaining_time":24.31937362},
{"learn":[0.09848731515],"iteration":504,"passed_time":25.4253581,"remaining_time":24.26737149},
{"learn":[0.09833534264],"iteration":505,"passed_time":25.47165053,"remaining_time":24.21316978},
{"learn":[0.0981173118],"iteration":506,"passed_time":25.51709928,"remaining_time":24.1582005},
{"learn":[0.09804468326],"iteration":507,"passed_time":25.56707387,"remaining_time":24.10753619},
{"learn":[0.09788555278],"iteration":508,"passed_time":25.61451553,"remaining_time":24.05449592},
{"learn":[0.09759513873],"iteration":509,"passed_time":25.66324894,"remaining_time":24.00268577},
{"learn":[0.09743616024],"iteration":510,"passed_time":25.71241068,"remaining_time":23.95128666},
{"learn":[0.09731993051],"iteration":511,"passed_time":25.75957081,"remaining_time":23.89803932},
{"learn":[0.09722608416],"iteration":512,"passed_time":25.80875537,"remaining_time":23.84668624},
{"learn":[0.09714485842],"iteration":513,"passed_time":25.85538814,"remaining_time":23.79299337},
{"learn":[0.0970477913],"iteration":514,"passed_time":25.90346037,"remaining_time":23.74064718},
{"learn":[0.09683733237],"iteration":515,"passed_time":25.95246355,"remaining_time":23.68916731},
{"learn":[0.09676565879],"iteration":516,"passed_time":25.99790231,"remaining_time":23.63445664},
{"learn":[0.09656348919],"iteration":517,"passed_time":26.04308518,"remaining_time":23.5795501},
{"learn":[0.09652963208],"iteration":518,"passed_time":26.09163614,"remaining_time":23.52771813},
{"learn":[0.09620926309],"iteration":519,"passed_time":26.13963851,"remaining_time":23.47540612},
{"learn":[0.09603755578],"iteration":520,"passed_time":26.18597521,"remaining_time":23.42162082},
{"learn":[0.09595973229],"iteration":521,"passed_time":26.23309958,"remaining_time":23.36856571},
{"learn":[0.0958819453],"iteration":522,"passed_time":26.28391109,"remaining_time":23.31880448},
{"learn":[0.09562771783],"iteration":523,"passed_time":26.33173719,"remaining_time":23.26640137},
{"learn":[0.09548099917],"iteration":524,"passed_time":26.37839405,"remaining_time":23.21298676},
{"learn":[0.09536869834],"iteration":525,"passed_time":26.42376609,"remaining_time":23.1584718},
{"learn":[0.09530112727],"iteration":526,"passed_time":26.47221851,"remaining_time":23.10668029},
{"learn":[0.09521521659],"iteration":527,"passed_time":26.5276643,"remaining_time":23.0609809},
{"learn":[0.09511096097],"iteration":528,"passed_time":26.57428096,"remaining_time":23.00760053},
{"learn":[0.09502765902],"iteration":529,"passed_time":26.62436641,"remaining_time":22.9572367},
{"learn":[0.09497928814],"iteration":530,"passed_time":26.67038128,"remaining_time":22.90337827},
{"learn":[0.09467659154],"iteration":531,"passed_time":26.7197537,"remaining_time":22.85242093},
{"learn":[0.09440655804],"iteration":532,"passed_time":26.7650875,"remaining_time":22.7980295},
{"learn":[0.09433775709],"iteration":533,"passed_time":26.80920831,"remaining_time":22.74264301},
{"learn":[0.09416513924],"iteration":534,"passed_time":26.85755901,"remaining_time":22.69087229},
{"learn":[0.09388614494],"iteration":535,"passed_time":26.90693341,"remaining_time":22.63997569},
{"learn":[0.09381509656],"iteration":536,"passed_time":26.95559514,"remaining_time":22.58848755},
{"learn":[0.09356742913],"iteration":537,"passed_time":27.00315342,"remaining_time":22.53608901},
{"learn":[0.09337435489],"iteration":538,"passed_time":27.05009454,"remaining_time":22.48319546},
{"learn":[0.09316548839],"iteration":539,"passed_time":27.09616303,"remaining_time":22.42960162},
{"learn":[0.09297734095],"iteration":540,"passed_time":27.14340554,"remaining_time":22.37700346},
{"learn":[0.09278690539],"iteration":541,"passed_time":27.19069062,"remaining_time":22.32446001},
{"learn":[0.09271954044],"iteration":542,"passed_time":27.23379987,"remaining_time":22.26852144},
{"learn":[0.0926402207],"iteration":543,"passed_time":27.27621177,"remaining_time":22.21206216},
{"learn":[0.09249707066],"iteration":544,"passed_time":27.32194023,"remaining_time":22.15834418},
{"learn":[0.09244798393],"iteration":545,"passed_time":27.36843529,"remaining_time":22.10527466},
{"learn":[0.09239264058],"iteration":546,"passed_time":27.41629455,"remaining_time":22.05332651},
{"learn":[0.09223187775],"iteration":547,"passed_time":27.46715586,"remaining_time":22.00379821},
{"learn":[0.09213848226],"iteration":548,"passed_time":27.51748596,"remaining_time":21.95384126},
{"learn":[0.09202819442],"iteration":549,"passed_time":27.56559573,"remaining_time":21.90211879},
{"learn":[0.09184480707],"iteration":550,"passed_time":27.61435959,"remaining_time":21.850927},
{"learn":[0.09173343019],"iteration":551,"passed_time":27.6655072,"remaining_time":21.80162252},
{"learn":[0.0915887167],"iteration":552,"passed_time":27.70919348,"remaining_time":21.74645564},
{"learn":[0.09141597911],"iteration":553,"passed_time":27.75630604,"remaining_time":21.69400815},
{"learn":[0.09127637975],"iteration":554,"passed_time":27.80240106,"remaining_time":21.64078785},
{"learn":[0.09108163046],"iteration":555,"passed_time":27.84914031,"remaining_time":21.58809258},
{"learn":[0.09096592973],"iteration":556,"passed_time":27.89391738,"remaining_time":21.5339039},
{"learn":[0.09084368408],"iteration":557,"passed_time":27.94045978,"remaining_time":21.48110618},
{"learn":[0.09076647935],"iteration":558,"passed_time":27.98387276,"remaining_time":21.42593478},
{"learn":[0.09057577955],"iteration":559,"passed_time":28.02915862,"remaining_time":21.37223345},
{"learn":[0.09042472161],"iteration":560,"passed_time":28.07518285,"remaining_time":21.3191228},
{"learn":[0.09029067511],"iteration":561,"passed_time":28.11705362,"remaining_time":21.26289642},
{"learn":[0.09016923905],"iteration":562,"passed_time":28.16542885,"remaining_time":21.21161959},
{"learn":[0.0899251572],"iteration":563,"passed_time":28.20782876,"remaining_time":21.15587157},
{"learn":[0.08980691744],"iteration":564,"passed_time":28.25487336,"remaining_time":21.10363993},
{"learn":[0.08967162254],"iteration":565,"passed_time":28.30200534,"remaining_time":21.0514916},
{"learn":[0.08950253981],"iteration":566,"passed_time":28.34786621,"remaining_time":20.99841941},
{"learn":[0.0894504455],"iteration":567,"passed_time":28.39616888,"remaining_time":20.94717388},
{"learn":[0.0891977085],"iteration":568,"passed_time":28.43822184,"remaining_time":20.8913475},
{"learn":[0.08915946261],"iteration":569,"passed_time":28.47679639,"remaining_time":20.83302473},
{"learn":[0.08900613655],"iteration":570,"passed_time":28.52748369,"remaining_time":20.78359582},
{"learn":[0.08879907854],"iteration":571,"passed_time":28.57069499,"remaining_time":20.72873849},
{"learn":[0.08871368646],"iteration":572,"passed_time":28.6202465,"remaining_time":20.6785027},
{"learn":[0.0886040084],"iteration":573,"passed_time":28.67147994,"remaining_time":20.62947947},
{"learn":[0.08851276178],"iteration":574,"passed_time":28.72126097,"remaining_time":20.57940786},
{"learn":[0.08847282108],"iteration":575,"passed_time":28.76476401,"remaining_time":20.52485765},
{"learn":[0.08837368428],"iteration":576,"passed_time":28.81534684,"remaining_time":20.47537644},
{"learn":[0.08821921687],"iteration":577,"passed_time":28.85392563,"remaining_time":20.4173972},
{"learn":[0.08805862817],"iteration":578,"passed_time":28.90739715,"remaining_time":20.36997934},
{"learn":[0.08799640278],"iteration":579,"passed_time":28.95288556,"remaining_time":20.31693866},
{"learn":[0.0878098368],"iteration":580,"passed_time":28.9996912,"remaining_time":20.26484446},
{"learn":[0.08771682664],"iteration":581,"passed_time":29.0481558,"remaining_time":20.21392285},
{"learn":[0.0875883846],"iteration":582,"passed_time":29.09378164,"remaining_time":20.16104251},
{"learn":[0.08749191406],"iteration":583,"passed_time":29.15430956,"remaining_time":20.11847047},
{"learn":[0.08737265176],"iteration":584,"passed_time":29.20970245,"remaining_time":20.07230835},
{"learn":[0.08725530627],"iteration":585,"passed_time":29.26326993,"remaining_time":20.0248656},
{"learn":[0.08719883888],"iteration":586,"passed_time":29.31066432,"remaining_time":19.97319545},
{"learn":[0.08708675257],"iteration":587,"passed_time":29.35861152,"remaining_time":19.92191496},
{"learn":[0.08696039572],"iteration":588,"passed_time":29.41169022,"remaining_time":19.87411326},
{"learn":[0.0868849202],"iteration":589,"passed_time":29.45962944,"remaining_time":19.8228354},
{"learn":[0.08687798164],"iteration":590,"passed_time":29.46370749,"remaining_time":19.74217964},
{"learn":[0.0868540418],"iteration":591,"passed_time":29.50526961,"remaining_time":19.68679307},
{"learn":[0.08678452027],"iteration":592,"passed_time":29.55698393,"remaining_time":19.63819843},
{"learn":[0.08670902425],"iteration":593,"passed_time":29.59760747,"remaining_time":19.58225544},
{"learn":[0.08660287494],"iteration":594,"passed_time":29.64440897,"remaining_time":19.53043415},
{"learn":[0.08655402948],"iteration":595,"passed_time":29.68532357,"remaining_time":19.47476764},
{"learn":[0.08652256599],"iteration":596,"passed_time":29.73782279,"remaining_time":19.42671841},
{"learn":[0.08644832675],"iteration":597,"passed_time":29.78266289,"remaining_time":19.37367201},
{"learn":[0.08631388874],"iteration":598,"passed_time":29.83038694,"remaining_time":19.32252109},
{"learn":[0.08621361571],"iteration":599,"passed_time":29.8806659,"remaining_time":19.2730295},
{"learn":[0.08615338875],"iteration":600,"passed_time":29.94181813,"remaining_time":19.2305188},
{"learn":[0.08611361354],"iteration":601,"passed_time":29.99098488,"remaining_time":19.18028103},
{"learn":[0.08604958211],"iteration":602,"passed_time":30.03993627,"remaining_time":19.12990966},
{"learn":[0.0859523086],"iteration":603,"passed_time":30.08713795,"remaining_time":19.0784335},
{"learn":[0.08584883908],"iteration":604,"passed_time":30.13220385,"remaining_time":19.02562293},
{"learn":[0.08578268364],"iteration":605,"passed_time":30.18146725,"remaining_time":18.97547694},
{"learn":[0.08562310541],"iteration":606,"passed_time":30.23000281,"remaining_time":18.9248782},
{"learn":[0.08554697983],"iteration":607,"passed_time":30.27729228,"remaining_time":18.8735095},
{"learn":[0.08542988758],"iteration":608,"passed_time":30.32590328,"remaining_time":18.82297445},
{"learn":[0.08539822201],"iteration":609,"passed_time":30.37199194,"remaining_time":18.77088682},
{"learn":[0.08530163825],"iteration":610,"passed_time":30.41553823,"remaining_time":18.71725429},
{"learn":[0.08517461142],"iteration":611,"passed_time":30.46122405,"remaining_time":18.66496572},
{"learn":[0.08508902947],"iteration":612,"passed_time":30.50474761,"remaining_time":18.61137945},
{"learn":[0.08502782465],"iteration":613,"passed_time":30.55043144,"remaining_time":18.55913832},
{"learn":[0.08495928147],"iteration":614,"passed_time":30.58973943,"remaining_time":18.5030619},
{"learn":[0.08465600971],"iteration":615,"passed_time":30.6315775,"remaining_time":18.44856372},
{"learn":[0.08452986955],"iteration":616,"passed_time":30.67550263,"remaining_time":18.39535814},
{"learn":[0.08431543927],"iteration":617,"passed_time":30.72324115,"remaining_time":18.34445952},
{"learn":[0.08429248334],"iteration":618,"passed_time":30.77060363,"remaining_time":18.29334756},
{"learn":[0.08418051902],"iteration":619,"passed_time":30.82471212,"remaining_time":18.24624088},
{"learn":[0.08404170796],"iteration":620,"passed_time":30.87225236,"remaining_time":18.19524052},
{"learn":[0.08398920404],"iteration":621,"passed_time":30.92017511,"remaining_time":18.14447575},
{"learn":[0.08384222995],"iteration":622,"passed_time":30.96119644,"remaining_time":18.08968781},
{"learn":[0.08371747063],"iteration":623,"passed_time":31.01098549,"remaining_time":18.04004445},
{"learn":[0.08365349507],"iteration":624,"passed_time":31.05894241,"remaining_time":17.98933944},
{"learn":[0.08353755622],"iteration":625,"passed_time":31.10425839,"remaining_time":17.93712025},
{"learn":[0.08347745081],"iteration":626,"passed_time":31.15524127,"remaining_time":17.88817681},
{"learn":[0.08333462337],"iteration":627,"passed_time":31.20220751,"remaining_time":17.83693073},
{"learn":[0.08314673708],"iteration":628,"passed_time":31.25011494,"remaining_time":17.78623394},
{"learn":[0.08303275412],"iteration":629,"passed_time":31.30039645,"remaining_time":17.73689132},
{"learn":[0.08282350122],"iteration":630,"passed_time":31.35022171,"remaining_time":17.68728832},
{"learn":[0.08279433016],"iteration":631,"passed_time":31.35657536,"remaining_time":17.61326622},
{"learn":[0.08265520742],"iteration":632,"passed_time":31.39909555,"remaining_time":17.55968377},
{"learn":[0.08256396296],"iteration":633,"passed_time":31.44681587,"remaining_time":17.50903155},
{"learn":[0.08234916484],"iteration":634,"passed_time":31.49251285,"remaining_time":17.45726697},
{"learn":[0.08211111866],"iteration":635,"passed_time":31.53945387,"remaining_time":17.40620803},
{"learn":[0.08203155954],"iteration":636,"passed_time":31.57995221,"remaining_time":17.3516221},
{"learn":[0.08193456903],"iteration":637,"passed_time":31.62937723,"remaining_time":17.3019634},
{"learn":[0.0818469545],"iteration":638,"passed_time":31.67681326,"remaining_time":17.25122224},
{"learn":[0.08174134228],"iteration":639,"passed_time":31.72440785,"remaining_time":17.20057738},
{"learn":[0.0817053287],"iteration":640,"passed_time":31.77162862,"remaining_time":17.14974026},
{"learn":[0.08163118447],"iteration":641,"passed_time":31.82220712,"remaining_time":17.10071878},
{"learn":[0.08153496059],"iteration":642,"passed_time":31.86476861,"remaining_time":17.04740342},
{"learn":[0.08148773466],"iteration":643,"passed_time":31.91155215,"remaining_time":16.99637017},
{"learn":[0.08138093593],"iteration":644,"passed_time":31.96171189,"remaining_time":16.94714026},
{"learn":[0.08112840305],"iteration":645,"passed_time":32.01044675,"remaining_time":16.89715533},
{"learn":[0.08098555017],"iteration":646,"passed_time":32.06164744,"remaining_time":16.84847006},
{"learn":[0.08080327013],"iteration":647,"passed_time":32.10844851,"remaining_time":16.79747538},
{"learn":[0.08065151515],"iteration":648,"passed_time":32.15557468,"remaining_time":16.74666293},
{"learn":[0.08045928963],"iteration":649,"passed_time":32.20124388,"remaining_time":16.69510644},
{"learn":[0.08035809665],"iteration":650,"passed_time":32.25291671,"remaining_time":16.64666669},
{"learn":[0.08024878268],"iteration":651,"passed_time":32.30492653,"remaining_time":16.59839017},
{"learn":[0.0801560997],"iteration":652,"passed_time":32.35392569,"remaining_time":16.5485623},
{"learn":[0.08005290507],"iteration":653,"passed_time":32.40002454,"remaining_time":16.4972602},
{"learn":[0.07994293884],"iteration":654,"passed_time":32.44043138,"remaining_time":16.44308888},
{"learn":[0.07988426477],"iteration":655,"passed_time":32.48997794,"remaining_time":16.39357118},
{"learn":[0.07982372209],"iteration":656,"passed_time":32.53188509,"remaining_time":16.34021625},
{"learn":[0.07973732997],"iteration":657,"passed_time":32.57990417,"remaining_time":16.28995209},
{"learn":[0.07953648713],"iteration":658,"passed_time":32.6299791,"remaining_time":16.24071797},
{"learn":[0.07933742444],"iteration":659,"passed_time":32.67228731,"remaining_time":16.18763326},
{"learn":[0.07922085927],"iteration":660,"passed_time":32.71988464,"remaining_time":16.1371897},
{"learn":[0.07901688316],"iteration":661,"passed_time":32.76946351,"remaining_time":16.08772755},
{"learn":[0.07896116894],"iteration":662,"passed_time":32.81798789,"remaining_time":16.03774974},
{"learn":[0.07878593721],"iteration":663,"passed_time":32.86949096,"remaining_time":15.98922527},
{"learn":[0.078712206],"iteration":664,"passed_time":32.91224495,"remaining_time":15.93645545},
{"learn":[0.07864797624],"iteration":665,"passed_time":32.96268289,"remaining_time":15.88741923},
{"learn":[0.07831355526],"iteration":666,"passed_time":33.01377241,"remaining_time":15.83869141},
{"learn":[0.07816829625],"iteration":667,"passed_time":33.06332943,"remaining_time":15.78922468},
{"learn":[0.07806142878],"iteration":668,"passed_time":33.10969497,"remaining_time":15.73824066},
{"learn":[0.07801029325],"iteration":669,"passed_time":33.15358423,"remaining_time":15.68609881},
{"learn":[0.07788437767],"iteration":670,"passed_time":33.1953629,"remaining_time":15.6329876},
{"learn":[0.07784454298],"iteration":671,"passed_time":33.24263264,"remaining_time":15.58248405},
{"learn":[0.07775858719],"iteration":672,"passed_time":33.28833799,"remaining_time":15.53126022},
{"learn":[0.07771691649],"iteration":673,"passed_time":33.33402462,"remaining_time":15.48004407},
{"learn":[0.07761346028],"iteration":674,"passed_time":33.38554738,"remaining_time":15.4315419},
{"learn":[0.0774949047],"iteration":675,"passed_time":33.43469472,"remaining_time":15.38193795},
{"learn":[0.07749389474],"iteration":676,"passed_time":33.43695025,"remaining_time":15.31086348},
{"learn":[0.07745069787],"iteration":677,"passed_time":33.4833678,"remaining_time":15.26011895},
{"learn":[0.07737722549],"iteration":678,"passed_time":33.52912518,"remaining_time":15.20908771},
{"learn":[0.07725314118],"iteration":679,"passed_time":33.57798208,"remaining_time":15.15947132},
{"learn":[0.07724534213],"iteration":680,"passed_time":33.58239114,"remaining_time":15.089885},
{"learn":[0.07720146789],"iteration":681,"passed_time":33.63147681,"remaining_time":15.04046983},
{"learn":[0.07708251563],"iteration":682,"passed_time":33.67378104,"remaining_time":14.98803724},
{"learn":[0.07701432311],"iteration":683,"passed_time":33.71974977,"remaining_time":14.93725757},
{"learn":[0.0769339707],"iteration":684,"passed_time":33.76900857,"remaining_time":14.88794247},
{"learn":[0.07681534885],"iteration":685,"passed_time":33.81572255,"remaining_time":14.83751092},
{"learn":[0.07672226872],"iteration":686,"passed_time":33.86292047,"remaining_time":14.78730152},
{"learn":[0.07664774342],"iteration":687,"passed_time":33.91083006,"remaining_time":14.73741016},
{"learn":[0.07659014913],"iteration":688,"passed_time":33.95932928,"remaining_time":14.68777957},
{"learn":[0.07652936803],"iteration":689,"passed_time":34.00173735,"remaining_time":14.63553042},
{"learn":[0.07630287173],"iteration":690,"passed_time":34.04395477,"remaining_time":14.58322809},
{"learn":[0.07618800767],"iteration":691,"passed_time":34.091688,"remaining_time":14.5333063},
{"learn":[0.07607235356],"iteration":692,"passed_time":34.14364512,"remaining_time":14.48518278},
{"learn":[0.07595574418],"iteration":693,"passed_time":34.1893827,"remaining_time":14.43442238},
{"learn":[0.07585916111],"iteration":694,"passed_time":34.23763611,"remaining_time":14.38473345},
{"learn":[0.07574115212],"iteration":695,"passed_time":34.28277773,"remaining_time":14.33374759},
{"learn":[0.0756839324],"iteration":696,"passed_time":34.32749978,"remaining_time":14.28260393},
{"learn":[0.07563610041],"iteration":697,"passed_time":34.37299912,"remaining_time":14.2318005},
{"learn":[0.07551824746],"iteration":698,"passed_time":34.41897452,"remaining_time":14.18120839},
{"learn":[0.07542269984],"iteration":699,"passed_time":34.46623929,"remaining_time":14.13115811},
{"learn":[0.07534378814],"iteration":700,"passed_time":34.50940895,"remaining_time":14.07944502},
{"learn":[0.07522847584],"iteration":701,"passed_time":34.56257498,"remaining_time":14.03181463},
{"learn":[0.07513840858],"iteration":702,"passed_time":34.61452591,"remaining_time":13.98367761},
{"learn":[0.07510583098],"iteration":703,"passed_time":34.65992833,"remaining_time":13.93289733},
{"learn":[0.07504841636],"iteration":704,"passed_time":34.70807975,"remaining_time":13.8832319},
{"learn":[0.07494725744],"iteration":705,"passed_time":34.75646913,"remaining_time":13.83366548},
{"learn":[0.0748743297],"iteration":706,"passed_time":34.80505343,"remaining_time":13.78417958},
{"learn":[0.07478175499],"iteration":707,"passed_time":34.85135508,"remaining_time":13.73379671},
{"learn":[0.07466329248],"iteration":708,"passed_time":34.89988757,"remaining_time":13.68430006},
{"learn":[0.07456423959],"iteration":709,"passed_time":34.94717705,"remaining_time":13.63432119},
{"learn":[0.07440751718],"iteration":710,"passed_time":34.99207748,"remaining_time":13.58342248},
{"learn":[0.07437328673],"iteration":711,"passed_time":35.04251464,"remaining_time":13.53467911},
{"learn":[0.07408927977],"iteration":712,"passed_time":35.09399394,"remaining_time":13.48633147},
{"learn":[0.07397004929],"iteration":713,"passed_time":35.13849692,"remaining_time":13.43530765},
{"learn":[0.07390829809],"iteration":714,"passed_time":35.18697514,"remaining_time":13.38581432},
{"learn":[0.07383372169],"iteration":715,"passed_time":35.22981044,"remaining_time":13.33418803},
{"learn":[0.07375095596],"iteration":716,"passed_time":35.27657633,"remaining_time":13.2840664},
{"learn":[0.07363986763],"iteration":717,"passed_time":35.32537011,"remaining_time":13.23471387},
{"learn":[0.0735679153],"iteration":718,"passed_time":35.37100127,"remaining_time":13.18418406},
{"learn":[0.07350824019],"iteration":719,"passed_time":35.41861037,"remaining_time":13.13440135},
{"learn":[0.0734210863],"iteration":720,"passed_time":35.46818498,"remaining_time":13.0853498},
{"learn":[0.07334874178],"iteration":721,"passed_time":35.51771443,"remaining_time":13.03628023},
{"learn":[0.07325869057],"iteration":722,"passed_time":35.56243345,"remaining_time":12.98545288},
{"learn":[0.07315806523],"iteration":723,"passed_time":35.61041526,"remaining_time":12.93582764},
{"learn":[0.07309314384],"iteration":724,"passed_time":35.65148966,"remaining_time":12.88371075},
{"learn":[0.07304553725],"iteration":725,"passed_time":35.7008635,"remaining_time":12.83460795},
{"learn":[0.07302776647],"iteration":726,"passed_time":35.75114713,"remaining_time":12.78582979},
{"learn":[0.07292304221],"iteration":727,"passed_time":35.80003679,"remaining_time":12.73655155},
{"learn":[0.0728697115],"iteration":728,"passed_time":35.84560331,"remaining_time":12.68609829},
{"learn":[0.0727899572],"iteration":729,"passed_time":35.8949323,"remaining_time":12.63698301},
{"learn":[0.07269718741],"iteration":730,"passed_time":35.9417499,"remaining_time":12.58698765},
{"learn":[0.0726070983],"iteration":731,"passed_time":35.99269971,"remaining_time":12.53844047},
{"learn":[0.07257458999],"iteration":732,"passed_time":36.0351058,"remaining_time":12.48692616},
{"learn":[0.07238412425],"iteration":733,"passed_time":36.07866115,"remaining_time":12.43583279},
{"learn":[0.0723098215],"iteration":734,"passed_time":36.12810026,"remaining_time":12.38677723},
{"learn":[0.07226748554],"iteration":735,"passed_time":36.17552354,"remaining_time":12.33703316},
{"learn":[0.07219472935],"iteration":736,"passed_time":36.22349835,"remaining_time":12.28748248},
{"learn":[0.07208066503],"iteration":737,"passed_time":36.27412299,"remaining_time":12.23883012},
{"learn":[0.0720361313],"iteration":738,"passed_time":36.32514707,"remaining_time":12.19030646},
{"learn":[0.07193137562],"iteration":739,"passed_time":36.37086684,"remaining_time":12.14000555},
{"learn":[0.07185074215],"iteration":740,"passed_time":36.42090325,"remaining_time":12.09115007},
{"learn":[0.07177242487],"iteration":741,"passed_time":36.4679504,"remaining_time":12.04130438},
{"learn":[0.07172249477],"iteration":742,"passed_time":36.51368557,"remaining_time":11.99103537},
{"learn":[0.07144421771],"iteration":743,"passed_time":36.55789763,"remaining_time":11.94028108},
{"learn":[0.07136488098],"iteration":744,"passed_time":36.60944049,"remaining_time":11.89192564},
{"learn":[0.07127766944],"iteration":745,"passed_time":36.65781391,"remaining_time":11.84253774},
{"learn":[0.07125443473],"iteration":746,"passed_time":36.70349067,"remaining_time":11.79228616},
{"learn":[0.07108803533],"iteration":747,"passed_time":36.75264468,"remaining_time":11.74315786},
{"learn":[0.07103214369],"iteration":748,"passed_time":36.8024785,"remaining_time":11.69424551},
{"learn":[0.07093214111],"iteration":749,"passed_time":36.85277585,"remaining_time":11.64547717},
{"learn":[0.07082865013],"iteration":750,"passed_time":36.89720535,"remaining_time":11.5948608},
{"learn":[0.07070777323],"iteration":751,"passed_time":36.94071988,"remaining_time":11.54397496},
{"learn":[0.07044760184],"iteration":752,"passed_time":36.9812416,"remaining_time":11.49217866},
{"learn":[0.07029731617],"iteration":753,"passed_time":37.0302175,"remaining_time":11.44302477},
{"learn":[0.07018402287],"iteration":754,"passed_time":37.07649793,"remaining_time":11.39304307},
{"learn":[0.0701264735],"iteration":755,"passed_time":37.13026793,"remaining_time":11.34535965},
{"learn":[0.07002601227],"iteration":756,"passed_time":37.17972591,"remaining_time":11.29635001},
{"learn":[0.06990262405],"iteration":757,"passed_time":37.22398941,"remaining_time":11.24576989},
{"learn":[0.06976680951],"iteration":758,"passed_time":37.27592961,"remaining_time":11.19751245},
{"learn":[0.06972630362],"iteration":759,"passed_time":37.32428347,"remaining_time":11.14817414},
{"learn":[0.06965792598],"iteration":760,"passed_time":37.37234407,"remaining_time":11.09875133},
{"learn":[0.06961833313],"iteration":761,"passed_time":37.41652234,"remaining_time":11.04818573},
{"learn":[0.06943963466],"iteration":762,"passed_time":37.46492207,"remaining_time":10.99887621},
{"learn":[0.06938692755],"iteration":763,"passed_time":37.51320766,"remaining_time":10.94953574},
{"learn":[0.06930971201],"iteration":764,"passed_time":37.56724731,"remaining_time":10.90186785},
{"learn":[0.06925456155],"iteration":765,"passed_time":37.61492072,"remaining_time":10.85234658},
{"learn":[0.06918499275],"iteration":766,"passed_time":37.66157028,"remaining_time":10.80253646},
{"learn":[0.06911994846],"iteration":767,"passed_time":37.70283288,"remaining_time":10.75119844},
{"learn":[0.06905052799],"iteration":768,"passed_time":37.74904953,"remaining_time":10.70129102},
{"learn":[0.06901590618],"iteration":769,"passed_time":37.79759848,"remaining_time":10.65205048},
{"learn":[0.06893500838],"iteration":770,"passed_time":37.83861,"remaining_time":10.60070008},
{"learn":[0.0688665575],"iteration":771,"passed_time":37.89023213,"remaining_time":10.55233149},
{"learn":[0.06881041189],"iteration":772,"passed_time":37.93993194,"remaining_time":10.5034223},
{"learn":[0.06856863846],"iteration":773,"passed_time":37.98467387,"remaining_time":10.45314669},
{"learn":[0.06848844882],"iteration":774,"passed_time":38.03688479,"remaining_time":10.40492849},
{"learn":[0.06843321893],"iteration":775,"passed_time":38.08524812,"remaining_time":10.3556538},
{"learn":[0.06833003393],"iteration":776,"passed_time":38.13032603,"remaining_time":10.30549352},
{"learn":[0.06828443427],"iteration":777,"passed_time":38.17805736,"remaining_time":10.25605911},
{"learn":[0.06817830313],"iteration":778,"passed_time":38.22405764,"remaining_time":10.20616687},
{"learn":[0.06816376404],"iteration":779,"passed_time":38.22683999,"remaining_time":10.14481523},
{"learn":[0.06810195043],"iteration":780,"passed_time":38.27362054,"remaining_time":10.09521873},
{"learn":[0.06801182967],"iteration":781,"passed_time":38.32185495,"remaining_time":10.04601057},
{"learn":[0.06791163311],"iteration":782,"passed_time":38.36886247,"remaining_time":9.99648524},
{"learn":[0.06782814485],"iteration":783,"passed_time":38.41677757,"remaining_time":9.947201336},
{"learn":[0.06777477994],"iteration":784,"passed_time":38.46096784,"remaining_time":9.896962424},
{"learn":[0.0677048513],"iteration":785,"passed_time":38.50564872,"remaining_time":9.846864367},
{"learn":[0.06764664284],"iteration":786,"passed_time":38.55549187,"remaining_time":9.798091961},
{"learn":[0.06757742182],"iteration":787,"passed_time":38.60395743,"remaining_time":9.748968945},
{"learn":[0.06748987161],"iteration":788,"passed_time":38.65165669,"remaining_time":9.699655292},
{"learn":[0.06741097432],"iteration":789,"passed_time":38.70342563,"remaining_time":9.651360567},
{"learn":[0.06735913171],"iteration":790,"passed_time":38.75265771,"remaining_time":9.602428458},
{"learn":[0.06717309377],"iteration":791,"passed_time":38.79983833,"remaining_time":9.552990499},
{"learn":[0.06706649665],"iteration":792,"passed_time":38.84020838,"remaining_time":9.501892088},
{"learn":[0.06699820113],"iteration":793,"passed_time":38.8933764,"remaining_time":9.453931542},
{"learn":[0.06693385215],"iteration":794,"passed_time":38.94433725,"remaining_time":9.405424845},
{"learn":[0.06686466332],"iteration":795,"passed_time":38.98917189,"remaining_time":9.355441998},
{"learn":[0.06680294781],"iteration":796,"passed_time":39.03665922,"remaining_time":9.306104456},
{"learn":[0.066753917],"iteration":797,"passed_time":39.07938531,"remaining_time":9.255643889},
{"learn":[0.06670738916],"iteration":798,"passed_time":39.09593451,"remaining_time":9.199043413},
{"learn":[0.06665918948],"iteration":799,"passed_time":39.1456937,"remaining_time":9.150305902},
{"learn":[0.06658298366],"iteration":800,"passed_time":39.19230292,"remaining_time":9.100834385},
{"learn":[0.06652741372],"iteration":801,"passed_time":39.24151422,"remaining_time":9.051970237},
{"learn":[0.06643829363],"iteration":802,"passed_time":39.28666597,"remaining_time":9.002175016},
{"learn":[0.06639242995],"iteration":803,"passed_time":39.33552161,"remaining_time":8.953234397},
{"learn":[0.06635353452],"iteration":804,"passed_time":39.38721175,"remaining_time":8.904934831},
{"learn":[0.06631788341],"iteration":805,"passed_time":39.43861728,"remaining_time":8.856562938},
{"learn":[0.06625684982],"iteration":806,"passed_time":39.489137,"remaining_time":8.807985948},
{"learn":[0.06604784599],"iteration":807,"passed_time":39.53676298,"remaining_time":8.758763085},
{"learn":[0.0659812599],"iteration":808,"passed_time":39.5871441,"remaining_time":8.71015037},
{"learn":[0.06593961175],"iteration":809,"passed_time":39.62985946,"remaining_time":8.659858179},
{"learn":[0.06588363206],"iteration":810,"passed_time":39.67684511,"remaining_time":8.610511392},
{"learn":[0.06583542049],"iteration":811,"passed_time":39.72252809,"remaining_time":8.560889674},
{"learn":[0.06578553056],"iteration":812,"passed_time":39.76625758,"remaining_time":8.510859556},
{"learn":[0.06562827001],"iteration":813,"passed_time":39.81485301,"remaining_time":8.46187908},
{"learn":[0.06554743876],"iteration":814,"passed_time":39.86045196,"remaining_time":8.412267162},
{"learn":[0.06538821084],"iteration":815,"passed_time":39.90587113,"remaining_time":8.362627406},
{"learn":[0.06534138485],"iteration":816,"passed_time":39.94953321,"remaining_time":8.312632368},
{"learn":[0.06530462152],"iteration":817,"passed_time":40.00043305,"remaining_time":8.264148149},
{"learn":[0.06524538327],"iteration":818,"passed_time":40.04716743,"remaining_time":8.214803575},
{"learn":[0.06517784485],"iteration":819,"passed_time":40.08779759,"remaining_time":8.164222192},
{"learn":[0.06512023042],"iteration":820,"passed_time":40.14150338,"remaining_time":8.116308845},
{"learn":[0.0650697419],"iteration":821,"passed_time":40.18887358,"remaining_time":8.06710966},
{"learn":[0.06502751816],"iteration":822,"passed_time":40.24106894,"remaining_time":8.018876435},
{"learn":[0.06491517014],"iteration":823,"passed_time":40.29211865,"remaining_time":7.970406966},
{"learn":[0.0648685082],"iteration":824,"passed_time":40.34282328,"remaining_time":7.921863481},
{"learn":[0.0647943944],"iteration":825,"passed_time":40.38675401,"remaining_time":7.871994426},
{"learn":[0.06468817403],"iteration":826,"passed_time":40.43303214,"remaining_time":7.822593884},
{"learn":[0.06464274323],"iteration":827,"passed_time":40.47923731,"remaining_time":7.773186874},
{"learn":[0.06450432282],"iteration":828,"passed_time":40.52327263,"remaining_time":7.723374036},
{"learn":[0.06442092774],"iteration":829,"passed_time":40.56811439,"remaining_time":7.673727662},
{"learn":[0.06435818117],"iteration":830,"passed_time":40.61517386,"remaining_time":7.624509173},
{"learn":[0.06424254967],"iteration":831,"passed_time":40.66337716,"remaining_time":7.575508966},
{"learn":[0.06417589062],"iteration":832,"passed_time":40.71239078,"remaining_time":7.52666048},
{"learn":[0.06414829369],"iteration":833,"passed_time":40.75615078,"remaining_time":7.476847805},
{"learn":[0.06411175934],"iteration":834,"passed_time":40.80206368,"remaining_time":7.427441531},
{"learn":[0.06397540309],"iteration":835,"passed_time":40.8527141,"remaining_time":7.378899317},
{"learn":[0.06384650541],"iteration":836,"passed_time":40.89967269,"remaining_time":7.329690446},
{"learn":[0.06380846295],"iteration":837,"passed_time":40.94821857,"remaining_time":7.280769173},
{"learn":[0.06376505411],"iteration":838,"passed_time":40.99651449,"remaining_time":7.231804702},
{"learn":[0.06374953844],"iteration":839,"passed_time":41.04580664,"remaining_time":7.183016162},
{"learn":[0.06366197225],"iteration":840,"passed_time":41.09258953,"remaining_time":7.133790809},
{"learn":[0.06363510507],"iteration":841,"passed_time":41.14165905,"remaining_time":7.084965038},
{"learn":[0.06358898286],"iteration":842,"passed_time":41.18691718,"remaining_time":7.035487631},
{"learn":[0.06350618586],"iteration":843,"passed_time":41.23493442,"remaining_time":6.986487703},
{"learn":[0.06349401957],"iteration":844,"passed_time":41.28746309,"remaining_time":6.938248235},
{"learn":[0.06340628939],"iteration":845,"passed_time":41.33316261,"remaining_time":6.888860435},
{"learn":[0.06338112345],"iteration":846,"passed_time":41.38109838,"remaining_time":6.839850972},
{"learn":[0.0633420686],"iteration":847,"passed_time":41.42749302,"remaining_time":6.790591426},
{"learn":[0.06319781718],"iteration":848,"passed_time":41.47726003,"remaining_time":6.741886789},
{"learn":[0.06311756981],"iteration":849,"passed_time":41.52284531,"remaining_time":6.692505656},
{"learn":[0.06301608082],"iteration":850,"passed_time":41.57319951,"remaining_time":6.643895574},
{"learn":[0.06296191271],"iteration":851,"passed_time":41.62026264,"remaining_time":6.594759925},
{"learn":[0.06285922853],"iteration":852,"passed_time":41.66887565,"remaining_time":6.545872611},
{"learn":[0.0628156384],"iteration":853,"passed_time":41.71860108,"remaining_time":6.497159184},
{"learn":[0.06269583091],"iteration":854,"passed_time":41.76693648,"remaining_time":6.44822879},
{"learn":[0.06264301342],"iteration":855,"passed_time":41.81495765,"remaining_time":6.399251696},
{"learn":[0.06256321242],"iteration":856,"passed_time":41.85985425,"remaining_time":6.349802862},
{"learn":[0.06249411299],"iteration":857,"passed_time":41.90848107,"remaining_time":6.300925475},
{"learn":[0.06247584591],"iteration":858,"passed_time":41.9575975,"remaining_time":6.25212163},
{"learn":[0.06243742941],"iteration":859,"passed_time":42.00974894,"remaining_time":6.20376525},
{"learn":[0.0623727457],"iteration":860,"passed_time":42.05870834,"remaining_time":6.154932928},
{"learn":[0.06234072906],"iteration":861,"passed_time":42.10004054,"remaining_time":6.104994277},
{"learn":[0.06232332456],"iteration":862,"passed_time":42.14965527,"remaining_time":6.056265648},
{"learn":[0.06223512802],"iteration":863,"passed_time":42.19351131,"remaining_time":6.006715152},
{"learn":[0.06217866049],"iteration":864,"passed_time":42.24416642,"remaining_time":5.958136766},
{"learn":[0.06211815916],"iteration":865,"passed_time":42.2926909,"remaining_time":5.909255888},
{"learn":[0.06206188697],"iteration":866,"passed_time":42.3439787,"remaining_time":5.860758298},
{"learn":[0.06205288265],"iteration":867,"passed_time":42.3591781,"remaining_time":5.807306675},
{"learn":[0.06192903231],"iteration":868,"passed_time":42.40283602,"remaining_time":5.757807423},
{"learn":[0.06187096113],"iteration":869,"passed_time":42.45138437,"remaining_time":5.708979278},
{"learn":[0.0618154009],"iteration":870,"passed_time":42.49304014,"remaining_time":5.659233819},
{"learn":[0.06174424518],"iteration":871,"passed_time":42.53701152,"remaining_time":5.609812299},
{"learn":[0.06172739487],"iteration":872,"passed_time":42.58594296,"remaining_time":5.561050971},
{"learn":[0.06167241048],"iteration":873,"passed_time":42.63117881,"remaining_time":5.511811448},
{"learn":[0.06153193584],"iteration":874,"passed_time":42.68107738,"remaining_time":5.463177904},
{"learn":[0.0614749581],"iteration":875,"passed_time":42.72439061,"remaining_time":5.413707029},
{"learn":[0.06141226398],"iteration":876,"passed_time":42.77152873,"remaining_time":5.364729944},
{"learn":[0.0613675531],"iteration":877,"passed_time":42.81554337,"remaining_time":5.315369279},
{"learn":[0.06123113267],"iteration":878,"passed_time":42.86086479,"remaining_time":5.26618134},
{"learn":[0.0611268818],"iteration":879,"passed_time":42.90576052,"remaining_time":5.216950427},
{"learn":[0.0609475578],"iteration":880,"passed_time":42.95043403,"remaining_time":5.167702618},
{"learn":[0.06092346594],"iteration":881,"passed_time":42.99941729,"remaining_time":5.118978248},
{"learn":[0.06089744972],"iteration":882,"passed_time":43.04511662,"remaining_time":5.06986651},
{"learn":[0.06082856563],"iteration":883,"passed_time":43.09700058,"remaining_time":5.021483099},
{"learn":[0.06074675843],"iteration":884,"passed_time":43.14479241,"remaining_time":4.972620142},
{"learn":[0.06069512035],"iteration":885,"passed_time":43.18829895,"remaining_time":4.9232711},
{"learn":[0.06065141382],"iteration":886,"passed_time":43.22944485,"remaining_time":4.873669093},
{"learn":[0.06057386092],"iteration":887,"passed_time":43.27844188,"remaining_time":4.824961426},
{"learn":[0.06041708227],"iteration":888,"passed_time":43.32653186,"remaining_time":4.776153119},
{"learn":[0.06040147698],"iteration":889,"passed_time":43.3738643,"remaining_time":4.727263862},
{"learn":[0.06036817143],"iteration":890,"passed_time":43.42230831,"remaining_time":4.678497865},
{"learn":[0.06034523959],"iteration":891,"passed_time":43.46697356,"remaining_time":4.629330143},
{"learn":[0.06031557515],"iteration":892,"passed_time":43.52029261,"remaining_time":4.581083432},
{"learn":[0.06021228941],"iteration":893,"passed_time":43.57078304,"remaining_time":4.532531122},
{"learn":[0.06015882726],"iteration":894,"passed_time":43.61536457,"remaining_time":4.483367084},
{"learn":[0.06011237664],"iteration":895,"passed_time":43.66582979,"remaining_time":4.434810839},
{"learn":[0.06004315422],"iteration":896,"passed_time":43.70894768,"remaining_time":4.385513145},
{"learn":[0.05989849613],"iteration":897,"passed_time":43.75314393,"remaining_time":4.336336091},
{"learn":[0.05982394978],"iteration":898,"passed_time":43.80402621,"remaining_time":4.28782459},
{"learn":[0.05977449174],"iteration":899,"passed_time":43.8506295,"remaining_time":4.238894185},
{"learn":[0.05973101167],"iteration":900,"passed_time":43.89963491,"remaining_time":4.190198227},
{"learn":[0.05968097176],"iteration":901,"passed_time":43.94715846,"remaining_time":4.141361939},
{"learn":[0.05959996901],"iteration":902,"passed_time":43.9859172,"remaining_time":4.091713228},
{"learn":[0.05955169881],"iteration":903,"passed_time":44.03211724,"remaining_time":4.042771826},
{"learn":[0.05948699504],"iteration":904,"passed_time":44.07998296,"remaining_time":3.993987406},
{"learn":[0.05942274866],"iteration":905,"passed_time":44.1234325,"remaining_time":3.94481019},
{"learn":[0.05927225413],"iteration":906,"passed_time":44.16435039,"remaining_time":3.895422306},
{"learn":[0.05922786154],"iteration":907,"passed_time":44.21008822,"remaining_time":3.846472434},
{"learn":[0.05920454259],"iteration":908,"passed_time":44.25390386,"remaining_time":3.797364687},
{"learn":[0.0591077627],"iteration":909,"passed_time":44.30006191,"remaining_time":3.748466777},
{"learn":[0.05905484264],"iteration":910,"passed_time":44.34796127,"remaining_time":3.69972015},
{"learn":[0.05902237804],"iteration":911,"passed_time":44.39467027,"remaining_time":3.650877489},
{"learn":[0.05895650556],"iteration":912,"passed_time":44.44660275,"remaining_time":3.602462874},
{"learn":[0.05891905809],"iteration":913,"passed_time":44.49384589,"remaining_time":3.553666028},
{"learn":[0.05887848363],"iteration":914,"passed_time":44.54174412,"remaining_time":3.504924128},
{"learn":[0.05884103446],"iteration":915,"passed_time":44.58546314,"remaining_time":3.455860134},
{"learn":[0.05878295925],"iteration":916,"passed_time":44.63699168,"remaining_time":3.407403945},
{"learn":[0.05874446542],"iteration":917,"passed_time":44.69025375,"remaining_time":3.35907136},
{"learn":[0.05869263546],"iteration":918,"passed_time":44.74121952,"remaining_time":3.310558137},
{"learn":[0.05866785702],"iteration":919,"passed_time":44.79225358,"remaining_time":3.262044554},
{"learn":[0.05860819802],"iteration":920,"passed_time":44.83882537,"remaining_time":3.213205727},
{"learn":[0.05855756171],"iteration":921,"passed_time":44.88557711,"remaining_time":3.164384503},
{"learn":[0.05852884365],"iteration":922,"passed_time":44.9363608,"remaining_time":3.115847336},
{"learn":[0.05848086123],"iteration":923,"passed_time":44.98302624,"remaining_time":3.067024516},
{"learn":[0.0584158657],"iteration":924,"passed_time":45.03476481,"remaining_time":3.018546398},
{"learn":[0.05828840119],"iteration":925,"passed_time":45.08409641,"remaining_time":2.969902679},
{"learn":[0.05824926111],"iteration":926,"passed_time":45.13022892,"remaining_time":2.921050416},
{"learn":[0.05821178321],"iteration":927,"passed_time":45.17952228,"remaining_time":2.872404973},
{"learn":[0.05813091967],"iteration":928,"passed_time":45.23095403,"remaining_time":2.82389164},
{"learn":[0.05806976306],"iteration":929,"passed_time":45.2755152,"remaining_time":2.774950932},
{"learn":[0.05802831316],"iteration":930,"passed_time":45.32253705,"remaining_time":2.726167642},
{"learn":[0.05798439909],"iteration":931,"passed_time":45.37574992,"remaining_time":2.677753483},
{"learn":[0.05792537426],"iteration":932,"passed_time":45.42119973,"remaining_time":2.628879727},
{"learn":[0.05784522443],"iteration":933,"passed_time":45.47221505,"remaining_time":2.58032912},
{"learn":[0.05776142901],"iteration":934,"passed_time":45.52197858,"remaining_time":2.531703621},
{"learn":[0.05768696805],"iteration":935,"passed_time":45.57042487,"remaining_time":2.483003919},
{"learn":[0.05764338119],"iteration":936,"passed_time":45.61973953,"remaining_time":2.434351095},
{"learn":[0.05754798407],"iteration":937,"passed_time":45.66670537,"remaining_time":2.385574161},
{"learn":[0.05750422031],"iteration":938,"passed_time":45.71699745,"remaining_time":2.336971115},
{"learn":[0.05740388091],"iteration":939,"passed_time":45.76106383,"remaining_time":2.288053192},
{"learn":[0.05722997229],"iteration":940,"passed_time":45.80470584,"remaining_time":2.239124834},
{"learn":[0.05713608748],"iteration":941,"passed_time":45.85533216,"remaining_time":2.190541345},
{"learn":[0.05710957717],"iteration":942,"passed_time":45.90229828,"remaining_time":2.141782741},
{"learn":[0.05709719384],"iteration":943,"passed_time":45.94679014,"remaining_time":2.092915229},
{"learn":[0.0570623558],"iteration":944,"passed_time":45.99030004,"remaining_time":2.044013335},
{"learn":[0.05700073959],"iteration":945,"passed_time":46.03653332,"remaining_time":1.995240873},
{"learn":[0.05688423882],"iteration":946,"passed_time":46.0841503,"remaining_time":1.94653222},
{"learn":[0.05682610324],"iteration":947,"passed_time":46.13210919,"remaining_time":1.897839935},
{"learn":[0.05675959313],"iteration":948,"passed_time":46.17928224,"remaining_time":1.849117729},
{"learn":[0.05664473127],"iteration":949,"passed_time":46.22902657,"remaining_time":1.800498929},
{"learn":[0.05658988863],"iteration":950,"passed_time":46.28196686,"remaining_time":1.751998746},
{"learn":[0.05652845009],"iteration":951,"passed_time":46.33879724,"remaining_time":1.703632251},
{"learn":[0.05645399887],"iteration":952,"passed_time":46.38286626,"remaining_time":1.65479271},
{"learn":[0.05638203778],"iteration":953,"passed_time":46.43106434,"remaining_time":1.606105999},
{"learn":[0.05633228812],"iteration":954,"passed_time":46.48156312,"remaining_time":1.557497403},
{"learn":[0.05625714366],"iteration":955,"passed_time":46.53155913,"remaining_time":1.508868549},
{"learn":[0.05618658666],"iteration":956,"passed_time":46.5789501,"remaining_time":1.460155175},
{"learn":[0.05611475736],"iteration":957,"passed_time":46.62339225,"remaining_time":1.411355298},
{"learn":[0.05611258037],"iteration":958,"passed_time":46.62547273,"remaining_time":1.361327671},
{"learn":[0.05596760796],"iteration":959,"passed_time":46.67016146,"remaining_time":1.312598291},
{"learn":[0.05586882342],"iteration":960,"passed_time":46.72051587,"remaining_time":1.264030606},
{"learn":[0.05580128486],"iteration":961,"passed_time":46.76883215,"remaining_time":1.215406241},
{"learn":[0.05566449661],"iteration":962,"passed_time":46.81826775,"remaining_time":1.166810411},
{"learn":[0.0555977576],"iteration":963,"passed_time":46.86809984,"remaining_time":1.118222299},
{"learn":[0.055563108],"iteration":964,"passed_time":46.91395066,"remaining_time":1.069540844},
{"learn":[0.05550856768],"iteration":965,"passed_time":46.9617236,"remaining_time":1.020907035},
{"learn":[0.05547469122],"iteration":966,"passed_time":47.01034507,"remaining_time":0.9722925558},
{"learn":[0.05534641531],"iteration":967,"passed_time":47.06068006,"remaining_time":0.9237116954},
{"learn":[0.05529722208],"iteration":968,"passed_time":47.10808968,"remaining_time":0.8750728734},
{"learn":[0.05521945466],"iteration":969,"passed_time":47.15645846,"remaining_time":0.8264533956},
{"learn":[0.05514431787],"iteration":970,"passed_time":47.19712144,"remaining_time":0.7777074594},
{"learn":[0.05505896674],"iteration":971,"passed_time":47.24835165,"remaining_time":0.7291412292},
{"learn":[0.0550477255],"iteration":972,"passed_time":47.25478412,"remaining_time":0.6799249514},
{"learn":[0.05500381511],"iteration":973,"passed_time":47.29879923,"remaining_time":0.6312981417},
{"learn":[0.05496592167],"iteration":974,"passed_time":47.34390078,"remaining_time":0.5826941635},
{"learn":[0.05489252225],"iteration":975,"passed_time":47.38998642,"remaining_time":0.5341084535},
{"learn":[0.05482151314],"iteration":976,"passed_time":47.43899789,"remaining_time":0.4855578085},
{"learn":[0.05473369951],"iteration":977,"passed_time":47.49291719,"remaining_time":0.4370513852},
{"learn":[0.05461085996],"iteration":978,"passed_time":47.54310629,"remaining_time":0.3885034222},
{"learn":[0.05456126404],"iteration":979,"passed_time":47.58891509,"remaining_time":0.3399208221},
{"learn":[0.05452861129],"iteration":980,"passed_time":47.63172352,"remaining_time":0.2913255261},
{"learn":[0.05447933855],"iteration":981,"passed_time":47.68373149,"remaining_time":0.2427888569},
{"learn":[0.05436945038],"iteration":982,"passed_time":47.73699667,"remaining_time":0.1942502408},
{"learn":[0.05429947394],"iteration":983,"passed_time":47.78852222,"remaining_time":0.1456967141},
{"learn":[0.05423409484],"iteration":984,"passed_time":47.84171126,"remaining_time":0.09714053049},
{"learn":[0.05406212027],"iteration":985,"passed_time":47.89367489,"remaining_time":0.04857370679},
{"learn":[0.05402681849],"iteration":986,"passed_time":47.93601845,"remaining_time":0}
]}